Workbook

Sheet Ringkasan
A1: Kode | B1: Nama Perusahaan | C1: Penutupan | D1: =IFERROR(__xludf.DUMMYFUNCTION("""Last Update: "" & TEXT(NOW() - GOOGLEFINANCE(""IDX:BBCA"",""datadelay"")/1440, ""dddd, yyyymmdd HH:mm"")"),"Last Update: Minggu, 20260614 14:19") -> Last Update: Minggu, 20260614 14:19 | E1: Index | F1: Index Expired | G1: ∑i ≥ 7 | H1: PER | I1: PBV | J1: ROE | K1: ROA | L1: DER | M1: NPM | N1: NIM | O1: CAR | P1: LDR | Q1: NPL | R1: BOPO | S1: CIR | T1: LAR | U1: Sebelumnya | V1: %Change | W1: Open | X1: High | Y1: Low | Z1: Volume | AA1: Industry | AB1: Sektor
A2: AADI | B2: {=VLOOKUP(A2,{Metrik!$C$2:$C$998,Metrik!$B$2:$B$998},2,0)} -> Adaro Andalan Indonesia Tbk. | C2: =IFERROR(__xludf.DUMMYFUNCTION("GOOGLEFINANCE(""IDX:""&A2,""price"")"),8650.0) -> 8650 | D2: =IFERROR(__xludf.DUMMYFUNCTION("IF(A2="""","""", SPARKLINE( INDEX( GOOGLEFINANCE(""IDX:""&A2,""close"",TODAY()-365,TODAY()), ,2 ), {""linewidth"",1} )) "),"#N/A") -> #N/A | E2: IDX80 | F2: 31 Juli 2026 | G2: =COUNTIFS($B$2:$B$1937,B2,$E$2:$E$1937,"<>") -> 9 | H2: =VLOOKUP(A2,Metrik!$C$2:$Y$959,8,0) -> 5.5 | I2: =VLOOKUP(A2,Metrik!$C$2:$Y$959,9,0) -> 1 | J2: =VLOOKUP(A2,Metrik!$C$2:$Y$959,10,0) -> 18.6 | K2: =VLOOKUP(A2,Metrik!$C$2:$Y$959,11,0) -> 12.2 | L2: =VLOOKUP(A2,Metrik!$C$2:$Y$959,12,0) -> 0.53 | M2: =VLOOKUP(A2,Metrik!$C$2:$Y$959,19,0) -> 67.3 | U2: =IFERROR(__xludf.DUMMYFUNCTION("IFERROR(GOOGLEFINANCE(A2,""closeyest""),"""")"),8050.0) -> 8050 | V2: =IFERROR(__xludf.DUMMYFUNCTION("IFERROR(GOOGLEFINANCE(A2,""changepct""),"""")"),7.45) -> 7.45 | W2: =IFERROR(__xludf.DUMMYFUNCTION("IFERROR(GOOGLEFINANCE(A2,""priceopen""),"""")"),8100.0) -> 8100 | X2: =IFERROR(__xludf.DUMMYFUNCTION("IFERROR(GOOGLEFINANCE(A2,""high""),"""")"),8850.0) -> 8850 | Y2: =IFERROR(__xludf.DUMMYFUNCTION("IFERROR(GOOGLEFINANCE(A2,""low""),"""")"),8050.0) -> 8050 | Z2: =IFERROR(__xludf.DUMMYFUNCTION("IFERROR(GOOGLEFINANCE(A2,""volume""),"""")"),2.12622E7) -> 21262200 | AA2: =VLOOKUP(A2,Metrik!$C$2:$Y$959,5,0) -> Coal | AB2: =VLOOKUP(A2,Metrik!$C$2:$Y$959,3,0) -> Energy
A3: AADI | B3: {=VLOOKUP(A3,{Metrik!$C$2:$C$998,Metrik!$B$2:$B$998},2,0)} -> Adaro Andalan Indonesia Tbk. | C3: =IFERROR(__xludf.DUMMYFUNCTION("GOOGLEFINANCE(""IDX:""&A3,""price"")"),8650.0) -> 8650 | D3: =IFERROR(__xludf.DUMMYFUNCTION("IF(A3="""","""", SPARKLINE( INDEX( GOOGLEFINANCE(""IDX:""&A3,""close"",TODAY()-365,TODAY()), ,2 ), {""linewidth"",1} )) "),"#N/A") -> #N/A | E3: IDX30 | F3: 31 Juli 2026 | G3: =COUNTIFS($B$2:$B$1937,B3,$E$2:$E$1937,"<>") -> 9 | H3: =VLOOKUP(A3,Metrik!$C$2:$Y$959,8,0) -> 5.5 | I3: =VLOOKUP(A3,Metrik!$C$2:$Y$959,9,0) -> 1 | J3: =VLOOKUP(A3,Metrik!$C$2:$Y$959,10,0) -> 18.6 | K3: =VLOOKUP(A3,Metrik!$C$2:$Y$959,11,0) -> 12.2 | L3: =VLOOKUP(A3,Metrik!$C$2:$Y$959,12,0) -> 0.53 | M3: =VLOOKUP(A3,Metrik!$C$2:$Y$959,19,0) -> 67.3 | U3: =IFERROR(__xludf.DUMMYFUNCTION("IFERROR(GOOGLEFINANCE(A3,""closeyest""),"""")"),8050.0) -> 8050 | V3: =IFERROR(__xludf.DUMMYFUNCTION("IFERROR(GOOGLEFINANCE(A3,""changepct""),"""")"),7.45) -> 7.45 | W3: =IFERROR(__xludf.DUMMYFUNCTION("IFERROR(GOOGLEFINANCE(A3,""priceopen""),"""")"),8100.0) -> 8100 | X3: =IFERROR(__xludf.DUMMYFUNCTION("IFERROR(GOOGLEFINANCE(A3,""high""),"""")"),8850.0) -> 8850 | Y3: =IFERROR(__xludf.DUMMYFUNCTION("IFERROR(GOOGLEFINANCE(A3,""low""),"""")"),8050.0) -> 8050 | Z3: =IFERROR(__xludf.DUMMYFUNCTION("IFERROR(GOOGLEFINANCE(A3,""volume""),"""")"),2.12622E7) -> 21262200 | AA3: =VLOOKUP(A3,Metrik!$C$2:$Y$959,5,0) -> Coal | AB3: =VLOOKUP(A3,Metrik!$C$2:$Y$959,3,0) -> Energy
A4: AADI | B4: {=VLOOKUP(A4,{Metrik!$C$2:$C$998,Metrik!$B$2:$B$998},2,0)} -> Adaro Andalan Indonesia Tbk. | C4: =IFERROR(__xludf.DUMMYFUNCTION("GOOGLEFINANCE(""IDX:""&A4,""price"")"),8650.0) -> 8650 | D4: =IFERROR(__xludf.DUMMYFUNCTION("IF(A4="""","""", SPARKLINE( INDEX( GOOGLEFINANCE(""IDX:""&A4,""close"",TODAY()-365,TODAY()), ,2 ), {""linewidth"",1} )) "),"#N/A") -> #N/A | E4: LQ45 | F4: 31 Juli 2026 | G4: =COUNTIFS($B$2:$B$1937,B4,$E$2:$E$1937,"<>") -> 9 | H4: =VLOOKUP(A4,Metrik!$C$2:$Y$959,8,0) -> 5.5 | I4: =VLOOKUP(A4,Metrik!$C$2:$Y$959,9,0) -> 1 | J4: =VLOOKUP(A4,Metrik!$C$2:$Y$959,10,0) -> 18.6 | K4: =VLOOKUP(A4,Metrik!$C$2:$Y$959,11,0) -> 12.2 | L4: =VLOOKUP(A4,Metrik!$C$2:$Y$959,12,0) -> 0.53 | M4: =VLOOKUP(A4,Metrik!$C$2:$Y$959,19,0) -> 67.3 | U4: =IFERROR(__xludf.DUMMYFUNCTION("IFERROR(GOOGLEFINANCE(A4,""closeyest""),"""")"),8050.0) -> 8050 | V4: =IFERROR(__xludf.DUMMYFUNCTION("IFERROR(GOOGLEFINANCE(A4,""changepct""),"""")"),7.45) -> 7.45 | W4: =IFERROR(__xludf.DUMMYFUNCTION("IFERROR(GOOGLEFINANCE(A4,""priceopen""),"""")"),8100.0) -> 8100 | X4: =IFERROR(__xludf.DUMMYFUNCTION("IFERROR(GOOGLEFINANCE(A4,""high""),"""")"),8850.0) -> 8850 | Y4: =IFERROR(__xludf.DUMMYFUNCTION("IFERROR(GOOGLEFINANCE(A4,""low""),"""")"),8050.0) -> 8050 | Z4: =IFERROR(__xludf.DUMMYFUNCTION("IFERROR(GOOGLEFINANCE(A4,""volume""),"""")"),2.12622E7) -> 21262200 | AA4: =VLOOKUP(A4,Metrik!$C$2:$Y$959,5,0) -> Coal | AB4: =VLOOKUP(A4,Metrik!$C$2:$Y$959,3,0) -> Energy
A5: AADI | B5: {=VLOOKUP(A5,{Metrik!$C$2:$C$998,Metrik!$B$2:$B$998},2,0)} -> Adaro Andalan Indonesia Tbk. | C5: =IFERROR(__xludf.DUMMYFUNCTION("GOOGLEFINANCE(""IDX:""&A5,""price"")"),8650.0) -> 8650 | D5: =IFERROR(__xludf.DUMMYFUNCTION("IF(A5="""","""", SPARKLINE( INDEX( GOOGLEFINANCE(""IDX:""&A5,""close"",TODAY()-365,TODAY()), ,2 ), {""linewidth"",1} )) "),"#N/A") -> #N/A | E5: Kompas100 | F5: 31 Juli 2026 | G5: =COUNTIFS($B$2:$B$1937,B5,$E$2:$E$1937,"<>") -> 9 | H5: =VLOOKUP(A5,Metrik!$C$2:$Y$959,8,0) -> 5.5 | I5: =VLOOKUP(A5,Metrik!$C$2:$Y$959,9,0) -> 1 | J5: =VLOOKUP(A5,Metrik!$C$2:$Y$959,10,0) -> 18.6 | K5: =VLOOKUP(A5,Metrik!$C$2:$Y$959,11,0) -> 12.2 | L5: =VLOOKUP(A5,Metrik!$C$2:$Y$959,12,0) -> 0.53 | M5: =VLOOKUP(A5,Metrik!$C$2:$Y$959,19,0) -> 67.3 | U5: =IFERROR(__xludf.DUMMYFUNCTION("IFERROR(GOOGLEFINANCE(A5,""closeyest""),"""")"),8050.0) -> 8050 | V5: =IFERROR(__xludf.DUMMYFUNCTION("IFERROR(GOOGLEFINANCE(A5,""changepct""),"""")"),7.45) -> 7.45 | W5: =IFERROR(__xludf.DUMMYFUNCTION("IFERROR(GOOGLEFINANCE(A5,""priceopen""),"""")"),8100.0) -> 8100 | X5: =IFERROR(__xludf.DUMMYFUNCTION("IFERROR(GOOGLEFINANCE(A5,""high""),"""")"),8850.0) -> 8850 | Y5: =IFERROR(__xludf.DUMMYFUNCTION("IFERROR(GOOGLEFINANCE(A5,""low""),"""")"),8050.0) -> 8050 | Z5: =IFERROR(__xludf.DUMMYFUNCTION("IFERROR(GOOGLEFINANCE(A5,""volume""),"""")"),2.12622E7) -> 21262200 | AA5: =VLOOKUP(A5,Metrik!$C$2:$Y$959,5,0) -> Coal | AB5: =VLOOKUP(A5,Metrik!$C$2:$Y$959,3,0) -> Energy
A6: AADI | B6: {=VLOOKUP(A6,{Metrik!$C$2:$C$998,Metrik!$B$2:$B$998},2,0)} -> Adaro Andalan Indonesia Tbk. | C6: =IFERROR(__xludf.DUMMYFUNCTION("GOOGLEFINANCE(""IDX:""&A6,""price"")"),8650.0) -> 8650 | D6: =IFERROR(__xludf.DUMMYFUNCTION("IF(A6="""","""", SPARKLINE( INDEX( GOOGLEFINANCE(""IDX:""&A6,""close"",TODAY()-365,TODAY()), ,2 ), {""linewidth"",1} )) "),"#N/A") -> #N/A | E6: IDXV30 | F6: 4 Agustus 2026 | G6: =COUNTIFS($B$2:$B$1937,B6,$E$2:$E$1937,"<>") -> 9 | H6: =VLOOKUP(A6,Metrik!$C$2:$Y$959,8,0) -> 5.5 | I6: =VLOOKUP(A6,Metrik!$C$2:$Y$959,9,0) -> 1 | J6: =VLOOKUP(A6,Metrik!$C$2:$Y$959,10,0) -> 18.6 | K6: =VLOOKUP(A6,Metrik!$C$2:$Y$959,11,0) -> 12.2 | L6: =VLOOKUP(A6,Metrik!$C$2:$Y$959,12,0) -> 0.53 | M6: =VLOOKUP(A6,Metrik!$C$2:$Y$959,19,0) -> 67.3 | U6: =IFERROR(__xludf.DUMMYFUNCTION("IFERROR(GOOGLEFINANCE(A6,""closeyest""),"""")"),8050.0) -> 8050 | V6: =IFERROR(__xludf.DUMMYFUNCTION("IFERROR(GOOGLEFINANCE(A6,""changepct""),"""")"),7.45) -> 7.45 | W6: =IFERROR(__xludf.DUMMYFUNCTION("IFERROR(GOOGLEFINANCE(A6,""priceopen""),"""")"),8100.0) -> 8100 | X6: =IFERROR(__xludf.DUMMYFUNCTION("IFERROR(GOOGLEFINANCE(A6,""high""),"""")"),8850.0) -> 8850 | Y6: =IFERROR(__xludf.DUMMYFUNCTION("IFERROR(GOOGLEFINANCE(A6,""low""),"""")"),8050.0) -> 8050 | Z6: =IFERROR(__xludf.DUMMYFUNCTION("IFERROR(GOOGLEFINANCE(A6,""volume""),"""")"),2.12622E7) -> 21262200 | AA6: =VLOOKUP(A6,Metrik!$C$2:$Y$959,5,0) -> Coal | AB6: =VLOOKUP(A6,Metrik!$C$2:$Y$959,3,0) -> Energy
A7: AADI | B7: {=VLOOKUP(A7,{Metrik!$C$2:$C$998,Metrik!$B$2:$B$998},2,0)} -> Adaro Andalan Indonesia Tbk. | C7: =IFERROR(__xludf.DUMMYFUNCTION("GOOGLEFINANCE(""IDX:""&A7,""price"")"),8650.0) -> 8650 | D7: =IFERROR(__xludf.DUMMYFUNCTION("IF(A7="""","""", SPARKLINE( INDEX( GOOGLEFINANCE(""IDX:""&A7,""close"",TODAY()-365,TODAY()), ,2 ), {""linewidth"",1} )) "),"#N/A") -> #N/A | E7: MSCI Small Cap | F7: 12 Agustus 2026 | G7: =COUNTIFS($B$2:$B$1937,B7,$E$2:$E$1937,"<>") -> 9 | H7: =VLOOKUP(A7,Metrik!$C$2:$Y$959,8,0) -> 5.5 | I7: =VLOOKUP(A7,Metrik!$C$2:$Y$959,9,0) -> 1 | J7: =VLOOKUP(A7,Metrik!$C$2:$Y$959,10,0) -> 18.6 | K7: =VLOOKUP(A7,Metrik!$C$2:$Y$959,11,0) -> 12.2 | L7: =VLOOKUP(A7,Metrik!$C$2:$Y$959,12,0) -> 0.53 | M7: =VLOOKUP(A7,Metrik!$C$2:$Y$959,19,0) -> 67.3 | U7: =IFERROR(__xludf.DUMMYFUNCTION("IFERROR(GOOGLEFINANCE(A7,""closeyest""),"""")"),8050.0) -> 8050 | V7: =IFERROR(__xludf.DUMMYFUNCTION("IFERROR(GOOGLEFINANCE(A7,""changepct""),"""")"),7.45) -> 7.45 | W7: =IFERROR(__xludf.DUMMYFUNCTION("IFERROR(GOOGLEFINANCE(A7,""priceopen""),"""")"),8100.0) -> 8100 | X7: =IFERROR(__xludf.DUMMYFUNCTION("IFERROR(GOOGLEFINANCE(A7,""high""),"""")"),8850.0) -> 8850 | Y7: =IFERROR(__xludf.DUMMYFUNCTION("IFERROR(GOOGLEFINANCE(A7,""low""),"""")"),8050.0) -> 8050 | Z7: =IFERROR(__xludf.DUMMYFUNCTION("IFERROR(GOOGLEFINANCE(A7,""volume""),"""")"),2.12622E7) -> 21262200 | AA7: =VLOOKUP(A7,Metrik!$C$2:$Y$959,5,0) -> Coal | AB7: =VLOOKUP(A7,Metrik!$C$2:$Y$959,3,0) -> Energy
A8: AADI | B8: {=VLOOKUP(A8,{Metrik!$C$2:$C$998,Metrik!$B$2:$B$998},2,0)} -> Adaro Andalan Indonesia Tbk. | C8: =IFERROR(__xludf.DUMMYFUNCTION("GOOGLEFINANCE(""IDX:""&A8,""price"")"),8650.0) -> 8650 | D8: =IFERROR(__xludf.DUMMYFUNCTION("IF(A8="""","""", SPARKLINE( INDEX( GOOGLEFINANCE(""IDX:""&A8,""close"",TODAY()-365,TODAY()), ,2 ), {""linewidth"",1} )) "),"#N/A") -> #N/A | E8: FTSE Small Cap | F8: 12 Agustus 2026 | G8: =COUNTIFS($B$2:$B$1937,B8,$E$2:$E$1937,"<>") -> 9 | H8: =VLOOKUP(A8,Metrik!$C$2:$Y$959,8,0) -> 5.5 | I8: =VLOOKUP(A8,Metrik!$C$2:$Y$959,9,0) -> 1 | J8: =VLOOKUP(A8,Metrik!$C$2:$Y$959,10,0) -> 18.6 | K8: =VLOOKUP(A8,Metrik!$C$2:$Y$959,11,0) -> 12.2 | L8: =VLOOKUP(A8,Metrik!$C$2:$Y$959,12,0) -> 0.53 | M8: =VLOOKUP(A8,Metrik!$C$2:$Y$959,19,0) -> 67.3 | U8: =IFERROR(__xludf.DUMMYFUNCTION("IFERROR(GOOGLEFINANCE(A8,""closeyest""),"""")"),8050.0) -> 8050 | V8: =IFERROR(__xludf.DUMMYFUNCTION("IFERROR(GOOGLEFINANCE(A8,""changepct""),"""")"),7.45) -> 7.45 | W8: =IFERROR(__xludf.DUMMYFUNCTION("IFERROR(GOOGLEFINANCE(A8,""priceopen""),"""")"),8100.0) -> 8100 | X8: =IFERROR(__xludf.DUMMYFUNCTION("IFERROR(GOOGLEFINANCE(A8,""high""),"""")"),8850.0) -> 8850 | Y8: =IFERROR(__xludf.DUMMYFUNCTION("IFERROR(GOOGLEFINANCE(A8,""low""),"""")"),8050.0) -> 8050 | Z8: =IFERROR(__xludf.DUMMYFUNCTION("IFERROR(GOOGLEFINANCE(A8,""volume""),"""")"),2.12622E7) -> 21262200 | AA8: =VLOOKUP(A8,Metrik!$C$2:$Y$959,5,0) -> Coal | AB8: =VLOOKUP(A8,Metrik!$C$2:$Y$959,3,0) -> Energy
A9: AADI | B9: {=VLOOKUP(A9,{Metrik!$C$2:$C$998,Metrik!$B$2:$B$998},2,0)} -> Adaro Andalan Indonesia Tbk. | C9: =IFERROR(__xludf.DUMMYFUNCTION("GOOGLEFINANCE(""IDX:""&A9,""price"")"),8650.0) -> 8650 | D9: =IFERROR(__xludf.DUMMYFUNCTION("IF(A9="""","""", SPARKLINE( INDEX( GOOGLEFINANCE(""IDX:""&A9,""close"",TODAY()-365,TODAY()), ,2 ), {""linewidth"",1} )) "),"#N/A") -> #N/A | E9: JII30 | F9: 46356 | G9: =COUNTIFS($B$2:$B$1937,B9,$E$2:$E$1937,"<>") -> 9 | H9: =VLOOKUP(A9,Metrik!$C$2:$Y$959,8,0) -> 5.5 | I9: =VLOOKUP(A9,Metrik!$C$2:$Y$959,9,0) -> 1 | J9: =VLOOKUP(A9,Metrik!$C$2:$Y$959,10,0) -> 18.6 | K9: =VLOOKUP(A9,Metrik!$C$2:$Y$959,11,0) -> 12.2 | L9: =VLOOKUP(A9,Metrik!$C$2:$Y$959,12,0) -> 0.53 | M9: =VLOOKUP(A9,Metrik!$C$2:$Y$959,19,0) -> 67.3 | U9: =IFERROR(__xludf.DUMMYFUNCTION("IFERROR(GOOGLEFINANCE(A9,""closeyest""),"""")"),8050.0) -> 8050 | V9: =IFERROR(__xludf.DUMMYFUNCTION("IFERROR(GOOGLEFINANCE(A9,""changepct""),"""")"),7.45) -> 7.45 | W9: =IFERROR(__xludf.DUMMYFUNCTION("IFERROR(GOOGLEFINANCE(A9,""priceopen""),"""")"),8100.0) -> 8100 | X9: =IFERROR(__xludf.DUMMYFUNCTION("IFERROR(GOOGLEFINANCE(A9,""high""),"""")"),8850.0) -> 8850 | Y9: =IFERROR(__xludf.DUMMYFUNCTION("IFERROR(GOOGLEFINANCE(A9,""low""),"""")"),8050.0) -> 8050 | Z9: =IFERROR(__xludf.DUMMYFUNCTION("IFERROR(GOOGLEFINANCE(A9,""volume""),"""")"),2.12622E7) -> 21262200 | AA9: =VLOOKUP(A9,Metrik!$C$2:$Y$959,5,0) -> Coal | AB9: =VLOOKUP(A9,Metrik!$C$2:$Y$959,3,0) -> Energy
A10: AADI | B10: {=VLOOKUP(A10,{Metrik!$C$2:$C$998,Metrik!$B$2:$B$998},2,0)} -> Adaro Andalan Indonesia Tbk. | C10: =IFERROR(__xludf.DUMMYFUNCTION("GOOGLEFINANCE(""IDX:""&A10,""price"")"),8650.0) -> 8650 | D10: =IFERROR(__xludf.DUMMYFUNCTION("IF(A10="""","""", SPARKLINE( INDEX( GOOGLEFINANCE(""IDX:""&A10,""close"",TODAY()-365,TODAY()), ,2 ), {""linewidth"",1} )) "),"#N/A") -> #N/A | E10: JII70 | F10: 46356 | G10: =COUNTIFS($B$2:$B$1937,B10,$E$2:$E$1937,"<>") -> 9 | H10: =VLOOKUP(A10,Metrik!$C$2:$Y$959,8,0) -> 5.5 | I10: =VLOOKUP(A10,Metrik!$C$2:$Y$959,9,0) -> 1 | J10: =VLOOKUP(A10,Metrik!$C$2:$Y$959,10,0) -> 18.6 | K10: =VLOOKUP(A10,Metrik!$C$2:$Y$959,11,0) -> 12.2 | L10: =VLOOKUP(A10,Metrik!$C$2:$Y$959,12,0) -> 0.53 | M10: =VLOOKUP(A10,Metrik!$C$2:$Y$959,19,0) -> 67.3 | U10: =IFERROR(__xludf.DUMMYFUNCTION("IFERROR(GOOGLEFINANCE(A10,""closeyest""),"""")"),8050.0) -> 8050 | V10: =IFERROR(__xludf.DUMMYFUNCTION("IFERROR(GOOGLEFINANCE(A10,""changepct""),"""")"),7.45) -> 7.45 | W10: =IFERROR(__xludf.DUMMYFUNCTION("IFERROR(GOOGLEFINANCE(A10,""priceopen""),"""")"),8100.0) -> 8100 | X10: =IFERROR(__xludf.DUMMYFUNCTION("IFERROR(GOOGLEFINANCE(A10,""high""),"""")"),8850.0) -> 8850 | Y10: =IFERROR(__xludf.DUMMYFUNCTION("IFERROR(GOOGLEFINANCE(A10,""low""),"""")"),8050.0) -> 8050 | Z10: =IFERROR(__xludf.DUMMYFUNCTION("IFERROR(GOOGLEFINANCE(A10,""volume""),"""")"),2.12622E7) -> 21262200 | AA10: =VLOOKUP(A10,Metrik!$C$2:$Y$959,5,0) -> Coal | AB10: =VLOOKUP(A10,Metrik!$C$2:$Y$959,3,0) -> Energy
A11: AALI | B11: {=VLOOKUP(A11,{Metrik!$C$2:$C$998,Metrik!$B$2:$B$998},2,0)} -> Astra Agro Lestari Tbk | C11: =IFERROR(__xludf.DUMMYFUNCTION("GOOGLEFINANCE(""IDX:""&A11,""price"")"),6175.0) -> 6175 | D11: =IFERROR(__xludf.DUMMYFUNCTION("IF(A11="""","""", SPARKLINE( INDEX( GOOGLEFINANCE(""IDX:""&A11,""close"",TODAY()-365,TODAY()), ,2 ), {""linewidth"",1} )) "),"#N/A") -> #N/A | E11: IDXSMC-LIQ | F11: 4 Agustus 2026 | G11: =COUNTIFS($B$2:$B$1937,B11,$E$2:$E$1937,"<>") -> 2 | H11: =VLOOKUP(A11,Metrik!$C$2:$Y$959,8,0) -> 8 | I11: =VLOOKUP(A11,Metrik!$C$2:$Y$959,9,0) -> 0.51 | J11: =VLOOKUP(A11,Metrik!$C$2:$Y$959,10,0) -> 6.4 | K11: =VLOOKUP(A11,Metrik!$C$2:$Y$959,11,0) -> 5.6 | L11: =VLOOKUP(A11,Metrik!$C$2:$Y$959,12,0) -> 0.14 | M11: =VLOOKUP(A11,Metrik!$C$2:$Y$959,19,0) -> 20.9 | U11: =IFERROR(__xludf.DUMMYFUNCTION("IFERROR(GOOGLEFINANCE(A11,""closeyest""),"""")"),6050.0) -> 6050 | V11: =IFERROR(__xludf.DUMMYFUNCTION("IFERROR(GOOGLEFINANCE(A11,""changepct""),"""")"),2.07) -> 2.07 | W11: =IFERROR(__xludf.DUMMYFUNCTION("IFERROR(GOOGLEFINANCE(A11,""priceopen""),"""")"),6075.0) -> 6075 | X11: =IFERROR(__xludf.DUMMYFUNCTION("IFERROR(GOOGLEFINANCE(A11,""high""),"""")"),6325.0) -> 6325 | Y11: =IFERROR(__xludf.DUMMYFUNCTION("IFERROR(GOOGLEFINANCE(A11,""low""),"""")"),6025.0) -> 6025 | Z11: =IFERROR(__xludf.DUMMYFUNCTION("IFERROR(GOOGLEFINANCE(A11,""volume""),"""")"),3068700.0) -> 3068700 | AA11: =VLOOKUP(A11,Metrik!$C$2:$Y$959,5,0) -> Agricultural Products | AB11: =VLOOKUP(A11,Metrik!$C$2:$Y$959,3,0) -> Consumer Non-Cyclicals
A12: AALI | B12: {=VLOOKUP(A12,{Metrik!$C$2:$C$998,Metrik!$B$2:$B$998},2,0)} -> Astra Agro Lestari Tbk | C12: =IFERROR(__xludf.DUMMYFUNCTION("GOOGLEFINANCE(""IDX:""&A12,""price"")"),6175.0) -> 6175 | D12: =IFERROR(__xludf.DUMMYFUNCTION("IF(A12="""","""", SPARKLINE( INDEX( GOOGLEFINANCE(""IDX:""&A12,""close"",TODAY()-365,TODAY()), ,2 ), {""linewidth"",1} )) "),"#N/A") -> #N/A | E12: Investor33 | F12: 46356 | G12: =COUNTIFS($B$2:$B$1937,B12,$E$2:$E$1937,"<>") -> 2 | H12: =VLOOKUP(A12,Metrik!$C$2:$Y$959,8,0) -> 8 | I12: =VLOOKUP(A12,Metrik!$C$2:$Y$959,9,0) -> 0.51 | J12: =VLOOKUP(A12,Metrik!$C$2:$Y$959,10,0) -> 6.4 | K12: =VLOOKUP(A12,Metrik!$C$2:$Y$959,11,0) -> 5.6 | L12: =VLOOKUP(A12,Metrik!$C$2:$Y$959,12,0) -> 0.14 | M12: =VLOOKUP(A12,Metrik!$C$2:$Y$959,19,0) -> 20.9 | U12: =IFERROR(__xludf.DUMMYFUNCTION("IFERROR(GOOGLEFINANCE(A12,""closeyest""),"""")"),6050.0) -> 6050 | V12: =IFERROR(__xludf.DUMMYFUNCTION("IFERROR(GOOGLEFINANCE(A12,""changepct""),"""")"),2.07) -> 2.07 | W12: =IFERROR(__xludf.DUMMYFUNCTION("IFERROR(GOOGLEFINANCE(A12,""priceopen""),"""")"),6075.0) -> 6075 | X12: =IFERROR(__xludf.DUMMYFUNCTION("IFERROR(GOOGLEFINANCE(A12,""high""),"""")"),6325.0) -> 6325 | Y12: =IFERROR(__xludf.DUMMYFUNCTION("IFERROR(GOOGLEFINANCE(A12,""low""),"""")"),6025.0) -> 6025 | Z12: =IFERROR(__xludf.DUMMYFUNCTION("IFERROR(GOOGLEFINANCE(A12,""volume""),"""")"),3068700.0) -> 3068700 | AA12: =VLOOKUP(A12,Metrik!$C$2:$Y$959,5,0) -> Agricultural Products | AB12: =VLOOKUP(A12,Metrik!$C$2:$Y$959,3,0) -> Consumer Non-Cyclicals
A13: ABBA | B13: {=VLOOKUP(A13,{Metrik!$C$2:$C$998,Metrik!$B$2:$B$998},2,0)} -> Mahaka Media Tbk. | C13: =IFERROR(__xludf.DUMMYFUNCTION("GOOGLEFINANCE(""IDX:""&A13,""price"")"),35.0) -> 35 | D13: =IFERROR(__xludf.DUMMYFUNCTION("IF(A13="""","""", SPARKLINE( INDEX( GOOGLEFINANCE(""IDX:""&A13,""close"",TODAY()-365,TODAY()), ,2 ), {""linewidth"",1} )) "),"#N/A") -> #N/A | G13: =COUNTIFS($B$2:$B$1937,B13,$E$2:$E$1937,"<>") -> 0 | H13: =VLOOKUP(A13,Metrik!$C$2:$Y$959,8,0) -> -5.5 | I13: =VLOOKUP(A13,Metrik!$C$2:$Y$959,9,0) -> -1.3 | J13: =VLOOKUP(A13,Metrik!$C$2:$Y$959,10,0) -> 0 | K13: =VLOOKUP(A13,Metrik!$C$2:$Y$959,11,0) -> -11.1 | L13: =VLOOKUP(A13,Metrik!$C$2:$Y$959,12,0) -> -3.1 | M13: =VLOOKUP(A13,Metrik!$C$2:$Y$959,19,0) -> -91.1 | U13: =IFERROR(__xludf.DUMMYFUNCTION("IFERROR(GOOGLEFINANCE(A13,""closeyest""),"""")"),35.0) -> 35 | V13: =IFERROR(__xludf.DUMMYFUNCTION("IFERROR(GOOGLEFINANCE(A13,""changepct""),"""")"),0.0) -> 0 | W13: =IFERROR(__xludf.DUMMYFUNCTION("IFERROR(GOOGLEFINANCE(A13,""priceopen""),"""")"),35.0) -> 35 | X13: =IFERROR(__xludf.DUMMYFUNCTION("IFERROR(GOOGLEFINANCE(A13,""high""),"""")"),35.0) -> 35 | Y13: =IFERROR(__xludf.DUMMYFUNCTION("IFERROR(GOOGLEFINANCE(A13,""low""),"""")"),35.0) -> 35 | Z13: =IFERROR(__xludf.DUMMYFUNCTION("IFERROR(GOOGLEFINANCE(A13,""volume""),"""")"),292000.0) -> 292000 | AA13: =VLOOKUP(A13,Metrik!$C$2:$Y$959,5,0) -> Media | AB13: =VLOOKUP(A13,Metrik!$C$2:$Y$959,3,0) -> Consumer Cyclicals
A14: ABDA | B14: {=VLOOKUP(A14,{Metrik!$C$2:$C$998,Metrik!$B$2:$B$998},2,0)} -> Asuransi Bina Dana Arta Tbk. | C14: =IFERROR(__xludf.DUMMYFUNCTION("GOOGLEFINANCE(""IDX:""&A14,""price"")"),3390.0) -> 3390 | D14: =IFERROR(__xludf.DUMMYFUNCTION("IF(A14="""","""", SPARKLINE( INDEX( GOOGLEFINANCE(""IDX:""&A14,""close"",TODAY()-365,TODAY()), ,2 ), {""linewidth"",1} )) "),"#N/A") -> #N/A | G14: =COUNTIFS($B$2:$B$1937,B14,$E$2:$E$1937,"<>") -> 0 | H14: =VLOOKUP(A14,Metrik!$C$2:$Y$959,8,0) -> 19.6 | I14: =VLOOKUP(A14,Metrik!$C$2:$Y$959,9,0) -> 1.2 | J14: =VLOOKUP(A14,Metrik!$C$2:$Y$959,10,0) -> 6.3 | K14: =VLOOKUP(A14,Metrik!$C$2:$Y$959,11,0) -> 3.9 | L14: =VLOOKUP(A14,Metrik!$C$2:$Y$959,12,0) -> 0.59 | M14: =VLOOKUP(A14,Metrik!$C$2:$Y$959,19,0) -> 31.1 | U14: =IFERROR(__xludf.DUMMYFUNCTION("IFERROR(GOOGLEFINANCE(A14,""closeyest""),"""")"),3330.0) -> 3330 | V14: =IFERROR(__xludf.DUMMYFUNCTION("IFERROR(GOOGLEFINANCE(A14,""changepct""),"""")"),1.8) -> 1.8 | W14: =IFERROR(__xludf.DUMMYFUNCTION("IFERROR(GOOGLEFINANCE(A14,""priceopen""),"""")"),3430.0) -> 3430 | X14: =IFERROR(__xludf.DUMMYFUNCTION("IFERROR(GOOGLEFINANCE(A14,""high""),"""")"),3430.0) -> 3430 | Y14: =IFERROR(__xludf.DUMMYFUNCTION("IFERROR(GOOGLEFINANCE(A14,""low""),"""")"),3100.0) -> 3100 | Z14: =IFERROR(__xludf.DUMMYFUNCTION("IFERROR(GOOGLEFINANCE(A14,""volume""),"""")"),10200.0) -> 10200 | AA14: =VLOOKUP(A14,Metrik!$C$2:$Y$959,5,0) -> Insurance | AB14: =VLOOKUP(A14,Metrik!$C$2:$Y$959,3,0) -> Financials
A15: ABMM | B15: {=VLOOKUP(A15,{Metrik!$C$2:$C$998,Metrik!$B$2:$B$998},2,0)} -> ABM Investama Tbk | C15: =IFERROR(__xludf.DUMMYFUNCTION("GOOGLEFINANCE(""IDX:""&A15,""price"")"),2420.0) -> 2420 | D15: =IFERROR(__xludf.DUMMYFUNCTION("IF(A15="""","""", SPARKLINE( INDEX( GOOGLEFINANCE(""IDX:""&A15,""close"",TODAY()-365,TODAY()), ,2 ), {""linewidth"",1} )) "),"#N/A") -> #N/A | G15: =COUNTIFS($B$2:$B$1937,B15,$E$2:$E$1937,"<>") -> 0 | H15: =VLOOKUP(A15,Metrik!$C$2:$Y$959,8,0) -> 6.2 | I15: =VLOOKUP(A15,Metrik!$C$2:$Y$959,9,0) -> 0.43 | J15: =VLOOKUP(A15,Metrik!$C$2:$Y$959,10,0) -> 7.1 | K15: =VLOOKUP(A15,Metrik!$C$2:$Y$959,11,0) -> 3.1 | L15: =VLOOKUP(A15,Metrik!$C$2:$Y$959,12,0) -> 1.3 | M15: =VLOOKUP(A15,Metrik!$C$2:$Y$959,19,0) -> 28.4 | U15: =IFERROR(__xludf.DUMMYFUNCTION("IFERROR(GOOGLEFINANCE(A15,""closeyest""),"""")"),2300.0) -> 2300 | V15: =IFERROR(__xludf.DUMMYFUNCTION("IFERROR(GOOGLEFINANCE(A15,""changepct""),"""")"),5.22) -> 5.22 | W15: =IFERROR(__xludf.DUMMYFUNCTION("IFERROR(GOOGLEFINANCE(A15,""priceopen""),"""")"),2300.0) -> 2300 | X15: =IFERROR(__xludf.DUMMYFUNCTION("IFERROR(GOOGLEFINANCE(A15,""high""),"""")"),"") | Y15: =IFERROR(__xludf.DUMMYFUNCTION("IFERROR(GOOGLEFINANCE(A15,""low""),"""")"),2300.0) -> 2300 | Z15: =IFERROR(__xludf.DUMMYFUNCTION("IFERROR(GOOGLEFINANCE(A15,""volume""),"""")"),739300.0) -> 739300 | AA15: =VLOOKUP(A15,Metrik!$C$2:$Y$959,5,0) -> Multi-sector Holdings | AB15: =VLOOKUP(A15,Metrik!$C$2:$Y$959,3,0) -> Industrials
A16: ACES | B16: {=VLOOKUP(A16,{Metrik!$C$2:$C$998,Metrik!$B$2:$B$998},2,0)} -> Aspirasi Hidup Indonesia Tbk. | C16: =IFERROR(__xludf.DUMMYFUNCTION("GOOGLEFINANCE(""IDX:""&A16,""price"")"),356.0) -> 356 | D16: =IFERROR(__xludf.DUMMYFUNCTION("IF(A16="""","""", SPARKLINE( INDEX( GOOGLEFINANCE(""IDX:""&A16,""close"",TODAY()-365,TODAY()), ,2 ), {""linewidth"",1} )) "),"#N/A") -> #N/A | E16: ESGQKEHATI | F16: 46356 | G16: =COUNTIFS($B$2:$B$1937,B16,$E$2:$E$1937,"<>") -> 11 | H16: =VLOOKUP(A16,Metrik!$C$2:$Y$959,8,0) -> 8.6 | I16: =VLOOKUP(A16,Metrik!$C$2:$Y$959,9,0) -> 0.88 | J16: =VLOOKUP(A16,Metrik!$C$2:$Y$959,10,0) -> 10.2 | K16: =VLOOKUP(A16,Metrik!$C$2:$Y$959,11,0) -> 8 | L16: =VLOOKUP(A16,Metrik!$C$2:$Y$959,12,0) -> 0.28 | M16: =VLOOKUP(A16,Metrik!$C$2:$Y$959,19,0) -> 29.4 | U16: =IFERROR(__xludf.DUMMYFUNCTION("IFERROR(GOOGLEFINANCE(A16,""closeyest""),"""")"),36.5) -> 36.5 | V16: =IFERROR(__xludf.DUMMYFUNCTION("IFERROR(GOOGLEFINANCE(A16,""changepct""),"""")"),1.12) -> 1.12 | W16: =IFERROR(__xludf.DUMMYFUNCTION("IFERROR(GOOGLEFINANCE(A16,""priceopen""),"""")"),36.6) -> 36.6 | X16: =IFERROR(__xludf.DUMMYFUNCTION("IFERROR(GOOGLEFINANCE(A16,""high""),"""")"),36.98) -> 36.98 | Y16: =IFERROR(__xludf.DUMMYFUNCTION("IFERROR(GOOGLEFINANCE(A16,""low""),"""")"),36.6) -> 36.6 | Z16: =IFERROR(__xludf.DUMMYFUNCTION("IFERROR(GOOGLEFINANCE(A16,""volume""),"""")"),846.0) -> 846 | AA16: =VLOOKUP(A16,Metrik!$C$2:$Y$959,5,0) -> Specialty Retail | AB16: =VLOOKUP(A16,Metrik!$C$2:$Y$959,3,0) -> Consumer Cyclicals
A17: ACES | B17: {=VLOOKUP(A17,{Metrik!$C$2:$C$998,Metrik!$B$2:$B$998},2,0)} -> Aspirasi Hidup Indonesia Tbk. | C17: =IFERROR(__xludf.DUMMYFUNCTION("GOOGLEFINANCE(""IDX:""&A17,""price"")"),356.0) -> 356 | D17: =IFERROR(__xludf.DUMMYFUNCTION("IF(A17="""","""", SPARKLINE( INDEX( GOOGLEFINANCE(""IDX:""&A17,""close"",TODAY()-365,TODAY()), ,2 ), {""linewidth"",1} )) "),"#N/A") -> #N/A | E17: IDXHIDIV20 | F17: 2 Februari 2027 | G17: =COUNTIFS($B$2:$B$1937,B17,$E$2:$E$1937,"<>") -> 11 | H17: =VLOOKUP(A17,Metrik!$C$2:$Y$959,8,0) -> 8.6 | I17: =VLOOKUP(A17,Metrik!$C$2:$Y$959,9,0) -> 0.88 | J17: =VLOOKUP(A17,Metrik!$C$2:$Y$959,10,0) -> 10.2 | K17: =VLOOKUP(A17,Metrik!$C$2:$Y$959,11,0) -> 8 | L17: =VLOOKUP(A17,Metrik!$C$2:$Y$959,12,0) -> 0.28 | M17: =VLOOKUP(A17,Metrik!$C$2:$Y$959,19,0) -> 29.4 | U17: =IFERROR(__xludf.DUMMYFUNCTION("IFERROR(GOOGLEFINANCE(A17,""closeyest""),"""")"),36.5) -> 36.5 | V17: =IFERROR(__xludf.DUMMYFUNCTION("IFERROR(GOOGLEFINANCE(A17,""changepct""),"""")"),1.12) -> 1.12 | W17: =IFERROR(__xludf.DUMMYFUNCTION("IFERROR(GOOGLEFINANCE(A17,""priceopen""),"""")"),36.6) -> 36.6 | X17: =IFERROR(__xludf.DUMMYFUNCTION("IFERROR(GOOGLEFINANCE(A17,""high""),"""")"),36.98) -> 36.98 | Y17: =IFERROR(__xludf.DUMMYFUNCTION("IFERROR(GOOGLEFINANCE(A17,""low""),"""")"),36.6) -> 36.6 | Z17: =IFERROR(__xludf.DUMMYFUNCTION("IFERROR(GOOGLEFINANCE(A17,""volume""),"""")"),846.0) -> 846 | AA17: =VLOOKUP(A17,Metrik!$C$2:$Y$959,5,0) -> Specialty Retail | AB17: =VLOOKUP(A17,Metrik!$C$2:$Y$959,3,0) -> Consumer Cyclicals
A18: ACES | B18: {=VLOOKUP(A18,{Metrik!$C$2:$C$998,Metrik!$B$2:$B$998},2,0)} -> Aspirasi Hidup Indonesia Tbk. | C18: =IFERROR(__xludf.DUMMYFUNCTION("GOOGLEFINANCE(""IDX:""&A18,""price"")"),356.0) -> 356 | D18: =IFERROR(__xludf.DUMMYFUNCTION("IF(A18="""","""", SPARKLINE( INDEX( GOOGLEFINANCE(""IDX:""&A18,""close"",TODAY()-365,TODAY()), ,2 ), {""linewidth"",1} )) "),"#N/A") -> #N/A | E18: IDX80 | F18: 31 Juli 2026 | G18: =COUNTIFS($B$2:$B$1937,B18,$E$2:$E$1937,"<>") -> 11 | H18: =VLOOKUP(A18,Metrik!$C$2:$Y$959,8,0) -> 8.6 | I18: =VLOOKUP(A18,Metrik!$C$2:$Y$959,9,0) -> 0.88 | J18: =VLOOKUP(A18,Metrik!$C$2:$Y$959,10,0) -> 10.2 | K18: =VLOOKUP(A18,Metrik!$C$2:$Y$959,11,0) -> 8 | L18: =VLOOKUP(A18,Metrik!$C$2:$Y$959,12,0) -> 0.28 | M18: =VLOOKUP(A18,Metrik!$C$2:$Y$959,19,0) -> 29.4 | U18: =IFERROR(__xludf.DUMMYFUNCTION("IFERROR(GOOGLEFINANCE(A18,""closeyest""),"""")"),36.5) -> 36.5 | V18: =IFERROR(__xludf.DUMMYFUNCTION("IFERROR(GOOGLEFINANCE(A18,""changepct""),"""")"),1.12) -> 1.12 | W18: =IFERROR(__xludf.DUMMYFUNCTION("IFERROR(GOOGLEFINANCE(A18,""priceopen""),"""")"),36.6) -> 36.6 | X18: =IFERROR(__xludf.DUMMYFUNCTION("IFERROR(GOOGLEFINANCE(A18,""high""),"""")"),36.98) -> 36.98 | Y18: =IFERROR(__xludf.DUMMYFUNCTION("IFERROR(GOOGLEFINANCE(A18,""low""),"""")"),36.6) -> 36.6 | Z18: =IFERROR(__xludf.DUMMYFUNCTION("IFERROR(GOOGLEFINANCE(A18,""volume""),"""")"),846.0) -> 846 | AA18: =VLOOKUP(A18,Metrik!$C$2:$Y$959,5,0) -> Specialty Retail | AB18: =VLOOKUP(A18,Metrik!$C$2:$Y$959,3,0) -> Consumer Cyclicals
A19: ACES | B19: {=VLOOKUP(A19,{Metrik!$C$2:$C$998,Metrik!$B$2:$B$998},2,0)} -> Aspirasi Hidup Indonesia Tbk. | C19: =IFERROR(__xludf.DUMMYFUNCTION("GOOGLEFINANCE(""IDX:""&A19,""price"")"),356.0) -> 356 | D19: =IFERROR(__xludf.DUMMYFUNCTION("IF(A19="""","""", SPARKLINE( INDEX( GOOGLEFINANCE(""IDX:""&A19,""close"",TODAY()-365,TODAY()), ,2 ), {""linewidth"",1} )) "),"#N/A") -> #N/A | E19: IDXESGL | F19: 30 Oktober 2026 | G19: =COUNTIFS($B$2:$B$1937,B19,$E$2:$E$1937,"<>") -> 11 | H19: =VLOOKUP(A19,Metrik!$C$2:$Y$959,8,0) -> 8.6 | I19: =VLOOKUP(A19,Metrik!$C$2:$Y$959,9,0) -> 0.88 | J19: =VLOOKUP(A19,Metrik!$C$2:$Y$959,10,0) -> 10.2 | K19: =VLOOKUP(A19,Metrik!$C$2:$Y$959,11,0) -> 8 | L19: =VLOOKUP(A19,Metrik!$C$2:$Y$959,12,0) -> 0.28 | M19: =VLOOKUP(A19,Metrik!$C$2:$Y$959,19,0) -> 29.4 | U19: =IFERROR(__xludf.DUMMYFUNCTION("IFERROR(GOOGLEFINANCE(A19,""closeyest""),"""")"),36.5) -> 36.5 | V19: =IFERROR(__xludf.DUMMYFUNCTION("IFERROR(GOOGLEFINANCE(A19,""changepct""),"""")"),1.12) -> 1.12 | W19: =IFERROR(__xludf.DUMMYFUNCTION("IFERROR(GOOGLEFINANCE(A19,""priceopen""),"""")"),36.6) -> 36.6 | X19: =IFERROR(__xludf.DUMMYFUNCTION("IFERROR(GOOGLEFINANCE(A19,""high""),"""")"),36.98) -> 36.98 | Y19: =IFERROR(__xludf.DUMMYFUNCTION("IFERROR(GOOGLEFINANCE(A19,""low""),"""")"),36.6) -> 36.6 | Z19: =IFERROR(__xludf.DUMMYFUNCTION("IFERROR(GOOGLEFINANCE(A19,""volume""),"""")"),846.0) -> 846 | AA19: =VLOOKUP(A19,Metrik!$C$2:$Y$959,5,0) -> Specialty Retail | AB19: =VLOOKUP(A19,Metrik!$C$2:$Y$959,3,0) -> Consumer Cyclicals
A20: ACES | B20: {=VLOOKUP(A20,{Metrik!$C$2:$C$998,Metrik!$B$2:$B$998},2,0)} -> Aspirasi Hidup Indonesia Tbk. | C20: =IFERROR(__xludf.DUMMYFUNCTION("GOOGLEFINANCE(""IDX:""&A20,""price"")"),356.0) -> 356 | D20: =IFERROR(__xludf.DUMMYFUNCTION("IF(A20="""","""", SPARKLINE( INDEX( GOOGLEFINANCE(""IDX:""&A20,""close"",TODAY()-365,TODAY()), ,2 ), {""linewidth"",1} )) "),"#N/A") -> #N/A | E20: ECONOMIC30 | F20: 31 Agustus 2026 | G20: =COUNTIFS($B$2:$B$1937,B20,$E$2:$E$1937,"<>") -> 11 | H20: =VLOOKUP(A20,Metrik!$C$2:$Y$959,8,0) -> 8.6 | I20: =VLOOKUP(A20,Metrik!$C$2:$Y$959,9,0) -> 0.88 | J20: =VLOOKUP(A20,Metrik!$C$2:$Y$959,10,0) -> 10.2 | K20: =VLOOKUP(A20,Metrik!$C$2:$Y$959,11,0) -> 8 | L20: =VLOOKUP(A20,Metrik!$C$2:$Y$959,12,0) -> 0.28 | M20: =VLOOKUP(A20,Metrik!$C$2:$Y$959,19,0) -> 29.4 | U20: =IFERROR(__xludf.DUMMYFUNCTION("IFERROR(GOOGLEFINANCE(A20,""closeyest""),"""")"),36.5) -> 36.5 | V20: =IFERROR(__xludf.DUMMYFUNCTION("IFERROR(GOOGLEFINANCE(A20,""changepct""),"""")"),1.12) -> 1.12 | W20: =IFERROR(__xludf.DUMMYFUNCTION("IFERROR(GOOGLEFINANCE(A20,""priceopen""),"""")"),36.6) -> 36.6 | X20: =IFERROR(__xludf.DUMMYFUNCTION("IFERROR(GOOGLEFINANCE(A20,""high""),"""")"),36.98) -> 36.98 | Y20: =IFERROR(__xludf.DUMMYFUNCTION("IFERROR(GOOGLEFINANCE(A20,""low""),"""")"),36.6) -> 36.6 | Z20: =IFERROR(__xludf.DUMMYFUNCTION("IFERROR(GOOGLEFINANCE(A20,""volume""),"""")"),846.0) -> 846 | AA20: =VLOOKUP(A20,Metrik!$C$2:$Y$959,5,0) -> Specialty Retail | AB20: =VLOOKUP(A20,Metrik!$C$2:$Y$959,3,0) -> Consumer Cyclicals
A21: ACES | B21: {=VLOOKUP(A21,{Metrik!$C$2:$C$998,Metrik!$B$2:$B$998},2,0)} -> Aspirasi Hidup Indonesia Tbk. | C21: =IFERROR(__xludf.DUMMYFUNCTION("GOOGLEFINANCE(""IDX:""&A21,""price"")"),356.0) -> 356 | D21: =IFERROR(__xludf.DUMMYFUNCTION("IF(A21="""","""", SPARKLINE( INDEX( GOOGLEFINANCE(""IDX:""&A21,""close"",TODAY()-365,TODAY()), ,2 ), {""linewidth"",1} )) "),"#N/A") -> #N/A | E21: Kompas100 | F21: 31 Juli 2026 | G21: =COUNTIFS($B$2:$B$1937,B21,$E$2:$E$1937,"<>") -> 11 | H21: =VLOOKUP(A21,Metrik!$C$2:$Y$959,8,0) -> 8.6 | I21: =VLOOKUP(A21,Metrik!$C$2:$Y$959,9,0) -> 0.88 | J21: =VLOOKUP(A21,Metrik!$C$2:$Y$959,10,0) -> 10.2 | K21: =VLOOKUP(A21,Metrik!$C$2:$Y$959,11,0) -> 8 | L21: =VLOOKUP(A21,Metrik!$C$2:$Y$959,12,0) -> 0.28 | M21: =VLOOKUP(A21,Metrik!$C$2:$Y$959,19,0) -> 29.4 | U21: =IFERROR(__xludf.DUMMYFUNCTION("IFERROR(GOOGLEFINANCE(A21,""closeyest""),"""")"),36.5) -> 36.5 | V21: =IFERROR(__xludf.DUMMYFUNCTION("IFERROR(GOOGLEFINANCE(A21,""changepct""),"""")"),1.12) -> 1.12 | W21: =IFERROR(__xludf.DUMMYFUNCTION("IFERROR(GOOGLEFINANCE(A21,""priceopen""),"""")"),36.6) -> 36.6 | X21: =IFERROR(__xludf.DUMMYFUNCTION("IFERROR(GOOGLEFINANCE(A21,""high""),"""")"),36.98) -> 36.98 | Y21: =IFERROR(__xludf.DUMMYFUNCTION("IFERROR(GOOGLEFINANCE(A21,""low""),"""")"),36.6) -> 36.6 | Z21: =IFERROR(__xludf.DUMMYFUNCTION("IFERROR(GOOGLEFINANCE(A21,""volume""),"""")"),846.0) -> 846 | AA21: =VLOOKUP(A21,Metrik!$C$2:$Y$959,5,0) -> Specialty Retail | AB21: =VLOOKUP(A21,Metrik!$C$2:$Y$959,3,0) -> Consumer Cyclicals
A22: ACES | B22: {=VLOOKUP(A22,{Metrik!$C$2:$C$998,Metrik!$B$2:$B$998},2,0)} -> Aspirasi Hidup Indonesia Tbk. | C22: =IFERROR(__xludf.DUMMYFUNCTION("GOOGLEFINANCE(""IDX:""&A22,""price"")"),356.0) -> 356 | D22: =IFERROR(__xludf.DUMMYFUNCTION("IF(A22="""","""", SPARKLINE( INDEX( GOOGLEFINANCE(""IDX:""&A22,""close"",TODAY()-365,TODAY()), ,2 ), {""linewidth"",1} )) "),"#N/A") -> #N/A | E22: IDXQ30 | F22: 4 Agustus 2026 | G22: =COUNTIFS($B$2:$B$1937,B22,$E$2:$E$1937,"<>") -> 11 | H22: =VLOOKUP(A22,Metrik!$C$2:$Y$959,8,0) -> 8.6 | I22: =VLOOKUP(A22,Metrik!$C$2:$Y$959,9,0) -> 0.88 | J22: =VLOOKUP(A22,Metrik!$C$2:$Y$959,10,0) -> 10.2 | K22: =VLOOKUP(A22,Metrik!$C$2:$Y$959,11,0) -> 8 | L22: =VLOOKUP(A22,Metrik!$C$2:$Y$959,12,0) -> 0.28 | M22: =VLOOKUP(A22,Metrik!$C$2:$Y$959,19,0) -> 29.4 | U22: =IFERROR(__xludf.DUMMYFUNCTION("IFERROR(GOOGLEFINANCE(A22,""closeyest""),"""")"),36.5) -> 36.5 | V22: =IFERROR(__xludf.DUMMYFUNCTION("IFERROR(GOOGLEFINANCE(A22,""changepct""),"""")"),1.12) -> 1.12 | W22: =IFERROR(__xludf.DUMMYFUNCTION("IFERROR(GOOGLEFINANCE(A22,""priceopen""),"""")"),36.6) -> 36.6 | X22: =IFERROR(__xludf.DUMMYFUNCTION("IFERROR(GOOGLEFINANCE(A22,""high""),"""")"),36.98) -> 36.98 | Y22: =IFERROR(__xludf.DUMMYFUNCTION("IFERROR(GOOGLEFINANCE(A22,""low""),"""")"),36.6) -> 36.6 | Z22: =IFERROR(__xludf.DUMMYFUNCTION("IFERROR(GOOGLEFINANCE(A22,""volume""),"""")"),846.0) -> 846 | AA22: =VLOOKUP(A22,Metrik!$C$2:$Y$959,5,0) -> Specialty Retail | AB22: =VLOOKUP(A22,Metrik!$C$2:$Y$959,3,0) -> Consumer Cyclicals
A23: ACES | B23: {=VLOOKUP(A23,{Metrik!$C$2:$C$998,Metrik!$B$2:$B$998},2,0)} -> Aspirasi Hidup Indonesia Tbk. | C23: =IFERROR(__xludf.DUMMYFUNCTION("GOOGLEFINANCE(""IDX:""&A23,""price"")"),356.0) -> 356 | D23: =IFERROR(__xludf.DUMMYFUNCTION("IF(A23="""","""", SPARKLINE( INDEX( GOOGLEFINANCE(""IDX:""&A23,""close"",TODAY()-365,TODAY()), ,2 ), {""linewidth"",1} )) "),"#N/A") -> #N/A | E23: IDXSMC-LIQ | F23: 4 Agustus 2026 | G23: =COUNTIFS($B$2:$B$1937,B23,$E$2:$E$1937,"<>") -> 11 | H23: =VLOOKUP(A23,Metrik!$C$2:$Y$959,8,0) -> 8.6 | I23: =VLOOKUP(A23,Metrik!$C$2:$Y$959,9,0) -> 0.88 | J23: =VLOOKUP(A23,Metrik!$C$2:$Y$959,10,0) -> 10.2 | K23: =VLOOKUP(A23,Metrik!$C$2:$Y$959,11,0) -> 8 | L23: =VLOOKUP(A23,Metrik!$C$2:$Y$959,12,0) -> 0.28 | M23: =VLOOKUP(A23,Metrik!$C$2:$Y$959,19,0) -> 29.4 | U23: =IFERROR(__xludf.DUMMYFUNCTION("IFERROR(GOOGLEFINANCE(A23,""closeyest""),"""")"),36.5) -> 36.5 | V23: =IFERROR(__xludf.DUMMYFUNCTION("IFERROR(GOOGLEFINANCE(A23,""changepct""),"""")"),1.12) -> 1.12 | W23: =IFERROR(__xludf.DUMMYFUNCTION("IFERROR(GOOGLEFINANCE(A23,""priceopen""),"""")"),36.6) -> 36.6 | X23: =IFERROR(__xludf.DUMMYFUNCTION("IFERROR(GOOGLEFINANCE(A23,""high""),"""")"),36.98) -> 36.98 | Y23: =IFERROR(__xludf.DUMMYFUNCTION("IFERROR(GOOGLEFINANCE(A23,""low""),"""")"),36.6) -> 36.6 | Z23: =IFERROR(__xludf.DUMMYFUNCTION("IFERROR(GOOGLEFINANCE(A23,""volume""),"""")"),846.0) -> 846 | AA23: =VLOOKUP(A23,Metrik!$C$2:$Y$959,5,0) -> Specialty Retail | AB23: =VLOOKUP(A23,Metrik!$C$2:$Y$959,3,0) -> Consumer Cyclicals
A24: ACES | B24: {=VLOOKUP(A24,{Metrik!$C$2:$C$998,Metrik!$B$2:$B$998},2,0)} -> Aspirasi Hidup Indonesia Tbk. | C24: =IFERROR(__xludf.DUMMYFUNCTION("GOOGLEFINANCE(""IDX:""&A24,""price"")"),356.0) -> 356 | D24: =IFERROR(__xludf.DUMMYFUNCTION("IF(A24="""","""", SPARKLINE( INDEX( GOOGLEFINANCE(""IDX:""&A24,""close"",TODAY()-365,TODAY()), ,2 ), {""linewidth"",1} )) "),"#N/A") -> #N/A | E24: IDXV30 | F24: 4 Agustus 2026 | G24: =COUNTIFS($B$2:$B$1937,B24,$E$2:$E$1937,"<>") -> 11 | H24: =VLOOKUP(A24,Metrik!$C$2:$Y$959,8,0) -> 8.6 | I24: =VLOOKUP(A24,Metrik!$C$2:$Y$959,9,0) -> 0.88 | J24: =VLOOKUP(A24,Metrik!$C$2:$Y$959,10,0) -> 10.2 | K24: =VLOOKUP(A24,Metrik!$C$2:$Y$959,11,0) -> 8 | L24: =VLOOKUP(A24,Metrik!$C$2:$Y$959,12,0) -> 0.28 | M24: =VLOOKUP(A24,Metrik!$C$2:$Y$959,19,0) -> 29.4 | U24: =IFERROR(__xludf.DUMMYFUNCTION("IFERROR(GOOGLEFINANCE(A24,""closeyest""),"""")"),36.5) -> 36.5 | V24: =IFERROR(__xludf.DUMMYFUNCTION("IFERROR(GOOGLEFINANCE(A24,""changepct""),"""")"),1.12) -> 1.12 | W24: =IFERROR(__xludf.DUMMYFUNCTION("IFERROR(GOOGLEFINANCE(A24,""priceopen""),"""")"),36.6) -> 36.6 | X24: =IFERROR(__xludf.DUMMYFUNCTION("IFERROR(GOOGLEFINANCE(A24,""high""),"""")"),36.98) -> 36.98 | Y24: =IFERROR(__xludf.DUMMYFUNCTION("IFERROR(GOOGLEFINANCE(A24,""low""),"""")"),36.6) -> 36.6 | Z24: =IFERROR(__xludf.DUMMYFUNCTION("IFERROR(GOOGLEFINANCE(A24,""volume""),"""")"),846.0) -> 846 | AA24: =VLOOKUP(A24,Metrik!$C$2:$Y$959,5,0) -> Specialty Retail | AB24: =VLOOKUP(A24,Metrik!$C$2:$Y$959,3,0) -> Consumer Cyclicals
A25: ACES | B25: {=VLOOKUP(A25,{Metrik!$C$2:$C$998,Metrik!$B$2:$B$998},2,0)} -> Aspirasi Hidup Indonesia Tbk. | C25: =IFERROR(__xludf.DUMMYFUNCTION("GOOGLEFINANCE(""IDX:""&A25,""price"")"),356.0) -> 356 | D25: =IFERROR(__xludf.DUMMYFUNCTION("IF(A25="""","""", SPARKLINE( INDEX( GOOGLEFINANCE(""IDX:""&A25,""close"",TODAY()-365,TODAY()), ,2 ), {""linewidth"",1} )) "),"#N/A") -> #N/A | E25: ESGSKEHATI | F25: 46356 | G25: =COUNTIFS($B$2:$B$1937,B25,$E$2:$E$1937,"<>") -> 11 | H25: =VLOOKUP(A25,Metrik!$C$2:$Y$959,8,0) -> 8.6 | I25: =VLOOKUP(A25,Metrik!$C$2:$Y$959,9,0) -> 0.88 | J25: =VLOOKUP(A25,Metrik!$C$2:$Y$959,10,0) -> 10.2 | K25: =VLOOKUP(A25,Metrik!$C$2:$Y$959,11,0) -> 8 | L25: =VLOOKUP(A25,Metrik!$C$2:$Y$959,12,0) -> 0.28 | M25: =VLOOKUP(A25,Metrik!$C$2:$Y$959,19,0) -> 29.4 | U25: =IFERROR(__xludf.DUMMYFUNCTION("IFERROR(GOOGLEFINANCE(A25,""closeyest""),"""")"),36.5) -> 36.5 | V25: =IFERROR(__xludf.DUMMYFUNCTION("IFERROR(GOOGLEFINANCE(A25,""changepct""),"""")"),1.12) -> 1.12 | W25: =IFERROR(__xludf.DUMMYFUNCTION("IFERROR(GOOGLEFINANCE(A25,""priceopen""),"""")"),36.6) -> 36.6 | X25: =IFERROR(__xludf.DUMMYFUNCTION("IFERROR(GOOGLEFINANCE(A25,""high""),"""")"),36.98) -> 36.98 | Y25: =IFERROR(__xludf.DUMMYFUNCTION("IFERROR(GOOGLEFINANCE(A25,""low""),"""")"),36.6) -> 36.6 | Z25: =IFERROR(__xludf.DUMMYFUNCTION("IFERROR(GOOGLEFINANCE(A25,""volume""),"""")"),846.0) -> 846 | AA25: =VLOOKUP(A25,Metrik!$C$2:$Y$959,5,0) -> Specialty Retail | AB25: =VLOOKUP(A25,Metrik!$C$2:$Y$959,3,0) -> Consumer Cyclicals
A26: ACES | B26: {=VLOOKUP(A26,{Metrik!$C$2:$C$998,Metrik!$B$2:$B$998},2,0)} -> Aspirasi Hidup Indonesia Tbk. | C26: =IFERROR(__xludf.DUMMYFUNCTION("GOOGLEFINANCE(""IDX:""&A26,""price"")"),356.0) -> 356 | D26: =IFERROR(__xludf.DUMMYFUNCTION("IF(A26="""","""", SPARKLINE( INDEX( GOOGLEFINANCE(""IDX:""&A26,""close"",TODAY()-365,TODAY()), ,2 ), {""linewidth"",1} )) "),"#N/A") -> #N/A | E26: JII70 | F26: 46356 | G26: =COUNTIFS($B$2:$B$1937,B26,$E$2:$E$1937,"<>") -> 11 | H26: =VLOOKUP(A26,Metrik!$C$2:$Y$959,8,0) -> 8.6 | I26: =VLOOKUP(A26,Metrik!$C$2:$Y$959,9,0) -> 0.88 | J26: =VLOOKUP(A26,Metrik!$C$2:$Y$959,10,0) -> 10.2 | K26: =VLOOKUP(A26,Metrik!$C$2:$Y$959,11,0) -> 8 | L26: =VLOOKUP(A26,Metrik!$C$2:$Y$959,12,0) -> 0.28 | M26: =VLOOKUP(A26,Metrik!$C$2:$Y$959,19,0) -> 29.4 | U26: =IFERROR(__xludf.DUMMYFUNCTION("IFERROR(GOOGLEFINANCE(A26,""closeyest""),"""")"),36.5) -> 36.5 | V26: =IFERROR(__xludf.DUMMYFUNCTION("IFERROR(GOOGLEFINANCE(A26,""changepct""),"""")"),1.12) -> 1.12 | W26: =IFERROR(__xludf.DUMMYFUNCTION("IFERROR(GOOGLEFINANCE(A26,""priceopen""),"""")"),36.6) -> 36.6 | X26: =IFERROR(__xludf.DUMMYFUNCTION("IFERROR(GOOGLEFINANCE(A26,""high""),"""")"),36.98) -> 36.98 | Y26: =IFERROR(__xludf.DUMMYFUNCTION("IFERROR(GOOGLEFINANCE(A26,""low""),"""")"),36.6) -> 36.6 | Z26: =IFERROR(__xludf.DUMMYFUNCTION("IFERROR(GOOGLEFINANCE(A26,""volume""),"""")"),846.0) -> 846 | AA26: =VLOOKUP(A26,Metrik!$C$2:$Y$959,5,0) -> Specialty Retail | AB26: =VLOOKUP(A26,Metrik!$C$2:$Y$959,3,0) -> Consumer Cyclicals
A27: ACRO | B27: {=VLOOKUP(A27,{Metrik!$C$2:$C$998,Metrik!$B$2:$B$998},2,0)} -> Samcro Hyosung Adilestari Tbk. | C27: =IFERROR(__xludf.DUMMYFUNCTION("GOOGLEFINANCE(""IDX:""&A27,""price"")"),61.0) -> 61 | D27: =IFERROR(__xludf.DUMMYFUNCTION("IF(A27="""","""", SPARKLINE( INDEX( GOOGLEFINANCE(""IDX:""&A27,""close"",TODAY()-365,TODAY()), ,2 ), {""linewidth"",1} )) "),"#N/A") -> #N/A | G27: =COUNTIFS($B$2:$B$1937,B27,$E$2:$E$1937,"<>") -> 0 | H27: =VLOOKUP(A27,Metrik!$C$2:$Y$959,8,0) -> 26.8 | I27: =VLOOKUP(A27,Metrik!$C$2:$Y$959,9,0) -> 1.2 | J27: =VLOOKUP(A27,Metrik!$C$2:$Y$959,10,0) -> 4.6 | K27: =VLOOKUP(A27,Metrik!$C$2:$Y$959,11,0) -> 3.5 | L27: =VLOOKUP(A27,Metrik!$C$2:$Y$959,12,0) -> 0.29 | M27: =VLOOKUP(A27,Metrik!$C$2:$Y$959,19,0) -> 70.6 | U27: =IFERROR(__xludf.DUMMYFUNCTION("IFERROR(GOOGLEFINANCE(A27,""closeyest""),"""")"),60.0) -> 60 | V27: =IFERROR(__xludf.DUMMYFUNCTION("IFERROR(GOOGLEFINANCE(A27,""changepct""),"""")"),1.67) -> 1.67 | W27: =IFERROR(__xludf.DUMMYFUNCTION("IFERROR(GOOGLEFINANCE(A27,""priceopen""),"""")"),60.0) -> 60 | X27: =IFERROR(__xludf.DUMMYFUNCTION("IFERROR(GOOGLEFINANCE(A27,""high""),"""")"),65.0) -> 65 | Y27: =IFERROR(__xludf.DUMMYFUNCTION("IFERROR(GOOGLEFINANCE(A27,""low""),"""")"),60.0) -> 60 | Z27: =IFERROR(__xludf.DUMMYFUNCTION("IFERROR(GOOGLEFINANCE(A27,""volume""),"""")"),3937300.0) -> 3937300 | AA27: =VLOOKUP(A27,Metrik!$C$2:$Y$959,5,0) -> Apparel & Luxury Goods | AB27: =VLOOKUP(A27,Metrik!$C$2:$Y$959,3,0) -> Consumer Cyclicals
A28: ACST | B28: {=VLOOKUP(A28,{Metrik!$C$2:$C$998,Metrik!$B$2:$B$998},2,0)} -> PT Acset Indonusa Tbk. | C28: =IFERROR(__xludf.DUMMYFUNCTION("GOOGLEFINANCE(""IDX:""&A28,""price"")"),71.0) -> 71 | D28: =IFERROR(__xludf.DUMMYFUNCTION("IF(A28="""","""", SPARKLINE( INDEX( GOOGLEFINANCE(""IDX:""&A28,""close"",TODAY()-365,TODAY()), ,2 ), {""linewidth"",1} )) "),"#N/A") -> #N/A | G28: =COUNTIFS($B$2:$B$1937,B28,$E$2:$E$1937,"<>") -> 0 | H28: =VLOOKUP(A28,Metrik!$C$2:$Y$959,8,0) -> -2.1 | I28: =VLOOKUP(A28,Metrik!$C$2:$Y$959,9,0) -> -4.4 | J28: =VLOOKUP(A28,Metrik!$C$2:$Y$959,10,0) -> 0 | K28: =VLOOKUP(A28,Metrik!$C$2:$Y$959,11,0) -> -23.3 | L28: =VLOOKUP(A28,Metrik!$C$2:$Y$959,12,0) -> -9.9 | M28: =VLOOKUP(A28,Metrik!$C$2:$Y$959,19,0) -> -150 | U28: =IFERROR(__xludf.DUMMYFUNCTION("IFERROR(GOOGLEFINANCE(A28,""closeyest""),"""")"),70.0) -> 70 | V28: =IFERROR(__xludf.DUMMYFUNCTION("IFERROR(GOOGLEFINANCE(A28,""changepct""),"""")"),1.43) -> 1.43 | W28: =IFERROR(__xludf.DUMMYFUNCTION("IFERROR(GOOGLEFINANCE(A28,""priceopen""),"""")"),70.0) -> 70 | X28: =IFERROR(__xludf.DUMMYFUNCTION("IFERROR(GOOGLEFINANCE(A28,""high""),"""")"),71.0) -> 71 | Y28: =IFERROR(__xludf.DUMMYFUNCTION("IFERROR(GOOGLEFINANCE(A28,""low""),"""")"),70.0) -> 70 | Z28: =IFERROR(__xludf.DUMMYFUNCTION("IFERROR(GOOGLEFINANCE(A28,""volume""),"""")"),173800.0) -> 173800 | AA28: =VLOOKUP(A28,Metrik!$C$2:$Y$959,5,0) -> Heavy Constructions & Civil Engineering | AB28: =VLOOKUP(A28,Metrik!$C$2:$Y$959,3,0) -> Infrastructures
A29: ADCP | B29: {=VLOOKUP(A29,{Metrik!$C$2:$C$998,Metrik!$B$2:$B$998},2,0)} -> Adhi Commuter Properti Tbk. | C29: =IFERROR(__xludf.DUMMYFUNCTION("GOOGLEFINANCE(""IDX:""&A29,""price"")"),50.0) -> 50 | D29: =IFERROR(__xludf.DUMMYFUNCTION("IF(A29="""","""", SPARKLINE( INDEX( GOOGLEFINANCE(""IDX:""&A29,""close"",TODAY()-365,TODAY()), ,2 ), {""linewidth"",1} )) "),"#N/A") -> #N/A | G29: =COUNTIFS($B$2:$B$1937,B29,$E$2:$E$1937,"<>") -> 0 | H29: =VLOOKUP(A29,Metrik!$C$2:$Y$959,8,0) -> -0.52 | I29: =VLOOKUP(A29,Metrik!$C$2:$Y$959,9,0) -> 2.8 | J29: =VLOOKUP(A29,Metrik!$C$2:$Y$959,10,0) -> -540 | K29: =VLOOKUP(A29,Metrik!$C$2:$Y$959,11,0) -> -42.2 | L29: =VLOOKUP(A29,Metrik!$C$2:$Y$959,12,0) -> 11.9 | M29: =VLOOKUP(A29,Metrik!$C$2:$Y$959,19,0) -> -5640 | U29: =IFERROR(__xludf.DUMMYFUNCTION("IFERROR(GOOGLEFINANCE(A29,""closeyest""),"""")"),50.0) -> 50 | V29: =IFERROR(__xludf.DUMMYFUNCTION("IFERROR(GOOGLEFINANCE(A29,""changepct""),"""")"),0.0) -> 0 | W29: =IFERROR(__xludf.DUMMYFUNCTION("IFERROR(GOOGLEFINANCE(A29,""priceopen""),"""")"),"") | X29: =IFERROR(__xludf.DUMMYFUNCTION("IFERROR(GOOGLEFINANCE(A29,""high""),"""")"),"") | Y29: =IFERROR(__xludf.DUMMYFUNCTION("IFERROR(GOOGLEFINANCE(A29,""low""),"""")"),"") | Z29: =IFERROR(__xludf.DUMMYFUNCTION("IFERROR(GOOGLEFINANCE(A29,""volume""),"""")"),0.0) -> 0 | AA29: =VLOOKUP(A29,Metrik!$C$2:$Y$959,5,0) -> Real Estate Management & Development | AB29: =VLOOKUP(A29,Metrik!$C$2:$Y$959,3,0) -> Properties & Real Estate
A30: ADES | B30: {=VLOOKUP(A30,{Metrik!$C$2:$C$998,Metrik!$B$2:$B$998},2,0)} -> Akasha Wira International Tbk. | C30: =IFERROR(__xludf.DUMMYFUNCTION("GOOGLEFINANCE(""IDX:""&A30,""price"")"),22000.0) -> 22000 | D30: =IFERROR(__xludf.DUMMYFUNCTION("IF(A30="""","""", SPARKLINE( INDEX( GOOGLEFINANCE(""IDX:""&A30,""close"",TODAY()-365,TODAY()), ,2 ), {""linewidth"",1} )) "),"#N/A") -> #N/A | G30: =COUNTIFS($B$2:$B$1937,B30,$E$2:$E$1937,"<>") -> 0 | H30: =VLOOKUP(A30,Metrik!$C$2:$Y$959,8,0) -> 14.6 | I30: =VLOOKUP(A30,Metrik!$C$2:$Y$959,9,0) -> 3.8 | J30: =VLOOKUP(A30,Metrik!$C$2:$Y$959,10,0) -> 26.1 | K30: =VLOOKUP(A30,Metrik!$C$2:$Y$959,11,0) -> 21.6 | L30: =VLOOKUP(A30,Metrik!$C$2:$Y$959,12,0) -> 0.21 | M30: =VLOOKUP(A30,Metrik!$C$2:$Y$959,19,0) -> 90.3 | U30: =IFERROR(__xludf.DUMMYFUNCTION("IFERROR(GOOGLEFINANCE(A30,""closeyest""),"""")"),21900.0) -> 21900 | V30: =IFERROR(__xludf.DUMMYFUNCTION("IFERROR(GOOGLEFINANCE(A30,""changepct""),"""")"),0.46) -> 0.46 | W30: =IFERROR(__xludf.DUMMYFUNCTION("IFERROR(GOOGLEFINANCE(A30,""priceopen""),"""")"),21900.0) -> 21900 | X30: =IFERROR(__xludf.DUMMYFUNCTION("IFERROR(GOOGLEFINANCE(A30,""high""),"""")"),22050.0) -> 22050 | Y30: =IFERROR(__xludf.DUMMYFUNCTION("IFERROR(GOOGLEFINANCE(A30,""low""),"""")"),21650.0) -> 21650 | Z30: =IFERROR(__xludf.DUMMYFUNCTION("IFERROR(GOOGLEFINANCE(A30,""volume""),"""")"),34900.0) -> 34900 | AA30: =VLOOKUP(A30,Metrik!$C$2:$Y$959,5,0) -> Beverages | AB30: =VLOOKUP(A30,Metrik!$C$2:$Y$959,3,0) -> Consumer Non-Cyclicals
A31: ADHI | B31: {=VLOOKUP(A31,{Metrik!$C$2:$C$998,Metrik!$B$2:$B$998},2,0)} -> PT Adhi Karya (Persero) Tbk. | C31: =IFERROR(__xludf.DUMMYFUNCTION("GOOGLEFINANCE(""IDX:""&A31,""price"")"),158.0) -> 158 | D31: =IFERROR(__xludf.DUMMYFUNCTION("IF(A31="""","""", SPARKLINE( INDEX( GOOGLEFINANCE(""IDX:""&A31,""close"",TODAY()-365,TODAY()), ,2 ), {""linewidth"",1} )) "),"#N/A") -> #N/A | E31: IDXBUMN20 | F31: 4 Agustus 2026 | G31: =COUNTIFS($B$2:$B$1937,B31,$E$2:$E$1937,"<>") -> 1 | H31: =VLOOKUP(A31,Metrik!$C$2:$Y$959,8,0) -> -0.27 | I31: =VLOOKUP(A31,Metrik!$C$2:$Y$959,9,0) -> 0.41 | J31: =VLOOKUP(A31,Metrik!$C$2:$Y$959,10,0) -> -150 | K31: =VLOOKUP(A31,Metrik!$C$2:$Y$959,11,0) -> -18.7 | L31: =VLOOKUP(A31,Metrik!$C$2:$Y$959,12,0) -> 7.1 | M31: =VLOOKUP(A31,Metrik!$C$2:$Y$959,19,0) -> -320 | U31: =IFERROR(__xludf.DUMMYFUNCTION("IFERROR(GOOGLEFINANCE(A31,""closeyest""),"""")"),0.19) -> 0.19 | V31: =IFERROR(__xludf.DUMMYFUNCTION("IFERROR(GOOGLEFINANCE(A31,""changepct""),"""")"),-10.53) -> -10.53 | W31: =IFERROR(__xludf.DUMMYFUNCTION("IFERROR(GOOGLEFINANCE(A31,""priceopen""),"""")"),0.17) -> 0.17 | X31: =IFERROR(__xludf.DUMMYFUNCTION("IFERROR(GOOGLEFINANCE(A31,""high""),"""")"),0.17) -> 0.17 | Y31: =IFERROR(__xludf.DUMMYFUNCTION("IFERROR(GOOGLEFINANCE(A31,""low""),"""")"),0.17) -> 0.17 | Z31: =IFERROR(__xludf.DUMMYFUNCTION("IFERROR(GOOGLEFINANCE(A31,""volume""),"""")"),427.0) -> 427 | AA31: =VLOOKUP(A31,Metrik!$C$2:$Y$959,5,0) -> Heavy Constructions & Civil Engineering | AB31: =VLOOKUP(A31,Metrik!$C$2:$Y$959,3,0) -> Infrastructures
A32: ADMF | B32: {=VLOOKUP(A32,{Metrik!$C$2:$C$998,Metrik!$B$2:$B$998},2,0)} -> Adira Dinamika Multi Finance Tbk. | C32: =IFERROR(__xludf.DUMMYFUNCTION("GOOGLEFINANCE(""IDX:""&A32,""price"")"),8200.0) -> 8200 | D32: =IFERROR(__xludf.DUMMYFUNCTION("IF(A32="""","""", SPARKLINE( INDEX( GOOGLEFINANCE(""IDX:""&A32,""close"",TODAY()-365,TODAY()), ,2 ), {""linewidth"",1} )) "),"#N/A") -> #N/A | G32: =COUNTIFS($B$2:$B$1937,B32,$E$2:$E$1937,"<>") -> 0 | H32: =VLOOKUP(A32,Metrik!$C$2:$Y$959,8,0) -> 5.9 | I32: =VLOOKUP(A32,Metrik!$C$2:$Y$959,9,0) -> 0.66 | J32: =VLOOKUP(A32,Metrik!$C$2:$Y$959,10,0) -> 11.2 | K32: =VLOOKUP(A32,Metrik!$C$2:$Y$959,11,0) -> 4.4 | L32: =VLOOKUP(A32,Metrik!$C$2:$Y$959,12,0) -> 1.6 | M32: =VLOOKUP(A32,Metrik!$C$2:$Y$959,19,0) -> 64.1 | U32: =IFERROR(__xludf.DUMMYFUNCTION("IFERROR(GOOGLEFINANCE(A32,""closeyest""),"""")"),8050.0) -> 8050 | V32: =IFERROR(__xludf.DUMMYFUNCTION("IFERROR(GOOGLEFINANCE(A32,""changepct""),"""")"),1.86) -> 1.86 | W32: =IFERROR(__xludf.DUMMYFUNCTION("IFERROR(GOOGLEFINANCE(A32,""priceopen""),"""")"),8100.0) -> 8100 | X32: =IFERROR(__xludf.DUMMYFUNCTION("IFERROR(GOOGLEFINANCE(A32,""high""),"""")"),8300.0) -> 8300 | Y32: =IFERROR(__xludf.DUMMYFUNCTION("IFERROR(GOOGLEFINANCE(A32,""low""),"""")"),8050.0) -> 8050 | Z32: =IFERROR(__xludf.DUMMYFUNCTION("IFERROR(GOOGLEFINANCE(A32,""volume""),"""")"),48500.0) -> 48500 | AA32: =VLOOKUP(A32,Metrik!$C$2:$Y$959,5,0) -> Consumer Financing | AB32: =VLOOKUP(A32,Metrik!$C$2:$Y$959,3,0) -> Financials
A33: ADMG | B33: {=VLOOKUP(A33,{Metrik!$C$2:$C$998,Metrik!$B$2:$B$998},2,0)} -> Polychem Indonesia Tbk | C33: =IFERROR(__xludf.DUMMYFUNCTION("GOOGLEFINANCE(""IDX:""&A33,""price"")"),200.0) -> 200 | D33: =IFERROR(__xludf.DUMMYFUNCTION("IF(A33="""","""", SPARKLINE( INDEX( GOOGLEFINANCE(""IDX:""&A33,""close"",TODAY()-365,TODAY()), ,2 ), {""linewidth"",1} )) "),"#N/A") -> #N/A | G33: =COUNTIFS($B$2:$B$1937,B33,$E$2:$E$1937,"<>") -> 0 | H33: =VLOOKUP(A33,Metrik!$C$2:$Y$959,8,0) -> -250 | I33: =VLOOKUP(A33,Metrik!$C$2:$Y$959,9,0) -> 0.43 | J33: =VLOOKUP(A33,Metrik!$C$2:$Y$959,10,0) -> -0.17 | K33: =VLOOKUP(A33,Metrik!$C$2:$Y$959,11,0) -> -0.13 | L33: =VLOOKUP(A33,Metrik!$C$2:$Y$959,12,0) -> 0.37 | M33: =VLOOKUP(A33,Metrik!$C$2:$Y$959,19,0) -> -0.61 | U33: =IFERROR(__xludf.DUMMYFUNCTION("IFERROR(GOOGLEFINANCE(A33,""closeyest""),"""")"),0.12) -> 0.12 | V33: =IFERROR(__xludf.DUMMYFUNCTION("IFERROR(GOOGLEFINANCE(A33,""changepct""),"""")"),0.0) -> 0 | W33: =IFERROR(__xludf.DUMMYFUNCTION("IFERROR(GOOGLEFINANCE(A33,""priceopen""),"""")"),"") | X33: =IFERROR(__xludf.DUMMYFUNCTION("IFERROR(GOOGLEFINANCE(A33,""high""),"""")"),"") | Y33: =IFERROR(__xludf.DUMMYFUNCTION("IFERROR(GOOGLEFINANCE(A33,""low""),"""")"),"") | Z33: =IFERROR(__xludf.DUMMYFUNCTION("IFERROR(GOOGLEFINANCE(A33,""volume""),"""")"),0.0) -> 0 | AA33: =VLOOKUP(A33,Metrik!$C$2:$Y$959,5,0) -> Chemicals | AB33: =VLOOKUP(A33,Metrik!$C$2:$Y$959,3,0) -> Basic Materials
A34: ADMR | B34: {=VLOOKUP(A34,{Metrik!$C$2:$C$998,Metrik!$B$2:$B$998},2,0)} -> Alamtri Minerals Indonesia Tbk. | C34: =IFERROR(__xludf.DUMMYFUNCTION("GOOGLEFINANCE(""IDX:""&A34,""price"")"),1575.0) -> 1575 | D34: =IFERROR(__xludf.DUMMYFUNCTION("IF(A34="""","""", SPARKLINE( INDEX( GOOGLEFINANCE(""IDX:""&A34,""close"",TODAY()-365,TODAY()), ,2 ), {""linewidth"",1} )) "),"#N/A") -> #N/A | E34: IDXQ30 | F34: 4 Agustus 2026 | G34: =COUNTIFS($B$2:$B$1937,B34,$E$2:$E$1937,"<>") -> 9 | H34: =VLOOKUP(A34,Metrik!$C$2:$Y$959,8,0) -> 12.6 | I34: =VLOOKUP(A34,Metrik!$C$2:$Y$959,9,0) -> 2 | J34: =VLOOKUP(A34,Metrik!$C$2:$Y$959,10,0) -> 16.2 | K34: =VLOOKUP(A34,Metrik!$C$2:$Y$959,11,0) -> 9.1 | L34: =VLOOKUP(A34,Metrik!$C$2:$Y$959,12,0) -> 0.78 | M34: =VLOOKUP(A34,Metrik!$C$2:$Y$959,19,0) -> 110 | U34: =IFERROR(__xludf.DUMMYFUNCTION("IFERROR(GOOGLEFINANCE(A34,""closeyest""),"""")"),1465.0) -> 1465 | V34: =IFERROR(__xludf.DUMMYFUNCTION("IFERROR(GOOGLEFINANCE(A34,""changepct""),"""")"),7.51) -> 7.51 | W34: =IFERROR(__xludf.DUMMYFUNCTION("IFERROR(GOOGLEFINANCE(A34,""priceopen""),"""")"),1495.0) -> 1495 | X34: =IFERROR(__xludf.DUMMYFUNCTION("IFERROR(GOOGLEFINANCE(A34,""high""),"""")"),1640.0) -> 1640 | Y34: =IFERROR(__xludf.DUMMYFUNCTION("IFERROR(GOOGLEFINANCE(A34,""low""),"""")"),1485.0) -> 1485 | Z34: =IFERROR(__xludf.DUMMYFUNCTION("IFERROR(GOOGLEFINANCE(A34,""volume""),"""")"),4.32668E7) -> 43266800 | AA34: =VLOOKUP(A34,Metrik!$C$2:$Y$959,5,0) -> Coal | AB34: =VLOOKUP(A34,Metrik!$C$2:$Y$959,3,0) -> Energy
A35: ADMR | B35: {=VLOOKUP(A35,{Metrik!$C$2:$C$998,Metrik!$B$2:$B$998},2,0)} -> Alamtri Minerals Indonesia Tbk. | C35: =IFERROR(__xludf.DUMMYFUNCTION("GOOGLEFINANCE(""IDX:""&A35,""price"")"),1575.0) -> 1575 | D35: =IFERROR(__xludf.DUMMYFUNCTION("IF(A35="""","""", SPARKLINE( INDEX( GOOGLEFINANCE(""IDX:""&A35,""close"",TODAY()-365,TODAY()), ,2 ), {""linewidth"",1} )) "),"#N/A") -> #N/A | E35: Kompas100 | F35: 31 Juli 2026 | G35: =COUNTIFS($B$2:$B$1937,B35,$E$2:$E$1937,"<>") -> 9 | H35: =VLOOKUP(A35,Metrik!$C$2:$Y$959,8,0) -> 12.6 | I35: =VLOOKUP(A35,Metrik!$C$2:$Y$959,9,0) -> 2 | J35: =VLOOKUP(A35,Metrik!$C$2:$Y$959,10,0) -> 16.2 | K35: =VLOOKUP(A35,Metrik!$C$2:$Y$959,11,0) -> 9.1 | L35: =VLOOKUP(A35,Metrik!$C$2:$Y$959,12,0) -> 0.78 | M35: =VLOOKUP(A35,Metrik!$C$2:$Y$959,19,0) -> 110 | U35: =IFERROR(__xludf.DUMMYFUNCTION("IFERROR(GOOGLEFINANCE(A35,""closeyest""),"""")"),1465.0) -> 1465 | V35: =IFERROR(__xludf.DUMMYFUNCTION("IFERROR(GOOGLEFINANCE(A35,""changepct""),"""")"),7.51) -> 7.51 | W35: =IFERROR(__xludf.DUMMYFUNCTION("IFERROR(GOOGLEFINANCE(A35,""priceopen""),"""")"),1495.0) -> 1495 | X35: =IFERROR(__xludf.DUMMYFUNCTION("IFERROR(GOOGLEFINANCE(A35,""high""),"""")"),1640.0) -> 1640 | Y35: =IFERROR(__xludf.DUMMYFUNCTION("IFERROR(GOOGLEFINANCE(A35,""low""),"""")"),1485.0) -> 1485 | Z35: =IFERROR(__xludf.DUMMYFUNCTION("IFERROR(GOOGLEFINANCE(A35,""volume""),"""")"),4.32668E7) -> 43266800 | AA35: =VLOOKUP(A35,Metrik!$C$2:$Y$959,5,0) -> Coal | AB35: =VLOOKUP(A35,Metrik!$C$2:$Y$959,3,0) -> Energy
A36: ADMR | B36: {=VLOOKUP(A36,{Metrik!$C$2:$C$998,Metrik!$B$2:$B$998},2,0)} -> Alamtri Minerals Indonesia Tbk. | C36: =IFERROR(__xludf.DUMMYFUNCTION("GOOGLEFINANCE(""IDX:""&A36,""price"")"),1575.0) -> 1575 | D36: =IFERROR(__xludf.DUMMYFUNCTION("IF(A36="""","""", SPARKLINE( INDEX( GOOGLEFINANCE(""IDX:""&A36,""close"",TODAY()-365,TODAY()), ,2 ), {""linewidth"",1} )) "),"#N/A") -> #N/A | E36: LQ45 | F36: 31 Juli 2026 | G36: =COUNTIFS($B$2:$B$1937,B36,$E$2:$E$1937,"<>") -> 9 | H36: =VLOOKUP(A36,Metrik!$C$2:$Y$959,8,0) -> 12.6 | I36: =VLOOKUP(A36,Metrik!$C$2:$Y$959,9,0) -> 2 | J36: =VLOOKUP(A36,Metrik!$C$2:$Y$959,10,0) -> 16.2 | K36: =VLOOKUP(A36,Metrik!$C$2:$Y$959,11,0) -> 9.1 | L36: =VLOOKUP(A36,Metrik!$C$2:$Y$959,12,0) -> 0.78 | M36: =VLOOKUP(A36,Metrik!$C$2:$Y$959,19,0) -> 110 | U36: =IFERROR(__xludf.DUMMYFUNCTION("IFERROR(GOOGLEFINANCE(A36,""closeyest""),"""")"),1465.0) -> 1465 | V36: =IFERROR(__xludf.DUMMYFUNCTION("IFERROR(GOOGLEFINANCE(A36,""changepct""),"""")"),7.51) -> 7.51 | W36: =IFERROR(__xludf.DUMMYFUNCTION("IFERROR(GOOGLEFINANCE(A36,""priceopen""),"""")"),1495.0) -> 1495 | X36: =IFERROR(__xludf.DUMMYFUNCTION("IFERROR(GOOGLEFINANCE(A36,""high""),"""")"),1640.0) -> 1640 | Y36: =IFERROR(__xludf.DUMMYFUNCTION("IFERROR(GOOGLEFINANCE(A36,""low""),"""")"),1485.0) -> 1485 | Z36: =IFERROR(__xludf.DUMMYFUNCTION("IFERROR(GOOGLEFINANCE(A36,""volume""),"""")"),4.32668E7) -> 43266800 | AA36: =VLOOKUP(A36,Metrik!$C$2:$Y$959,5,0) -> Coal | AB36: =VLOOKUP(A36,Metrik!$C$2:$Y$959,3,0) -> Energy
A37: ADMR | B37: {=VLOOKUP(A37,{Metrik!$C$2:$C$998,Metrik!$B$2:$B$998},2,0)} -> Alamtri Minerals Indonesia Tbk. | C37: =IFERROR(__xludf.DUMMYFUNCTION("GOOGLEFINANCE(""IDX:""&A37,""price"")"),1575.0) -> 1575 | D37: =IFERROR(__xludf.DUMMYFUNCTION("IF(A37="""","""", SPARKLINE( INDEX( GOOGLEFINANCE(""IDX:""&A37,""close"",TODAY()-365,TODAY()), ,2 ), {""linewidth"",1} )) "),"#N/A") -> #N/A | E37: IDX80 | F37: 31 Juli 2026 | G37: =COUNTIFS($B$2:$B$1937,B37,$E$2:$E$1937,"<>") -> 9 | H37: =VLOOKUP(A37,Metrik!$C$2:$Y$959,8,0) -> 12.6 | I37: =VLOOKUP(A37,Metrik!$C$2:$Y$959,9,0) -> 2 | J37: =VLOOKUP(A37,Metrik!$C$2:$Y$959,10,0) -> 16.2 | K37: =VLOOKUP(A37,Metrik!$C$2:$Y$959,11,0) -> 9.1 | L37: =VLOOKUP(A37,Metrik!$C$2:$Y$959,12,0) -> 0.78 | M37: =VLOOKUP(A37,Metrik!$C$2:$Y$959,19,0) -> 110 | U37: =IFERROR(__xludf.DUMMYFUNCTION("IFERROR(GOOGLEFINANCE(A37,""closeyest""),"""")"),1465.0) -> 1465 | V37: =IFERROR(__xludf.DUMMYFUNCTION("IFERROR(GOOGLEFINANCE(A37,""changepct""),"""")"),7.51) -> 7.51 | W37: =IFERROR(__xludf.DUMMYFUNCTION("IFERROR(GOOGLEFINANCE(A37,""priceopen""),"""")"),1495.0) -> 1495 | X37: =IFERROR(__xludf.DUMMYFUNCTION("IFERROR(GOOGLEFINANCE(A37,""high""),"""")"),1640.0) -> 1640 | Y37: =IFERROR(__xludf.DUMMYFUNCTION("IFERROR(GOOGLEFINANCE(A37,""low""),"""")"),1485.0) -> 1485 | Z37: =IFERROR(__xludf.DUMMYFUNCTION("IFERROR(GOOGLEFINANCE(A37,""volume""),"""")"),4.32668E7) -> 43266800 | AA37: =VLOOKUP(A37,Metrik!$C$2:$Y$959,5,0) -> Coal | AB37: =VLOOKUP(A37,Metrik!$C$2:$Y$959,3,0) -> Energy
A38: ADMR | B38: {=VLOOKUP(A38,{Metrik!$C$2:$C$998,Metrik!$B$2:$B$998},2,0)} -> Alamtri Minerals Indonesia Tbk. | C38: =IFERROR(__xludf.DUMMYFUNCTION("GOOGLEFINANCE(""IDX:""&A38,""price"")"),1575.0) -> 1575 | D38: =IFERROR(__xludf.DUMMYFUNCTION("IF(A38="""","""", SPARKLINE( INDEX( GOOGLEFINANCE(""IDX:""&A38,""close"",TODAY()-365,TODAY()), ,2 ), {""linewidth"",1} )) "),"#N/A") -> #N/A | E38: IDX30 | F38: 31 Juli 2026 | G38: =COUNTIFS($B$2:$B$1937,B38,$E$2:$E$1937,"<>") -> 9 | H38: =VLOOKUP(A38,Metrik!$C$2:$Y$959,8,0) -> 12.6 | I38: =VLOOKUP(A38,Metrik!$C$2:$Y$959,9,0) -> 2 | J38: =VLOOKUP(A38,Metrik!$C$2:$Y$959,10,0) -> 16.2 | K38: =VLOOKUP(A38,Metrik!$C$2:$Y$959,11,0) -> 9.1 | L38: =VLOOKUP(A38,Metrik!$C$2:$Y$959,12,0) -> 0.78 | M38: =VLOOKUP(A38,Metrik!$C$2:$Y$959,19,0) -> 110 | U38: =IFERROR(__xludf.DUMMYFUNCTION("IFERROR(GOOGLEFINANCE(A38,""closeyest""),"""")"),1465.0) -> 1465 | V38: =IFERROR(__xludf.DUMMYFUNCTION("IFERROR(GOOGLEFINANCE(A38,""changepct""),"""")"),7.51) -> 7.51 | W38: =IFERROR(__xludf.DUMMYFUNCTION("IFERROR(GOOGLEFINANCE(A38,""priceopen""),"""")"),1495.0) -> 1495 | X38: =IFERROR(__xludf.DUMMYFUNCTION("IFERROR(GOOGLEFINANCE(A38,""high""),"""")"),1640.0) -> 1640 | Y38: =IFERROR(__xludf.DUMMYFUNCTION("IFERROR(GOOGLEFINANCE(A38,""low""),"""")"),1485.0) -> 1485 | Z38: =IFERROR(__xludf.DUMMYFUNCTION("IFERROR(GOOGLEFINANCE(A38,""volume""),"""")"),4.32668E7) -> 43266800 | AA38: =VLOOKUP(A38,Metrik!$C$2:$Y$959,5,0) -> Coal | AB38: =VLOOKUP(A38,Metrik!$C$2:$Y$959,3,0) -> Energy
A39: ADMR | B39: {=VLOOKUP(A39,{Metrik!$C$2:$C$998,Metrik!$B$2:$B$998},2,0)} -> Alamtri Minerals Indonesia Tbk. | C39: =IFERROR(__xludf.DUMMYFUNCTION("GOOGLEFINANCE(""IDX:""&A39,""price"")"),1575.0) -> 1575 | D39: =IFERROR(__xludf.DUMMYFUNCTION("IF(A39="""","""", SPARKLINE( INDEX( GOOGLEFINANCE(""IDX:""&A39,""close"",TODAY()-365,TODAY()), ,2 ), {""linewidth"",1} )) "),"#N/A") -> #N/A | E39: IDXSHAGROW | F39: 46356 | G39: =COUNTIFS($B$2:$B$1937,B39,$E$2:$E$1937,"<>") -> 9 | H39: =VLOOKUP(A39,Metrik!$C$2:$Y$959,8,0) -> 12.6 | I39: =VLOOKUP(A39,Metrik!$C$2:$Y$959,9,0) -> 2 | J39: =VLOOKUP(A39,Metrik!$C$2:$Y$959,10,0) -> 16.2 | K39: =VLOOKUP(A39,Metrik!$C$2:$Y$959,11,0) -> 9.1 | L39: =VLOOKUP(A39,Metrik!$C$2:$Y$959,12,0) -> 0.78 | M39: =VLOOKUP(A39,Metrik!$C$2:$Y$959,19,0) -> 110 | U39: =IFERROR(__xludf.DUMMYFUNCTION("IFERROR(GOOGLEFINANCE(A39,""closeyest""),"""")"),1465.0) -> 1465 | V39: =IFERROR(__xludf.DUMMYFUNCTION("IFERROR(GOOGLEFINANCE(A39,""changepct""),"""")"),7.51) -> 7.51 | W39: =IFERROR(__xludf.DUMMYFUNCTION("IFERROR(GOOGLEFINANCE(A39,""priceopen""),"""")"),1495.0) -> 1495 | X39: =IFERROR(__xludf.DUMMYFUNCTION("IFERROR(GOOGLEFINANCE(A39,""high""),"""")"),1640.0) -> 1640 | Y39: =IFERROR(__xludf.DUMMYFUNCTION("IFERROR(GOOGLEFINANCE(A39,""low""),"""")"),1485.0) -> 1485 | Z39: =IFERROR(__xludf.DUMMYFUNCTION("IFERROR(GOOGLEFINANCE(A39,""volume""),"""")"),4.32668E7) -> 43266800 | AA39: =VLOOKUP(A39,Metrik!$C$2:$Y$959,5,0) -> Coal | AB39: =VLOOKUP(A39,Metrik!$C$2:$Y$959,3,0) -> Energy
A40: ADMR | B40: {=VLOOKUP(A40,{Metrik!$C$2:$C$998,Metrik!$B$2:$B$998},2,0)} -> Alamtri Minerals Indonesia Tbk. | C40: =IFERROR(__xludf.DUMMYFUNCTION("GOOGLEFINANCE(""IDX:""&A40,""price"")"),1575.0) -> 1575 | D40: =IFERROR(__xludf.DUMMYFUNCTION("IF(A40="""","""", SPARKLINE( INDEX( GOOGLEFINANCE(""IDX:""&A40,""close"",TODAY()-365,TODAY()), ,2 ), {""linewidth"",1} )) "),"#N/A") -> #N/A | E40: Investor33 | F40: 46356 | G40: =COUNTIFS($B$2:$B$1937,B40,$E$2:$E$1937,"<>") -> 9 | H40: =VLOOKUP(A40,Metrik!$C$2:$Y$959,8,0) -> 12.6 | I40: =VLOOKUP(A40,Metrik!$C$2:$Y$959,9,0) -> 2 | J40: =VLOOKUP(A40,Metrik!$C$2:$Y$959,10,0) -> 16.2 | K40: =VLOOKUP(A40,Metrik!$C$2:$Y$959,11,0) -> 9.1 | L40: =VLOOKUP(A40,Metrik!$C$2:$Y$959,12,0) -> 0.78 | M40: =VLOOKUP(A40,Metrik!$C$2:$Y$959,19,0) -> 110 | U40: =IFERROR(__xludf.DUMMYFUNCTION("IFERROR(GOOGLEFINANCE(A40,""closeyest""),"""")"),1465.0) -> 1465 | V40: =IFERROR(__xludf.DUMMYFUNCTION("IFERROR(GOOGLEFINANCE(A40,""changepct""),"""")"),7.51) -> 7.51 | W40: =IFERROR(__xludf.DUMMYFUNCTION("IFERROR(GOOGLEFINANCE(A40,""priceopen""),"""")"),1495.0) -> 1495 | X40: =IFERROR(__xludf.DUMMYFUNCTION("IFERROR(GOOGLEFINANCE(A40,""high""),"""")"),1640.0) -> 1640 | Y40: =IFERROR(__xludf.DUMMYFUNCTION("IFERROR(GOOGLEFINANCE(A40,""low""),"""")"),1485.0) -> 1485 | Z40: =IFERROR(__xludf.DUMMYFUNCTION("IFERROR(GOOGLEFINANCE(A40,""volume""),"""")"),4.32668E7) -> 43266800 | AA40: =VLOOKUP(A40,Metrik!$C$2:$Y$959,5,0) -> Coal | AB40: =VLOOKUP(A40,Metrik!$C$2:$Y$959,3,0) -> Energy
A41: ADMR | B41: {=VLOOKUP(A41,{Metrik!$C$2:$C$998,Metrik!$B$2:$B$998},2,0)} -> Alamtri Minerals Indonesia Tbk. | C41: =IFERROR(__xludf.DUMMYFUNCTION("GOOGLEFINANCE(""IDX:""&A41,""price"")"),1575.0) -> 1575 | D41: =IFERROR(__xludf.DUMMYFUNCTION("IF(A41="""","""", SPARKLINE( INDEX( GOOGLEFINANCE(""IDX:""&A41,""close"",TODAY()-365,TODAY()), ,2 ), {""linewidth"",1} )) "),"#N/A") -> #N/A | E41: JII30 | F41: 46356 | G41: =COUNTIFS($B$2:$B$1937,B41,$E$2:$E$1937,"<>") -> 9 | H41: =VLOOKUP(A41,Metrik!$C$2:$Y$959,8,0) -> 12.6 | I41: =VLOOKUP(A41,Metrik!$C$2:$Y$959,9,0) -> 2 | J41: =VLOOKUP(A41,Metrik!$C$2:$Y$959,10,0) -> 16.2 | K41: =VLOOKUP(A41,Metrik!$C$2:$Y$959,11,0) -> 9.1 | L41: =VLOOKUP(A41,Metrik!$C$2:$Y$959,12,0) -> 0.78 | M41: =VLOOKUP(A41,Metrik!$C$2:$Y$959,19,0) -> 110 | U41: =IFERROR(__xludf.DUMMYFUNCTION("IFERROR(GOOGLEFINANCE(A41,""closeyest""),"""")"),1465.0) -> 1465 | V41: =IFERROR(__xludf.DUMMYFUNCTION("IFERROR(GOOGLEFINANCE(A41,""changepct""),"""")"),7.51) -> 7.51 | W41: =IFERROR(__xludf.DUMMYFUNCTION("IFERROR(GOOGLEFINANCE(A41,""priceopen""),"""")"),1495.0) -> 1495 | X41: =IFERROR(__xludf.DUMMYFUNCTION("IFERROR(GOOGLEFINANCE(A41,""high""),"""")"),1640.0) -> 1640 | Y41: =IFERROR(__xludf.DUMMYFUNCTION("IFERROR(GOOGLEFINANCE(A41,""low""),"""")"),1485.0) -> 1485 | Z41: =IFERROR(__xludf.DUMMYFUNCTION("IFERROR(GOOGLEFINANCE(A41,""volume""),"""")"),4.32668E7) -> 43266800 | AA41: =VLOOKUP(A41,Metrik!$C$2:$Y$959,5,0) -> Coal | AB41: =VLOOKUP(A41,Metrik!$C$2:$Y$959,3,0) -> Energy
A42: ADMR | B42: {=VLOOKUP(A42,{Metrik!$C$2:$C$998,Metrik!$B$2:$B$998},2,0)} -> Alamtri Minerals Indonesia Tbk. | C42: =IFERROR(__xludf.DUMMYFUNCTION("GOOGLEFINANCE(""IDX:""&A42,""price"")"),1575.0) -> 1575 | D42: =IFERROR(__xludf.DUMMYFUNCTION("IF(A42="""","""", SPARKLINE( INDEX( GOOGLEFINANCE(""IDX:""&A42,""close"",TODAY()-365,TODAY()), ,2 ), {""linewidth"",1} )) "),"#N/A") -> #N/A | E42: JII70 | F42: 46356 | G42: =COUNTIFS($B$2:$B$1937,B42,$E$2:$E$1937,"<>") -> 9 | H42: =VLOOKUP(A42,Metrik!$C$2:$Y$959,8,0) -> 12.6 | I42: =VLOOKUP(A42,Metrik!$C$2:$Y$959,9,0) -> 2 | J42: =VLOOKUP(A42,Metrik!$C$2:$Y$959,10,0) -> 16.2 | K42: =VLOOKUP(A42,Metrik!$C$2:$Y$959,11,0) -> 9.1 | L42: =VLOOKUP(A42,Metrik!$C$2:$Y$959,12,0) -> 0.78 | M42: =VLOOKUP(A42,Metrik!$C$2:$Y$959,19,0) -> 110 | U42: =IFERROR(__xludf.DUMMYFUNCTION("IFERROR(GOOGLEFINANCE(A42,""closeyest""),"""")"),1465.0) -> 1465 | V42: =IFERROR(__xludf.DUMMYFUNCTION("IFERROR(GOOGLEFINANCE(A42,""changepct""),"""")"),7.51) -> 7.51 | W42: =IFERROR(__xludf.DUMMYFUNCTION("IFERROR(GOOGLEFINANCE(A42,""priceopen""),"""")"),1495.0) -> 1495 | X42: =IFERROR(__xludf.DUMMYFUNCTION("IFERROR(GOOGLEFINANCE(A42,""high""),"""")"),1640.0) -> 1640 | Y42: =IFERROR(__xludf.DUMMYFUNCTION("IFERROR(GOOGLEFINANCE(A42,""low""),"""")"),1485.0) -> 1485 | Z42: =IFERROR(__xludf.DUMMYFUNCTION("IFERROR(GOOGLEFINANCE(A42,""volume""),"""")"),4.32668E7) -> 43266800 | AA42: =VLOOKUP(A42,Metrik!$C$2:$Y$959,5,0) -> Coal | AB42: =VLOOKUP(A42,Metrik!$C$2:$Y$959,3,0) -> Energy
A43: ADRO | B43: {=VLOOKUP(A43,{Metrik!$C$2:$C$998,Metrik!$B$2:$B$998},2,0)} -> Alamtri Resources Indonesia Tbk. | C43: =IFERROR(__xludf.DUMMYFUNCTION("GOOGLEFINANCE(""IDX:""&A43,""price"")"),2280.0) -> 2280 | D43: =IFERROR(__xludf.DUMMYFUNCTION("IF(A43="""","""", SPARKLINE( INDEX( GOOGLEFINANCE(""IDX:""&A43,""close"",TODAY()-365,TODAY()), ,2 ), {""linewidth"",1} )) "),"#N/A") -> #N/A | E43: BISNIS-27 | F43: 30 Oktober 2026 | G43: =COUNTIFS($B$2:$B$1937,B43,$E$2:$E$1937,"<>") -> 14 | H43: =VLOOKUP(A43,Metrik!$C$2:$Y$959,8,0) -> 8 | I43: =VLOOKUP(A43,Metrik!$C$2:$Y$959,9,0) -> 0.73 | J43: =VLOOKUP(A43,Metrik!$C$2:$Y$959,10,0) -> 9.1 | K43: =VLOOKUP(A43,Metrik!$C$2:$Y$959,11,0) -> 6.9 | L43: =VLOOKUP(A43,Metrik!$C$2:$Y$959,12,0) -> 0.32 | M43: =VLOOKUP(A43,Metrik!$C$2:$Y$959,19,0) -> 110 | U43: =IFERROR(__xludf.DUMMYFUNCTION("IFERROR(GOOGLEFINANCE(A43,""closeyest""),"""")"),2250.0) -> 2250 | V43: =IFERROR(__xludf.DUMMYFUNCTION("IFERROR(GOOGLEFINANCE(A43,""changepct""),"""")"),1.33) -> 1.33 | W43: =IFERROR(__xludf.DUMMYFUNCTION("IFERROR(GOOGLEFINANCE(A43,""priceopen""),"""")"),2270.0) -> 2270 | X43: =IFERROR(__xludf.DUMMYFUNCTION("IFERROR(GOOGLEFINANCE(A43,""high""),"""")"),2340.0) -> 2340 | Y43: =IFERROR(__xludf.DUMMYFUNCTION("IFERROR(GOOGLEFINANCE(A43,""low""),"""")"),2250.0) -> 2250 | Z43: =IFERROR(__xludf.DUMMYFUNCTION("IFERROR(GOOGLEFINANCE(A43,""volume""),"""")"),3.69179E7) -> 36917900 | AA43: =VLOOKUP(A43,Metrik!$C$2:$Y$959,5,0) -> Coal | AB43: =VLOOKUP(A43,Metrik!$C$2:$Y$959,3,0) -> Energy
A44: ADRO | B44: {=VLOOKUP(A44,{Metrik!$C$2:$C$998,Metrik!$B$2:$B$998},2,0)} -> Alamtri Resources Indonesia Tbk. | C44: =IFERROR(__xludf.DUMMYFUNCTION("GOOGLEFINANCE(""IDX:""&A44,""price"")"),2280.0) -> 2280 | D44: =IFERROR(__xludf.DUMMYFUNCTION("IF(A44="""","""", SPARKLINE( INDEX( GOOGLEFINANCE(""IDX:""&A44,""close"",TODAY()-365,TODAY()), ,2 ), {""linewidth"",1} )) "),"#N/A") -> #N/A | E44: IDX30 | F44: 31 Juli 2026 | G44: =COUNTIFS($B$2:$B$1937,B44,$E$2:$E$1937,"<>") -> 14 | H44: =VLOOKUP(A44,Metrik!$C$2:$Y$959,8,0) -> 8 | I44: =VLOOKUP(A44,Metrik!$C$2:$Y$959,9,0) -> 0.73 | J44: =VLOOKUP(A44,Metrik!$C$2:$Y$959,10,0) -> 9.1 | K44: =VLOOKUP(A44,Metrik!$C$2:$Y$959,11,0) -> 6.9 | L44: =VLOOKUP(A44,Metrik!$C$2:$Y$959,12,0) -> 0.32 | M44: =VLOOKUP(A44,Metrik!$C$2:$Y$959,19,0) -> 110 | U44: =IFERROR(__xludf.DUMMYFUNCTION("IFERROR(GOOGLEFINANCE(A44,""closeyest""),"""")"),2250.0) -> 2250 | V44: =IFERROR(__xludf.DUMMYFUNCTION("IFERROR(GOOGLEFINANCE(A44,""changepct""),"""")"),1.33) -> 1.33 | W44: =IFERROR(__xludf.DUMMYFUNCTION("IFERROR(GOOGLEFINANCE(A44,""priceopen""),"""")"),2270.0) -> 2270 | X44: =IFERROR(__xludf.DUMMYFUNCTION("IFERROR(GOOGLEFINANCE(A44,""high""),"""")"),2340.0) -> 2340 | Y44: =IFERROR(__xludf.DUMMYFUNCTION("IFERROR(GOOGLEFINANCE(A44,""low""),"""")"),2250.0) -> 2250 | Z44: =IFERROR(__xludf.DUMMYFUNCTION("IFERROR(GOOGLEFINANCE(A44,""volume""),"""")"),3.69179E7) -> 36917900 | AA44: =VLOOKUP(A44,Metrik!$C$2:$Y$959,5,0) -> Coal | AB44: =VLOOKUP(A44,Metrik!$C$2:$Y$959,3,0) -> Energy
A45: ADRO | B45: {=VLOOKUP(A45,{Metrik!$C$2:$C$998,Metrik!$B$2:$B$998},2,0)} -> Alamtri Resources Indonesia Tbk. | C45: =IFERROR(__xludf.DUMMYFUNCTION("GOOGLEFINANCE(""IDX:""&A45,""price"")"),2280.0) -> 2280 | D45: =IFERROR(__xludf.DUMMYFUNCTION("IF(A45="""","""", SPARKLINE( INDEX( GOOGLEFINANCE(""IDX:""&A45,""close"",TODAY()-365,TODAY()), ,2 ), {""linewidth"",1} )) "),"#N/A") -> #N/A | E45: IDX80 | F45: 31 Juli 2026 | G45: =COUNTIFS($B$2:$B$1937,B45,$E$2:$E$1937,"<>") -> 14 | H45: =VLOOKUP(A45,Metrik!$C$2:$Y$959,8,0) -> 8 | I45: =VLOOKUP(A45,Metrik!$C$2:$Y$959,9,0) -> 0.73 | J45: =VLOOKUP(A45,Metrik!$C$2:$Y$959,10,0) -> 9.1 | K45: =VLOOKUP(A45,Metrik!$C$2:$Y$959,11,0) -> 6.9 | L45: =VLOOKUP(A45,Metrik!$C$2:$Y$959,12,0) -> 0.32 | M45: =VLOOKUP(A45,Metrik!$C$2:$Y$959,19,0) -> 110 | U45: =IFERROR(__xludf.DUMMYFUNCTION("IFERROR(GOOGLEFINANCE(A45,""closeyest""),"""")"),2250.0) -> 2250 | V45: =IFERROR(__xludf.DUMMYFUNCTION("IFERROR(GOOGLEFINANCE(A45,""changepct""),"""")"),1.33) -> 1.33 | W45: =IFERROR(__xludf.DUMMYFUNCTION("IFERROR(GOOGLEFINANCE(A45,""priceopen""),"""")"),2270.0) -> 2270 | X45: =IFERROR(__xludf.DUMMYFUNCTION("IFERROR(GOOGLEFINANCE(A45,""high""),"""")"),2340.0) -> 2340 | Y45: =IFERROR(__xludf.DUMMYFUNCTION("IFERROR(GOOGLEFINANCE(A45,""low""),"""")"),2250.0) -> 2250 | Z45: =IFERROR(__xludf.DUMMYFUNCTION("IFERROR(GOOGLEFINANCE(A45,""volume""),"""")"),3.69179E7) -> 36917900 | AA45: =VLOOKUP(A45,Metrik!$C$2:$Y$959,5,0) -> Coal | AB45: =VLOOKUP(A45,Metrik!$C$2:$Y$959,3,0) -> Energy
A46: ADRO | B46: {=VLOOKUP(A46,{Metrik!$C$2:$C$998,Metrik!$B$2:$B$998},2,0)} -> Alamtri Resources Indonesia Tbk. | C46: =IFERROR(__xludf.DUMMYFUNCTION("GOOGLEFINANCE(""IDX:""&A46,""price"")"),2280.0) -> 2280 | D46: =IFERROR(__xludf.DUMMYFUNCTION("IF(A46="""","""", SPARKLINE( INDEX( GOOGLEFINANCE(""IDX:""&A46,""close"",TODAY()-365,TODAY()), ,2 ), {""linewidth"",1} )) "),"#N/A") -> #N/A | E46: IDXG30 | F46: 4 Agustus 2026 | G46: =COUNTIFS($B$2:$B$1937,B46,$E$2:$E$1937,"<>") -> 14 | H46: =VLOOKUP(A46,Metrik!$C$2:$Y$959,8,0) -> 8 | I46: =VLOOKUP(A46,Metrik!$C$2:$Y$959,9,0) -> 0.73 | J46: =VLOOKUP(A46,Metrik!$C$2:$Y$959,10,0) -> 9.1 | K46: =VLOOKUP(A46,Metrik!$C$2:$Y$959,11,0) -> 6.9 | L46: =VLOOKUP(A46,Metrik!$C$2:$Y$959,12,0) -> 0.32 | M46: =VLOOKUP(A46,Metrik!$C$2:$Y$959,19,0) -> 110 | U46: =IFERROR(__xludf.DUMMYFUNCTION("IFERROR(GOOGLEFINANCE(A46,""closeyest""),"""")"),2250.0) -> 2250 | V46: =IFERROR(__xludf.DUMMYFUNCTION("IFERROR(GOOGLEFINANCE(A46,""changepct""),"""")"),1.33) -> 1.33 | W46: =IFERROR(__xludf.DUMMYFUNCTION("IFERROR(GOOGLEFINANCE(A46,""priceopen""),"""")"),2270.0) -> 2270 | X46: =IFERROR(__xludf.DUMMYFUNCTION("IFERROR(GOOGLEFINANCE(A46,""high""),"""")"),2340.0) -> 2340 | Y46: =IFERROR(__xludf.DUMMYFUNCTION("IFERROR(GOOGLEFINANCE(A46,""low""),"""")"),2250.0) -> 2250 | Z46: =IFERROR(__xludf.DUMMYFUNCTION("IFERROR(GOOGLEFINANCE(A46,""volume""),"""")"),3.69179E7) -> 36917900 | AA46: =VLOOKUP(A46,Metrik!$C$2:$Y$959,5,0) -> Coal | AB46: =VLOOKUP(A46,Metrik!$C$2:$Y$959,3,0) -> Energy
A47: ADRO | B47: {=VLOOKUP(A47,{Metrik!$C$2:$C$998,Metrik!$B$2:$B$998},2,0)} -> Alamtri Resources Indonesia Tbk. | C47: =IFERROR(__xludf.DUMMYFUNCTION("GOOGLEFINANCE(""IDX:""&A47,""price"")"),2280.0) -> 2280 | D47: =IFERROR(__xludf.DUMMYFUNCTION("IF(A47="""","""", SPARKLINE( INDEX( GOOGLEFINANCE(""IDX:""&A47,""close"",TODAY()-365,TODAY()), ,2 ), {""linewidth"",1} )) "),"#N/A") -> #N/A | E47: IDXHIDIV20 | F47: 2 Februari 2027 | G47: =COUNTIFS($B$2:$B$1937,B47,$E$2:$E$1937,"<>") -> 14 | H47: =VLOOKUP(A47,Metrik!$C$2:$Y$959,8,0) -> 8 | I47: =VLOOKUP(A47,Metrik!$C$2:$Y$959,9,0) -> 0.73 | J47: =VLOOKUP(A47,Metrik!$C$2:$Y$959,10,0) -> 9.1 | K47: =VLOOKUP(A47,Metrik!$C$2:$Y$959,11,0) -> 6.9 | L47: =VLOOKUP(A47,Metrik!$C$2:$Y$959,12,0) -> 0.32 | M47: =VLOOKUP(A47,Metrik!$C$2:$Y$959,19,0) -> 110 | U47: =IFERROR(__xludf.DUMMYFUNCTION("IFERROR(GOOGLEFINANCE(A47,""closeyest""),"""")"),2250.0) -> 2250 | V47: =IFERROR(__xludf.DUMMYFUNCTION("IFERROR(GOOGLEFINANCE(A47,""changepct""),"""")"),1.33) -> 1.33 | W47: =IFERROR(__xludf.DUMMYFUNCTION("IFERROR(GOOGLEFINANCE(A47,""priceopen""),"""")"),2270.0) -> 2270 | X47: =IFERROR(__xludf.DUMMYFUNCTION("IFERROR(GOOGLEFINANCE(A47,""high""),"""")"),2340.0) -> 2340 | Y47: =IFERROR(__xludf.DUMMYFUNCTION("IFERROR(GOOGLEFINANCE(A47,""low""),"""")"),2250.0) -> 2250 | Z47: =IFERROR(__xludf.DUMMYFUNCTION("IFERROR(GOOGLEFINANCE(A47,""volume""),"""")"),3.69179E7) -> 36917900 | AA47: =VLOOKUP(A47,Metrik!$C$2:$Y$959,5,0) -> Coal | AB47: =VLOOKUP(A47,Metrik!$C$2:$Y$959,3,0) -> Energy
A48: ADRO | B48: {=VLOOKUP(A48,{Metrik!$C$2:$C$998,Metrik!$B$2:$B$998},2,0)} -> Alamtri Resources Indonesia Tbk. | C48: =IFERROR(__xludf.DUMMYFUNCTION("GOOGLEFINANCE(""IDX:""&A48,""price"")"),2280.0) -> 2280 | D48: =IFERROR(__xludf.DUMMYFUNCTION("IF(A48="""","""", SPARKLINE( INDEX( GOOGLEFINANCE(""IDX:""&A48,""close"",TODAY()-365,TODAY()), ,2 ), {""linewidth"",1} )) "),"#N/A") -> #N/A | E48: Kompas100 | F48: 31 Juli 2026 | G48: =COUNTIFS($B$2:$B$1937,B48,$E$2:$E$1937,"<>") -> 14 | H48: =VLOOKUP(A48,Metrik!$C$2:$Y$959,8,0) -> 8 | I48: =VLOOKUP(A48,Metrik!$C$2:$Y$959,9,0) -> 0.73 | J48: =VLOOKUP(A48,Metrik!$C$2:$Y$959,10,0) -> 9.1 | K48: =VLOOKUP(A48,Metrik!$C$2:$Y$959,11,0) -> 6.9 | L48: =VLOOKUP(A48,Metrik!$C$2:$Y$959,12,0) -> 0.32 | M48: =VLOOKUP(A48,Metrik!$C$2:$Y$959,19,0) -> 110 | U48: =IFERROR(__xludf.DUMMYFUNCTION("IFERROR(GOOGLEFINANCE(A48,""closeyest""),"""")"),2250.0) -> 2250 | V48: =IFERROR(__xludf.DUMMYFUNCTION("IFERROR(GOOGLEFINANCE(A48,""changepct""),"""")"),1.33) -> 1.33 | W48: =IFERROR(__xludf.DUMMYFUNCTION("IFERROR(GOOGLEFINANCE(A48,""priceopen""),"""")"),2270.0) -> 2270 | X48: =IFERROR(__xludf.DUMMYFUNCTION("IFERROR(GOOGLEFINANCE(A48,""high""),"""")"),2340.0) -> 2340 | Y48: =IFERROR(__xludf.DUMMYFUNCTION("IFERROR(GOOGLEFINANCE(A48,""low""),"""")"),2250.0) -> 2250 | Z48: =IFERROR(__xludf.DUMMYFUNCTION("IFERROR(GOOGLEFINANCE(A48,""volume""),"""")"),3.69179E7) -> 36917900 | AA48: =VLOOKUP(A48,Metrik!$C$2:$Y$959,5,0) -> Coal | AB48: =VLOOKUP(A48,Metrik!$C$2:$Y$959,3,0) -> Energy
A49: ADRO | B49: {=VLOOKUP(A49,{Metrik!$C$2:$C$998,Metrik!$B$2:$B$998},2,0)} -> Alamtri Resources Indonesia Tbk. | C49: =IFERROR(__xludf.DUMMYFUNCTION("GOOGLEFINANCE(""IDX:""&A49,""price"")"),2280.0) -> 2280 | D49: =IFERROR(__xludf.DUMMYFUNCTION("IF(A49="""","""", SPARKLINE( INDEX( GOOGLEFINANCE(""IDX:""&A49,""close"",TODAY()-365,TODAY()), ,2 ), {""linewidth"",1} )) "),"#N/A") -> #N/A | E49: LQ45 | F49: 31 Juli 2026 | G49: =COUNTIFS($B$2:$B$1937,B49,$E$2:$E$1937,"<>") -> 14 | H49: =VLOOKUP(A49,Metrik!$C$2:$Y$959,8,0) -> 8 | I49: =VLOOKUP(A49,Metrik!$C$2:$Y$959,9,0) -> 0.73 | J49: =VLOOKUP(A49,Metrik!$C$2:$Y$959,10,0) -> 9.1 | K49: =VLOOKUP(A49,Metrik!$C$2:$Y$959,11,0) -> 6.9 | L49: =VLOOKUP(A49,Metrik!$C$2:$Y$959,12,0) -> 0.32 | M49: =VLOOKUP(A49,Metrik!$C$2:$Y$959,19,0) -> 110 | U49: =IFERROR(__xludf.DUMMYFUNCTION("IFERROR(GOOGLEFINANCE(A49,""closeyest""),"""")"),2250.0) -> 2250 | V49: =IFERROR(__xludf.DUMMYFUNCTION("IFERROR(GOOGLEFINANCE(A49,""changepct""),"""")"),1.33) -> 1.33 | W49: =IFERROR(__xludf.DUMMYFUNCTION("IFERROR(GOOGLEFINANCE(A49,""priceopen""),"""")"),2270.0) -> 2270 | X49: =IFERROR(__xludf.DUMMYFUNCTION("IFERROR(GOOGLEFINANCE(A49,""high""),"""")"),2340.0) -> 2340 | Y49: =IFERROR(__xludf.DUMMYFUNCTION("IFERROR(GOOGLEFINANCE(A49,""low""),"""")"),2250.0) -> 2250 | Z49: =IFERROR(__xludf.DUMMYFUNCTION("IFERROR(GOOGLEFINANCE(A49,""volume""),"""")"),3.69179E7) -> 36917900 | AA49: =VLOOKUP(A49,Metrik!$C$2:$Y$959,5,0) -> Coal | AB49: =VLOOKUP(A49,Metrik!$C$2:$Y$959,3,0) -> Energy
A50: ADRO | B50: {=VLOOKUP(A50,{Metrik!$C$2:$C$998,Metrik!$B$2:$B$998},2,0)} -> Alamtri Resources Indonesia Tbk. | C50: =IFERROR(__xludf.DUMMYFUNCTION("GOOGLEFINANCE(""IDX:""&A50,""price"")"),2280.0) -> 2280 | D50: =IFERROR(__xludf.DUMMYFUNCTION("IF(A50="""","""", SPARKLINE( INDEX( GOOGLEFINANCE(""IDX:""&A50,""close"",TODAY()-365,TODAY()), ,2 ), {""linewidth"",1} )) "),"#N/A") -> #N/A | E50: IDXV30 | F50: 4 Agustus 2026 | G50: =COUNTIFS($B$2:$B$1937,B50,$E$2:$E$1937,"<>") -> 14 | H50: =VLOOKUP(A50,Metrik!$C$2:$Y$959,8,0) -> 8 | I50: =VLOOKUP(A50,Metrik!$C$2:$Y$959,9,0) -> 0.73 | J50: =VLOOKUP(A50,Metrik!$C$2:$Y$959,10,0) -> 9.1 | K50: =VLOOKUP(A50,Metrik!$C$2:$Y$959,11,0) -> 6.9 | L50: =VLOOKUP(A50,Metrik!$C$2:$Y$959,12,0) -> 0.32 | M50: =VLOOKUP(A50,Metrik!$C$2:$Y$959,19,0) -> 110 | U50: =IFERROR(__xludf.DUMMYFUNCTION("IFERROR(GOOGLEFINANCE(A50,""closeyest""),"""")"),2250.0) -> 2250 | V50: =IFERROR(__xludf.DUMMYFUNCTION("IFERROR(GOOGLEFINANCE(A50,""changepct""),"""")"),1.33) -> 1.33 | W50: =IFERROR(__xludf.DUMMYFUNCTION("IFERROR(GOOGLEFINANCE(A50,""priceopen""),"""")"),2270.0) -> 2270 | X50: =IFERROR(__xludf.DUMMYFUNCTION("IFERROR(GOOGLEFINANCE(A50,""high""),"""")"),2340.0) -> 2340 | Y50: =IFERROR(__xludf.DUMMYFUNCTION("IFERROR(GOOGLEFINANCE(A50,""low""),"""")"),2250.0) -> 2250 | Z50: =IFERROR(__xludf.DUMMYFUNCTION("IFERROR(GOOGLEFINANCE(A50,""volume""),"""")"),3.69179E7) -> 36917900 | AA50: =VLOOKUP(A50,Metrik!$C$2:$Y$959,5,0) -> Coal | AB50: =VLOOKUP(A50,Metrik!$C$2:$Y$959,3,0) -> Energy
A51: ADRO | B51: {=VLOOKUP(A51,{Metrik!$C$2:$C$998,Metrik!$B$2:$B$998},2,0)} -> Alamtri Resources Indonesia Tbk. | C51: =IFERROR(__xludf.DUMMYFUNCTION("GOOGLEFINANCE(""IDX:""&A51,""price"")"),2280.0) -> 2280 | D51: =IFERROR(__xludf.DUMMYFUNCTION("IF(A51="""","""", SPARKLINE( INDEX( GOOGLEFINANCE(""IDX:""&A51,""close"",TODAY()-365,TODAY()), ,2 ), {""linewidth"",1} )) "),"#N/A") -> #N/A | E51: FTSE Large Cap | F51: Juni 2026 | G51: =COUNTIFS($B$2:$B$1937,B51,$E$2:$E$1937,"<>") -> 14 | H51: =VLOOKUP(A51,Metrik!$C$2:$Y$959,8,0) -> 8 | I51: =VLOOKUP(A51,Metrik!$C$2:$Y$959,9,0) -> 0.73 | J51: =VLOOKUP(A51,Metrik!$C$2:$Y$959,10,0) -> 9.1 | K51: =VLOOKUP(A51,Metrik!$C$2:$Y$959,11,0) -> 6.9 | L51: =VLOOKUP(A51,Metrik!$C$2:$Y$959,12,0) -> 0.32 | M51: =VLOOKUP(A51,Metrik!$C$2:$Y$959,19,0) -> 110 | U51: =IFERROR(__xludf.DUMMYFUNCTION("IFERROR(GOOGLEFINANCE(A51,""closeyest""),"""")"),2250.0) -> 2250 | V51: =IFERROR(__xludf.DUMMYFUNCTION("IFERROR(GOOGLEFINANCE(A51,""changepct""),"""")"),1.33) -> 1.33 | W51: =IFERROR(__xludf.DUMMYFUNCTION("IFERROR(GOOGLEFINANCE(A51,""priceopen""),"""")"),2270.0) -> 2270 | X51: =IFERROR(__xludf.DUMMYFUNCTION("IFERROR(GOOGLEFINANCE(A51,""high""),"""")"),2340.0) -> 2340 | Y51: =IFERROR(__xludf.DUMMYFUNCTION("IFERROR(GOOGLEFINANCE(A51,""low""),"""")"),2250.0) -> 2250 | Z51: =IFERROR(__xludf.DUMMYFUNCTION("IFERROR(GOOGLEFINANCE(A51,""volume""),"""")"),3.69179E7) -> 36917900 | AA51: =VLOOKUP(A51,Metrik!$C$2:$Y$959,5,0) -> Coal | AB51: =VLOOKUP(A51,Metrik!$C$2:$Y$959,3,0) -> Energy
A52: ADRO | B52: {=VLOOKUP(A52,{Metrik!$C$2:$C$998,Metrik!$B$2:$B$998},2,0)} -> Alamtri Resources Indonesia Tbk. | C52: =IFERROR(__xludf.DUMMYFUNCTION("GOOGLEFINANCE(""IDX:""&A52,""price"")"),2280.0) -> 2280 | D52: =IFERROR(__xludf.DUMMYFUNCTION("IF(A52="""","""", SPARKLINE( INDEX( GOOGLEFINANCE(""IDX:""&A52,""close"",TODAY()-365,TODAY()), ,2 ), {""linewidth"",1} )) "),"#N/A") -> #N/A | E52: MSCI Small Cap | F52: 12 Agustus 2026 | G52: =COUNTIFS($B$2:$B$1937,B52,$E$2:$E$1937,"<>") -> 14 | H52: =VLOOKUP(A52,Metrik!$C$2:$Y$959,8,0) -> 8 | I52: =VLOOKUP(A52,Metrik!$C$2:$Y$959,9,0) -> 0.73 | J52: =VLOOKUP(A52,Metrik!$C$2:$Y$959,10,0) -> 9.1 | K52: =VLOOKUP(A52,Metrik!$C$2:$Y$959,11,0) -> 6.9 | L52: =VLOOKUP(A52,Metrik!$C$2:$Y$959,12,0) -> 0.32 | M52: =VLOOKUP(A52,Metrik!$C$2:$Y$959,19,0) -> 110 | U52: =IFERROR(__xludf.DUMMYFUNCTION("IFERROR(GOOGLEFINANCE(A52,""closeyest""),"""")"),2250.0) -> 2250 | V52: =IFERROR(__xludf.DUMMYFUNCTION("IFERROR(GOOGLEFINANCE(A52,""changepct""),"""")"),1.33) -> 1.33 | W52: =IFERROR(__xludf.DUMMYFUNCTION("IFERROR(GOOGLEFINANCE(A52,""priceopen""),"""")"),2270.0) -> 2270 | X52: =IFERROR(__xludf.DUMMYFUNCTION("IFERROR(GOOGLEFINANCE(A52,""high""),"""")"),2340.0) -> 2340 | Y52: =IFERROR(__xludf.DUMMYFUNCTION("IFERROR(GOOGLEFINANCE(A52,""low""),"""")"),2250.0) -> 2250 | Z52: =IFERROR(__xludf.DUMMYFUNCTION("IFERROR(GOOGLEFINANCE(A52,""volume""),"""")"),3.69179E7) -> 36917900 | AA52: =VLOOKUP(A52,Metrik!$C$2:$Y$959,5,0) -> Coal | AB52: =VLOOKUP(A52,Metrik!$C$2:$Y$959,3,0) -> Energy
A53: ADRO | B53: {=VLOOKUP(A53,{Metrik!$C$2:$C$998,Metrik!$B$2:$B$998},2,0)} -> Alamtri Resources Indonesia Tbk. | C53: =IFERROR(__xludf.DUMMYFUNCTION("GOOGLEFINANCE(""IDX:""&A53,""price"")"),2280.0) -> 2280 | D53: =IFERROR(__xludf.DUMMYFUNCTION("IF(A53="""","""", SPARKLINE( INDEX( GOOGLEFINANCE(""IDX:""&A53,""close"",TODAY()-365,TODAY()), ,2 ), {""linewidth"",1} )) "),"#N/A") -> #N/A | E53: IDXSHAGROW | F53: 46356 | G53: =COUNTIFS($B$2:$B$1937,B53,$E$2:$E$1937,"<>") -> 14 | H53: =VLOOKUP(A53,Metrik!$C$2:$Y$959,8,0) -> 8 | I53: =VLOOKUP(A53,Metrik!$C$2:$Y$959,9,0) -> 0.73 | J53: =VLOOKUP(A53,Metrik!$C$2:$Y$959,10,0) -> 9.1 | K53: =VLOOKUP(A53,Metrik!$C$2:$Y$959,11,0) -> 6.9 | L53: =VLOOKUP(A53,Metrik!$C$2:$Y$959,12,0) -> 0.32 | M53: =VLOOKUP(A53,Metrik!$C$2:$Y$959,19,0) -> 110 | U53: =IFERROR(__xludf.DUMMYFUNCTION("IFERROR(GOOGLEFINANCE(A53,""closeyest""),"""")"),2250.0) -> 2250 | V53: =IFERROR(__xludf.DUMMYFUNCTION("IFERROR(GOOGLEFINANCE(A53,""changepct""),"""")"),1.33) -> 1.33 | W53: =IFERROR(__xludf.DUMMYFUNCTION("IFERROR(GOOGLEFINANCE(A53,""priceopen""),"""")"),2270.0) -> 2270 | X53: =IFERROR(__xludf.DUMMYFUNCTION("IFERROR(GOOGLEFINANCE(A53,""high""),"""")"),2340.0) -> 2340 | Y53: =IFERROR(__xludf.DUMMYFUNCTION("IFERROR(GOOGLEFINANCE(A53,""low""),"""")"),2250.0) -> 2250 | Z53: =IFERROR(__xludf.DUMMYFUNCTION("IFERROR(GOOGLEFINANCE(A53,""volume""),"""")"),3.69179E7) -> 36917900 | AA53: =VLOOKUP(A53,Metrik!$C$2:$Y$959,5,0) -> Coal | AB53: =VLOOKUP(A53,Metrik!$C$2:$Y$959,3,0) -> Energy
A54: ADRO | B54: {=VLOOKUP(A54,{Metrik!$C$2:$C$998,Metrik!$B$2:$B$998},2,0)} -> Alamtri Resources Indonesia Tbk. | C54: =IFERROR(__xludf.DUMMYFUNCTION("GOOGLEFINANCE(""IDX:""&A54,""price"")"),2280.0) -> 2280 | D54: =IFERROR(__xludf.DUMMYFUNCTION("IF(A54="""","""", SPARKLINE( INDEX( GOOGLEFINANCE(""IDX:""&A54,""close"",TODAY()-365,TODAY()), ,2 ), {""linewidth"",1} )) "),"#N/A") -> #N/A | E54: Investor33 | F54: 46356 | G54: =COUNTIFS($B$2:$B$1937,B54,$E$2:$E$1937,"<>") -> 14 | H54: =VLOOKUP(A54,Metrik!$C$2:$Y$959,8,0) -> 8 | I54: =VLOOKUP(A54,Metrik!$C$2:$Y$959,9,0) -> 0.73 | J54: =VLOOKUP(A54,Metrik!$C$2:$Y$959,10,0) -> 9.1 | K54: =VLOOKUP(A54,Metrik!$C$2:$Y$959,11,0) -> 6.9 | L54: =VLOOKUP(A54,Metrik!$C$2:$Y$959,12,0) -> 0.32 | M54: =VLOOKUP(A54,Metrik!$C$2:$Y$959,19,0) -> 110 | U54: =IFERROR(__xludf.DUMMYFUNCTION("IFERROR(GOOGLEFINANCE(A54,""closeyest""),"""")"),2250.0) -> 2250 | V54: =IFERROR(__xludf.DUMMYFUNCTION("IFERROR(GOOGLEFINANCE(A54,""changepct""),"""")"),1.33) -> 1.33 | W54: =IFERROR(__xludf.DUMMYFUNCTION("IFERROR(GOOGLEFINANCE(A54,""priceopen""),"""")"),2270.0) -> 2270 | X54: =IFERROR(__xludf.DUMMYFUNCTION("IFERROR(GOOGLEFINANCE(A54,""high""),"""")"),2340.0) -> 2340 | Y54: =IFERROR(__xludf.DUMMYFUNCTION("IFERROR(GOOGLEFINANCE(A54,""low""),"""")"),2250.0) -> 2250 | Z54: =IFERROR(__xludf.DUMMYFUNCTION("IFERROR(GOOGLEFINANCE(A54,""volume""),"""")"),3.69179E7) -> 36917900 | AA54: =VLOOKUP(A54,Metrik!$C$2:$Y$959,5,0) -> Coal | AB54: =VLOOKUP(A54,Metrik!$C$2:$Y$959,3,0) -> Energy
A55: ADRO | B55: {=VLOOKUP(A55,{Metrik!$C$2:$C$998,Metrik!$B$2:$B$998},2,0)} -> Alamtri Resources Indonesia Tbk. | C55: =IFERROR(__xludf.DUMMYFUNCTION("GOOGLEFINANCE(""IDX:""&A55,""price"")"),2280.0) -> 2280 | D55: =IFERROR(__xludf.DUMMYFUNCTION("IF(A55="""","""", SPARKLINE( INDEX( GOOGLEFINANCE(""IDX:""&A55,""close"",TODAY()-365,TODAY()), ,2 ), {""linewidth"",1} )) "),"#N/A") -> #N/A | E55: JII30 | F55: 46356 | G55: =COUNTIFS($B$2:$B$1937,B55,$E$2:$E$1937,"<>") -> 14 | H55: =VLOOKUP(A55,Metrik!$C$2:$Y$959,8,0) -> 8 | I55: =VLOOKUP(A55,Metrik!$C$2:$Y$959,9,0) -> 0.73 | J55: =VLOOKUP(A55,Metrik!$C$2:$Y$959,10,0) -> 9.1 | K55: =VLOOKUP(A55,Metrik!$C$2:$Y$959,11,0) -> 6.9 | L55: =VLOOKUP(A55,Metrik!$C$2:$Y$959,12,0) -> 0.32 | M55: =VLOOKUP(A55,Metrik!$C$2:$Y$959,19,0) -> 110 | U55: =IFERROR(__xludf.DUMMYFUNCTION("IFERROR(GOOGLEFINANCE(A55,""closeyest""),"""")"),2250.0) -> 2250 | V55: =IFERROR(__xludf.DUMMYFUNCTION("IFERROR(GOOGLEFINANCE(A55,""changepct""),"""")"),1.33) -> 1.33 | W55: =IFERROR(__xludf.DUMMYFUNCTION("IFERROR(GOOGLEFINANCE(A55,""priceopen""),"""")"),2270.0) -> 2270 | X55: =IFERROR(__xludf.DUMMYFUNCTION("IFERROR(GOOGLEFINANCE(A55,""high""),"""")"),2340.0) -> 2340 | Y55: =IFERROR(__xludf.DUMMYFUNCTION("IFERROR(GOOGLEFINANCE(A55,""low""),"""")"),2250.0) -> 2250 | Z55: =IFERROR(__xludf.DUMMYFUNCTION("IFERROR(GOOGLEFINANCE(A55,""volume""),"""")"),3.69179E7) -> 36917900 | AA55: =VLOOKUP(A55,Metrik!$C$2:$Y$959,5,0) -> Coal | AB55: =VLOOKUP(A55,Metrik!$C$2:$Y$959,3,0) -> Energy
A56: ADRO | B56: {=VLOOKUP(A56,{Metrik!$C$2:$C$998,Metrik!$B$2:$B$998},2,0)} -> Alamtri Resources Indonesia Tbk. | C56: =IFERROR(__xludf.DUMMYFUNCTION("GOOGLEFINANCE(""IDX:""&A56,""price"")"),2280.0) -> 2280 | D56: =IFERROR(__xludf.DUMMYFUNCTION("IF(A56="""","""", SPARKLINE( INDEX( GOOGLEFINANCE(""IDX:""&A56,""close"",TODAY()-365,TODAY()), ,2 ), {""linewidth"",1} )) "),"#N/A") -> #N/A | E56: JII70 | F56: 46356 | G56: =COUNTIFS($B$2:$B$1937,B56,$E$2:$E$1937,"<>") -> 14 | H56: =VLOOKUP(A56,Metrik!$C$2:$Y$959,8,0) -> 8 | I56: =VLOOKUP(A56,Metrik!$C$2:$Y$959,9,0) -> 0.73 | J56: =VLOOKUP(A56,Metrik!$C$2:$Y$959,10,0) -> 9.1 | K56: =VLOOKUP(A56,Metrik!$C$2:$Y$959,11,0) -> 6.9 | L56: =VLOOKUP(A56,Metrik!$C$2:$Y$959,12,0) -> 0.32 | M56: =VLOOKUP(A56,Metrik!$C$2:$Y$959,19,0) -> 110 | U56: =IFERROR(__xludf.DUMMYFUNCTION("IFERROR(GOOGLEFINANCE(A56,""closeyest""),"""")"),2250.0) -> 2250 | V56: =IFERROR(__xludf.DUMMYFUNCTION("IFERROR(GOOGLEFINANCE(A56,""changepct""),"""")"),1.33) -> 1.33 | W56: =IFERROR(__xludf.DUMMYFUNCTION("IFERROR(GOOGLEFINANCE(A56,""priceopen""),"""")"),2270.0) -> 2270 | X56: =IFERROR(__xludf.DUMMYFUNCTION("IFERROR(GOOGLEFINANCE(A56,""high""),"""")"),2340.0) -> 2340 | Y56: =IFERROR(__xludf.DUMMYFUNCTION("IFERROR(GOOGLEFINANCE(A56,""low""),"""")"),2250.0) -> 2250 | Z56: =IFERROR(__xludf.DUMMYFUNCTION("IFERROR(GOOGLEFINANCE(A56,""volume""),"""")"),3.69179E7) -> 36917900 | AA56: =VLOOKUP(A56,Metrik!$C$2:$Y$959,5,0) -> Coal | AB56: =VLOOKUP(A56,Metrik!$C$2:$Y$959,3,0) -> Energy
A57: AEGS | B57: {=VLOOKUP(A57,{Metrik!$C$2:$C$998,Metrik!$B$2:$B$998},2,0)} -> PT Anugerah Spareparts Sejahtera Tbk. | C57: =IFERROR(__xludf.DUMMYFUNCTION("GOOGLEFINANCE(""IDX:""&A57,""price"")"),40.0) -> 40 | D57: =IFERROR(__xludf.DUMMYFUNCTION("IF(A57="""","""", SPARKLINE( INDEX( GOOGLEFINANCE(""IDX:""&A57,""close"",TODAY()-365,TODAY()), ,2 ), {""linewidth"",1} )) "),"#N/A") -> #N/A | G57: =COUNTIFS($B$2:$B$1937,B57,$E$2:$E$1937,"<>") -> 0 | H57: =VLOOKUP(A57,Metrik!$C$2:$Y$959,8,0) -> 190 | I57: =VLOOKUP(A57,Metrik!$C$2:$Y$959,9,0) -> 0.7 | J57: =VLOOKUP(A57,Metrik!$C$2:$Y$959,10,0) -> 0.37 | K57: =VLOOKUP(A57,Metrik!$C$2:$Y$959,11,0) -> 0.35 | L57: =VLOOKUP(A57,Metrik!$C$2:$Y$959,12,0) -> 0.06 | M57: =VLOOKUP(A57,Metrik!$C$2:$Y$959,19,0) -> 1 | U57: =IFERROR(__xludf.DUMMYFUNCTION("IFERROR(GOOGLEFINANCE(A57,""closeyest""),"""")"),39.0) -> 39 | V57: =IFERROR(__xludf.DUMMYFUNCTION("IFERROR(GOOGLEFINANCE(A57,""changepct""),"""")"),2.56) -> 2.56 | W57: =IFERROR(__xludf.DUMMYFUNCTION("IFERROR(GOOGLEFINANCE(A57,""priceopen""),"""")"),39.0) -> 39 | X57: =IFERROR(__xludf.DUMMYFUNCTION("IFERROR(GOOGLEFINANCE(A57,""high""),"""")"),41.0) -> 41 | Y57: =IFERROR(__xludf.DUMMYFUNCTION("IFERROR(GOOGLEFINANCE(A57,""low""),"""")"),39.0) -> 39 | Z57: =IFERROR(__xludf.DUMMYFUNCTION("IFERROR(GOOGLEFINANCE(A57,""volume""),"""")"),1070500.0) -> 1070500 | AA57: =VLOOKUP(A57,Metrik!$C$2:$Y$959,5,0) -> Auto Components | AB57: =VLOOKUP(A57,Metrik!$C$2:$Y$959,3,0) -> Consumer Cyclicals
A58: AGAR | B58: {=VLOOKUP(A58,{Metrik!$C$2:$C$998,Metrik!$B$2:$B$998},2,0)} -> Asia Sejahtera Mina Tbk. | C58: =IFERROR(__xludf.DUMMYFUNCTION("GOOGLEFINANCE(""IDX:""&A58,""price"")"),216.0) -> 216 | D58: =IFERROR(__xludf.DUMMYFUNCTION("IF(A58="""","""", SPARKLINE( INDEX( GOOGLEFINANCE(""IDX:""&A58,""close"",TODAY()-365,TODAY()), ,2 ), {""linewidth"",1} )) "),"#N/A") -> #N/A | G58: =COUNTIFS($B$2:$B$1937,B58,$E$2:$E$1937,"<>") -> 0 | H58: =VLOOKUP(A58,Metrik!$C$2:$Y$959,8,0) -> 48.2 | I58: =VLOOKUP(A58,Metrik!$C$2:$Y$959,9,0) -> 2.1 | J58: =VLOOKUP(A58,Metrik!$C$2:$Y$959,10,0) -> 4.4 | K58: =VLOOKUP(A58,Metrik!$C$2:$Y$959,11,0) -> 2.6 | L58: =VLOOKUP(A58,Metrik!$C$2:$Y$959,12,0) -> 0.65 | M58: =VLOOKUP(A58,Metrik!$C$2:$Y$959,19,0) -> 10.7 | U58: =IFERROR(__xludf.DUMMYFUNCTION("IFERROR(GOOGLEFINANCE(A58,""closeyest""),"""")"),218.0) -> 218 | V58: =IFERROR(__xludf.DUMMYFUNCTION("IFERROR(GOOGLEFINANCE(A58,""changepct""),"""")"),-0.92) -> -0.92 | W58: =IFERROR(__xludf.DUMMYFUNCTION("IFERROR(GOOGLEFINANCE(A58,""priceopen""),"""")"),218.0) -> 218 | X58: =IFERROR(__xludf.DUMMYFUNCTION("IFERROR(GOOGLEFINANCE(A58,""high""),"""")"),226.0) -> 226 | Y58: =IFERROR(__xludf.DUMMYFUNCTION("IFERROR(GOOGLEFINANCE(A58,""low""),"""")"),214.0) -> 214 | Z58: =IFERROR(__xludf.DUMMYFUNCTION("IFERROR(GOOGLEFINANCE(A58,""volume""),"""")"),195700.0) -> 195700 | AA58: =VLOOKUP(A58,Metrik!$C$2:$Y$959,5,0) -> Agricultural Products | AB58: =VLOOKUP(A58,Metrik!$C$2:$Y$959,3,0) -> Consumer Non-Cyclicals
A59: AGII | B59: {=VLOOKUP(A59,{Metrik!$C$2:$C$998,Metrik!$B$2:$B$998},2,0)} -> Samator Indo Gas Tbk. | C59: =IFERROR(__xludf.DUMMYFUNCTION("GOOGLEFINANCE(""IDX:""&A59,""price"")"),2680.0) -> 2680 | D59: =IFERROR(__xludf.DUMMYFUNCTION("IF(A59="""","""", SPARKLINE( INDEX( GOOGLEFINANCE(""IDX:""&A59,""close"",TODAY()-365,TODAY()), ,2 ), {""linewidth"",1} )) "),"#N/A") -> #N/A | G59: =COUNTIFS($B$2:$B$1937,B59,$E$2:$E$1937,"<>") -> 0 | H59: =VLOOKUP(A59,Metrik!$C$2:$Y$959,8,0) -> 97.9 | I59: =VLOOKUP(A59,Metrik!$C$2:$Y$959,9,0) -> 2.2 | J59: =VLOOKUP(A59,Metrik!$C$2:$Y$959,10,0) -> 2.2 | K59: =VLOOKUP(A59,Metrik!$C$2:$Y$959,11,0) -> 1 | L59: =VLOOKUP(A59,Metrik!$C$2:$Y$959,12,0) -> 1.2 | M59: =VLOOKUP(A59,Metrik!$C$2:$Y$959,19,0) -> 11.3 | U59: =IFERROR(__xludf.DUMMYFUNCTION("IFERROR(GOOGLEFINANCE(A59,""closeyest""),"""")"),2550.0) -> 2550 | V59: =IFERROR(__xludf.DUMMYFUNCTION("IFERROR(GOOGLEFINANCE(A59,""changepct""),"""")"),5.1) -> 5.1 | W59: =IFERROR(__xludf.DUMMYFUNCTION("IFERROR(GOOGLEFINANCE(A59,""priceopen""),"""")"),2580.0) -> 2580 | X59: =IFERROR(__xludf.DUMMYFUNCTION("IFERROR(GOOGLEFINANCE(A59,""high""),"""")"),2730.0) -> 2730 | Y59: =IFERROR(__xludf.DUMMYFUNCTION("IFERROR(GOOGLEFINANCE(A59,""low""),"""")"),2580.0) -> 2580 | Z59: =IFERROR(__xludf.DUMMYFUNCTION("IFERROR(GOOGLEFINANCE(A59,""volume""),"""")"),83100.0) -> 83100 | AA59: =VLOOKUP(A59,Metrik!$C$2:$Y$959,5,0) -> Chemicals | AB59: =VLOOKUP(A59,Metrik!$C$2:$Y$959,3,0) -> Basic Materials
A60: AGRO | B60: {=VLOOKUP(A60,{Metrik!$C$2:$C$998,Metrik!$B$2:$B$998},2,0)} -> PT Bank Rakyat Indonesia Agroniaga Tbk | C60: =IFERROR(__xludf.DUMMYFUNCTION("GOOGLEFINANCE(""IDX:""&A60,""price"")"),151.0) -> 151 | D60: =IFERROR(__xludf.DUMMYFUNCTION("IF(A60="""","""", SPARKLINE( INDEX( GOOGLEFINANCE(""IDX:""&A60,""close"",TODAY()-365,TODAY()), ,2 ), {""linewidth"",1} )) "),"#N/A") -> #N/A | E60: IDXBUMN20 | F60: 4 Agustus 2026 | G60: =COUNTIFS($B$2:$B$1937,B60,$E$2:$E$1937,"<>") -> 2 | H60: =VLOOKUP(A60,Metrik!$C$2:$Y$959,8,0) -> -8 | I60: =VLOOKUP(A60,Metrik!$C$2:$Y$959,9,0) -> 1.4 | J60: =VLOOKUP(A60,Metrik!$C$2:$Y$959,10,0) -> -17.3 | K60: =VLOOKUP(A60,Metrik!$C$2:$Y$959,11,0) -> -4 | L60: =VLOOKUP(A60,Metrik!$C$2:$Y$959,12,0) -> 3.4 | M60: =VLOOKUP(A60,Metrik!$C$2:$Y$959,19,0) -> -160 | N60: 4.44 | O60: 44.29 | P60: 87.62 | Q60: 3.22 | R60: 96.68 | S60: 58.02 | U60: =IFERROR(__xludf.DUMMYFUNCTION("IFERROR(GOOGLEFINANCE(A60,""closeyest""),"""")"),11.69) -> 11.69 | V60: =IFERROR(__xludf.DUMMYFUNCTION("IFERROR(GOOGLEFINANCE(A60,""changepct""),"""")"),-0.34) -> -0.34 | W60: =IFERROR(__xludf.DUMMYFUNCTION("IFERROR(GOOGLEFINANCE(A60,""priceopen""),"""")"),11.63) -> 11.63 | X60: =IFERROR(__xludf.DUMMYFUNCTION("IFERROR(GOOGLEFINANCE(A60,""high""),"""")"),11.84) -> 11.84 | Y60: =IFERROR(__xludf.DUMMYFUNCTION("IFERROR(GOOGLEFINANCE(A60,""low""),"""")"),11.58) -> 11.58 | Z60: =IFERROR(__xludf.DUMMYFUNCTION("IFERROR(GOOGLEFINANCE(A60,""volume""),"""")"),921019.0) -> 921019 | AA60: =VLOOKUP(A60,Metrik!$C$2:$Y$959,5,0) -> Banks | AB60: =VLOOKUP(A60,Metrik!$C$2:$Y$959,3,0) -> Financials
A61: AGRO | B61: {=VLOOKUP(A61,{Metrik!$C$2:$C$998,Metrik!$B$2:$B$998},2,0)} -> PT Bank Rakyat Indonesia Agroniaga Tbk | C61: =IFERROR(__xludf.DUMMYFUNCTION("GOOGLEFINANCE(""IDX:""&A61,""price"")"),151.0) -> 151 | D61: =IFERROR(__xludf.DUMMYFUNCTION("IF(A61="""","""", SPARKLINE( INDEX( GOOGLEFINANCE(""IDX:""&A61,""close"",TODAY()-365,TODAY()), ,2 ), {""linewidth"",1} )) "),"#N/A") -> #N/A | E61: Infobank15 | F61: 30 Juni 2026 | G61: =COUNTIFS($B$2:$B$1937,B61,$E$2:$E$1937,"<>") -> 2 | H61: =VLOOKUP(A61,Metrik!$C$2:$Y$959,8,0) -> -8 | I61: =VLOOKUP(A61,Metrik!$C$2:$Y$959,9,0) -> 1.4 | J61: =VLOOKUP(A61,Metrik!$C$2:$Y$959,10,0) -> -17.3 | K61: =VLOOKUP(A61,Metrik!$C$2:$Y$959,11,0) -> -4 | L61: =VLOOKUP(A61,Metrik!$C$2:$Y$959,12,0) -> 3.4 | M61: =VLOOKUP(A61,Metrik!$C$2:$Y$959,19,0) -> -160 | N61: 4.44 | O61: 44.29 | P61: 87.62 | Q61: 3.22 | R61: 96.68 | S61: 58.02 | U61: =IFERROR(__xludf.DUMMYFUNCTION("IFERROR(GOOGLEFINANCE(A61,""closeyest""),"""")"),11.69) -> 11.69 | V61: =IFERROR(__xludf.DUMMYFUNCTION("IFERROR(GOOGLEFINANCE(A61,""changepct""),"""")"),-0.34) -> -0.34 | W61: =IFERROR(__xludf.DUMMYFUNCTION("IFERROR(GOOGLEFINANCE(A61,""priceopen""),"""")"),11.63) -> 11.63 | X61: =IFERROR(__xludf.DUMMYFUNCTION("IFERROR(GOOGLEFINANCE(A61,""high""),"""")"),11.84) -> 11.84 | Y61: =IFERROR(__xludf.DUMMYFUNCTION("IFERROR(GOOGLEFINANCE(A61,""low""),"""")"),11.58) -> 11.58 | Z61: =IFERROR(__xludf.DUMMYFUNCTION("IFERROR(GOOGLEFINANCE(A61,""volume""),"""")"),921019.0) -> 921019 | AA61: =VLOOKUP(A61,Metrik!$C$2:$Y$959,5,0) -> Banks | AB61: =VLOOKUP(A61,Metrik!$C$2:$Y$959,3,0) -> Financials
A62: AGRS | B62: {=VLOOKUP(A62,{Metrik!$C$2:$C$998,Metrik!$B$2:$B$998},2,0)} -> PT Bank IBK Indonesia Tbk. | C62: =IFERROR(__xludf.DUMMYFUNCTION("GOOGLEFINANCE(""IDX:""&A62,""price"")"),62.0) -> 62 | D62: =IFERROR(__xludf.DUMMYFUNCTION("IF(A62="""","""", SPARKLINE( INDEX( GOOGLEFINANCE(""IDX:""&A62,""close"",TODAY()-365,TODAY()), ,2 ), {""linewidth"",1} )) "),"#N/A") -> #N/A | G62: =COUNTIFS($B$2:$B$1937,B62,$E$2:$E$1937,"<>") -> 0 | H62: =VLOOKUP(A62,Metrik!$C$2:$Y$959,8,0) -> 17.3 | I62: =VLOOKUP(A62,Metrik!$C$2:$Y$959,9,0) -> 0.53 | J62: =VLOOKUP(A62,Metrik!$C$2:$Y$959,10,0) -> 3.1 | K62: =VLOOKUP(A62,Metrik!$C$2:$Y$959,11,0) -> 0.76 | L62: =VLOOKUP(A62,Metrik!$C$2:$Y$959,12,0) -> 3 | M62: =VLOOKUP(A62,Metrik!$C$2:$Y$959,19,0) -> 48.6 | N62: 3.42 | O62: 26.05 | P62: 85.34 | Q62: 1.84 | R62: 86.12 | S62: 51.46 | T62: 6.22 | U62: =IFERROR(__xludf.DUMMYFUNCTION("IFERROR(GOOGLEFINANCE(A62,""closeyest""),"""")"),0.0) -> 0 | V62: =IFERROR(__xludf.DUMMYFUNCTION("IFERROR(GOOGLEFINANCE(A62,""changepct""),"""")"),0.0) -> 0 | W62: =IFERROR(__xludf.DUMMYFUNCTION("IFERROR(GOOGLEFINANCE(A62,""priceopen""),"""")"),"") | X62: =IFERROR(__xludf.DUMMYFUNCTION("IFERROR(GOOGLEFINANCE(A62,""high""),"""")"),"") | Y62: =IFERROR(__xludf.DUMMYFUNCTION("IFERROR(GOOGLEFINANCE(A62,""low""),"""")"),"") | Z62: =IFERROR(__xludf.DUMMYFUNCTION("IFERROR(GOOGLEFINANCE(A62,""volume""),"""")"),0.0) -> 0 | AA62: =VLOOKUP(A62,Metrik!$C$2:$Y$959,5,0) -> Banks | AB62: =VLOOKUP(A62,Metrik!$C$2:$Y$959,3,0) -> Financials
A63: AHAP | B63: {=VLOOKUP(A63,{Metrik!$C$2:$C$998,Metrik!$B$2:$B$998},2,0)} -> Asuransi Harta Aman Pratama Tbk. | C63: =IFERROR(__xludf.DUMMYFUNCTION("GOOGLEFINANCE(""IDX:""&A63,""price"")"),82.0) -> 82 | D63: =IFERROR(__xludf.DUMMYFUNCTION("IF(A63="""","""", SPARKLINE( INDEX( GOOGLEFINANCE(""IDX:""&A63,""close"",TODAY()-365,TODAY()), ,2 ), {""linewidth"",1} )) "),"#N/A") -> #N/A | G63: =COUNTIFS($B$2:$B$1937,B63,$E$2:$E$1937,"<>") -> 0 | H63: =VLOOKUP(A63,Metrik!$C$2:$Y$959,8,0) -> -18 | I63: =VLOOKUP(A63,Metrik!$C$2:$Y$959,9,0) -> 2.4 | J63: =VLOOKUP(A63,Metrik!$C$2:$Y$959,10,0) -> -13.5 | K63: =VLOOKUP(A63,Metrik!$C$2:$Y$959,11,0) -> -2.7 | L63: =VLOOKUP(A63,Metrik!$C$2:$Y$959,12,0) -> 4 | M63: =VLOOKUP(A63,Metrik!$C$2:$Y$959,19,0) -> -11.6 | U63: =IFERROR(__xludf.DUMMYFUNCTION("IFERROR(GOOGLEFINANCE(A63,""closeyest""),"""")"),78.0) -> 78 | V63: =IFERROR(__xludf.DUMMYFUNCTION("IFERROR(GOOGLEFINANCE(A63,""changepct""),"""")"),5.13) -> 5.13 | W63: =IFERROR(__xludf.DUMMYFUNCTION("IFERROR(GOOGLEFINANCE(A63,""priceopen""),"""")"),78.0) -> 78 | X63: =IFERROR(__xludf.DUMMYFUNCTION("IFERROR(GOOGLEFINANCE(A63,""high""),"""")"),85.0) -> 85 | Y63: =IFERROR(__xludf.DUMMYFUNCTION("IFERROR(GOOGLEFINANCE(A63,""low""),"""")"),78.0) -> 78 | Z63: =IFERROR(__xludf.DUMMYFUNCTION("IFERROR(GOOGLEFINANCE(A63,""volume""),"""")"),1.3048E7) -> 13048000 | AA63: =VLOOKUP(A63,Metrik!$C$2:$Y$959,5,0) -> Insurance | AB63: =VLOOKUP(A63,Metrik!$C$2:$Y$959,3,0) -> Financials
A64: AIMS | B64: {=VLOOKUP(A64,{Metrik!$C$2:$C$998,Metrik!$B$2:$B$998},2,0)} -> Artha Mahiya Investama Tbk. | C64: =IFERROR(__xludf.DUMMYFUNCTION("GOOGLEFINANCE(""IDX:""&A64,""price"")"),390.0) -> 390 | D64: =IFERROR(__xludf.DUMMYFUNCTION("IF(A64="""","""", SPARKLINE( INDEX( GOOGLEFINANCE(""IDX:""&A64,""close"",TODAY()-365,TODAY()), ,2 ), {""linewidth"",1} )) "),"#N/A") -> #N/A | G64: =COUNTIFS($B$2:$B$1937,B64,$E$2:$E$1937,"<>") -> 0 | H64: =VLOOKUP(A64,Metrik!$C$2:$Y$959,8,0) -> -110 | I64: =VLOOKUP(A64,Metrik!$C$2:$Y$959,9,0) -> 510 | J64: =VLOOKUP(A64,Metrik!$C$2:$Y$959,10,0) -> -480 | K64: =VLOOKUP(A64,Metrik!$C$2:$Y$959,11,0) -> -18.2 | L64: =VLOOKUP(A64,Metrik!$C$2:$Y$959,12,0) -> 25.3 | M64: =VLOOKUP(A64,Metrik!$C$2:$Y$959,19,0) -> -62.2 | U64: =IFERROR(__xludf.DUMMYFUNCTION("IFERROR(GOOGLEFINANCE(A64,""closeyest""),"""")"),27.76) -> 27.76 | V64: =IFERROR(__xludf.DUMMYFUNCTION("IFERROR(GOOGLEFINANCE(A64,""changepct""),"""")"),2.29) -> 2.29 | W64: =IFERROR(__xludf.DUMMYFUNCTION("IFERROR(GOOGLEFINANCE(A64,""priceopen""),"""")"),28.41) -> 28.41 | X64: =IFERROR(__xludf.DUMMYFUNCTION("IFERROR(GOOGLEFINANCE(A64,""high""),"""")"),28.48) -> 28.48 | Y64: =IFERROR(__xludf.DUMMYFUNCTION("IFERROR(GOOGLEFINANCE(A64,""low""),"""")"),28.29) -> 28.29 | Z64: =IFERROR(__xludf.DUMMYFUNCTION("IFERROR(GOOGLEFINANCE(A64,""volume""),"""")"),3526.0) -> 3526 | AA64: =VLOOKUP(A64,Metrik!$C$2:$Y$959,5,0) -> Coal | AB64: =VLOOKUP(A64,Metrik!$C$2:$Y$959,3,0) -> Energy
A65: AISA | B65: {=VLOOKUP(A65,{Metrik!$C$2:$C$998,Metrik!$B$2:$B$998},2,0)} -> FKS Food Sejahtera Tbk. | C65: =IFERROR(__xludf.DUMMYFUNCTION("GOOGLEFINANCE(""IDX:""&A65,""price"")"),101.0) -> 101 | D65: =IFERROR(__xludf.DUMMYFUNCTION("IF(A65="""","""", SPARKLINE( INDEX( GOOGLEFINANCE(""IDX:""&A65,""close"",TODAY()-365,TODAY()), ,2 ), {""linewidth"",1} )) "),"#N/A") -> #N/A | G65: =COUNTIFS($B$2:$B$1937,B65,$E$2:$E$1937,"<>") -> 0 | H65: =VLOOKUP(A65,Metrik!$C$2:$Y$959,8,0) -> 15.2 | I65: =VLOOKUP(A65,Metrik!$C$2:$Y$959,9,0) -> 0.86 | J65: =VLOOKUP(A65,Metrik!$C$2:$Y$959,10,0) -> 5.7 | K65: =VLOOKUP(A65,Metrik!$C$2:$Y$959,11,0) -> 3 | L65: =VLOOKUP(A65,Metrik!$C$2:$Y$959,12,0) -> 0.87 | M65: =VLOOKUP(A65,Metrik!$C$2:$Y$959,19,0) -> 13 | U65: =IFERROR(__xludf.DUMMYFUNCTION("IFERROR(GOOGLEFINANCE(A65,""closeyest""),"""")"),102.0) -> 102 | V65: =IFERROR(__xludf.DUMMYFUNCTION("IFERROR(GOOGLEFINANCE(A65,""changepct""),"""")"),-0.98) -> -0.98 | W65: =IFERROR(__xludf.DUMMYFUNCTION("IFERROR(GOOGLEFINANCE(A65,""priceopen""),"""")"),101.0) -> 101 | X65: =IFERROR(__xludf.DUMMYFUNCTION("IFERROR(GOOGLEFINANCE(A65,""high""),"""")"),105.0) -> 105 | Y65: =IFERROR(__xludf.DUMMYFUNCTION("IFERROR(GOOGLEFINANCE(A65,""low""),"""")"),100.0) -> 100 | Z65: =IFERROR(__xludf.DUMMYFUNCTION("IFERROR(GOOGLEFINANCE(A65,""volume""),"""")"),4799800.0) -> 4799800 | AA65: =VLOOKUP(A65,Metrik!$C$2:$Y$959,5,0) -> Processed Foods | AB65: =VLOOKUP(A65,Metrik!$C$2:$Y$959,3,0) -> Consumer Non-Cyclicals
A66: AKKU | B66: {=VLOOKUP(A66,{Metrik!$C$2:$C$998,Metrik!$B$2:$B$998},2,0)} -> Anugerah Kagum Karya Utama Tbk. | C66: =IFERROR(__xludf.DUMMYFUNCTION("GOOGLEFINANCE(""IDX:""&A66,""price"")"),38.0) -> 38 | D66: =IFERROR(__xludf.DUMMYFUNCTION("IF(A66="""","""", SPARKLINE( INDEX( GOOGLEFINANCE(""IDX:""&A66,""close"",TODAY()-365,TODAY()), ,2 ), {""linewidth"",1} )) "),"#N/A") -> #N/A | G66: =COUNTIFS($B$2:$B$1937,B66,$E$2:$E$1937,"<>") -> 0 | H66: =VLOOKUP(A66,Metrik!$C$2:$Y$959,8,0) -> -9.4 | I66: =VLOOKUP(A66,Metrik!$C$2:$Y$959,9,0) -> 0.62 | J66: =VLOOKUP(A66,Metrik!$C$2:$Y$959,10,0) -> -6.6 | K66: =VLOOKUP(A66,Metrik!$C$2:$Y$959,11,0) -> -3.7 | L66: =VLOOKUP(A66,Metrik!$C$2:$Y$959,12,0) -> 0.77 | M66: =VLOOKUP(A66,Metrik!$C$2:$Y$959,19,0) -> -1280 | U66: =IFERROR(__xludf.DUMMYFUNCTION("IFERROR(GOOGLEFINANCE(A66,""closeyest""),"""")"),38.0) -> 38 | V66: =IFERROR(__xludf.DUMMYFUNCTION("IFERROR(GOOGLEFINANCE(A66,""changepct""),"""")"),0.0) -> 0 | W66: =IFERROR(__xludf.DUMMYFUNCTION("IFERROR(GOOGLEFINANCE(A66,""priceopen""),"""")"),"") | X66: =IFERROR(__xludf.DUMMYFUNCTION("IFERROR(GOOGLEFINANCE(A66,""high""),"""")"),"") | Y66: =IFERROR(__xludf.DUMMYFUNCTION("IFERROR(GOOGLEFINANCE(A66,""low""),"""")"),"") | Z66: =IFERROR(__xludf.DUMMYFUNCTION("IFERROR(GOOGLEFINANCE(A66,""volume""),"""")"),0.0) -> 0 | AA66: =VLOOKUP(A66,Metrik!$C$2:$Y$959,5,0) -> Tourism & Recreation | AB66: =VLOOKUP(A66,Metrik!$C$2:$Y$959,3,0) -> Consumer Cyclicals
A67: AKPI | B67: {=VLOOKUP(A67,{Metrik!$C$2:$C$998,Metrik!$B$2:$B$998},2,0)} -> Argha Karya Prima Industry Tbk. | C67: =IFERROR(__xludf.DUMMYFUNCTION("GOOGLEFINANCE(""IDX:""&A67,""price"")"),"#N/A") -> #N/A | D67: =IFERROR(__xludf.DUMMYFUNCTION("IF(A67="""","""", SPARKLINE( INDEX( GOOGLEFINANCE(""IDX:""&A67,""close"",TODAY()-365,TODAY()), ,2 ), {""linewidth"",1} )) "),"#N/A") -> #N/A | G67: =COUNTIFS($B$2:$B$1937,B67,$E$2:$E$1937,"<>") -> 0 | H67: =VLOOKUP(A67,Metrik!$C$2:$Y$959,8,0) -> 10.1 | I67: =VLOOKUP(A67,Metrik!$C$2:$Y$959,9,0) -> 0.17 | J67: =VLOOKUP(A67,Metrik!$C$2:$Y$959,10,0) -> 1.7 | K67: =VLOOKUP(A67,Metrik!$C$2:$Y$959,11,0) -> 0.86 | L67: =VLOOKUP(A67,Metrik!$C$2:$Y$959,12,0) -> 1 | M67: =VLOOKUP(A67,Metrik!$C$2:$Y$959,19,0) -> 4.4 | U67: =IFERROR(__xludf.DUMMYFUNCTION("IFERROR(GOOGLEFINANCE(A67,""closeyest""),"""")"),461.73) -> 461.73 | V67: =IFERROR(__xludf.DUMMYFUNCTION("IFERROR(GOOGLEFINANCE(A67,""changepct""),"""")"),9.37) -> 9.37 | W67: =IFERROR(__xludf.DUMMYFUNCTION("IFERROR(GOOGLEFINANCE(A67,""priceopen""),"""")"),468.0) -> 468 | X67: =IFERROR(__xludf.DUMMYFUNCTION("IFERROR(GOOGLEFINANCE(A67,""high""),"""")"),510.0) -> 510 | Y67: =IFERROR(__xludf.DUMMYFUNCTION("IFERROR(GOOGLEFINANCE(A67,""low""),"""")"),462.0) -> 462 | Z67: =IFERROR(__xludf.DUMMYFUNCTION("IFERROR(GOOGLEFINANCE(A67,""volume""),"""")"),330700.0) -> 330700 | AA67: =VLOOKUP(A67,Metrik!$C$2:$Y$959,5,0) -> Chemicals | AB67: =VLOOKUP(A67,Metrik!$C$2:$Y$959,3,0) -> Basic Materials
A68: AKRA | B68: {=VLOOKUP(A68,{Metrik!$C$2:$C$998,Metrik!$B$2:$B$998},2,0)} -> AKR Corporindo Tbk. | C68: =IFERROR(__xludf.DUMMYFUNCTION("GOOGLEFINANCE(""IDX:""&A68,""price"")"),1250.0) -> 1250 | D68: =IFERROR(__xludf.DUMMYFUNCTION("IF(A68="""","""", SPARKLINE( INDEX( GOOGLEFINANCE(""IDX:""&A68,""close"",TODAY()-365,TODAY()), ,2 ), {""linewidth"",1} )) "),"#N/A") -> #N/A | E68: ESGQKEHATI | F68: 46356 | G68: =COUNTIFS($B$2:$B$1937,B68,$E$2:$E$1937,"<>") -> 16 | H68: =VLOOKUP(A68,Metrik!$C$2:$Y$959,8,0) -> 9.7 | I68: =VLOOKUP(A68,Metrik!$C$2:$Y$959,9,0) -> 1.5 | J68: =VLOOKUP(A68,Metrik!$C$2:$Y$959,10,0) -> 15.8 | K68: =VLOOKUP(A68,Metrik!$C$2:$Y$959,11,0) -> 6.9 | L68: =VLOOKUP(A68,Metrik!$C$2:$Y$959,12,0) -> 1.3 | M68: =VLOOKUP(A68,Metrik!$C$2:$Y$959,19,0) -> 19.8 | U68: =IFERROR(__xludf.DUMMYFUNCTION("IFERROR(GOOGLEFINANCE(A68,""closeyest""),"""")"),1265.0) -> 1265 | V68: =IFERROR(__xludf.DUMMYFUNCTION("IFERROR(GOOGLEFINANCE(A68,""changepct""),"""")"),-1.19) -> -1.19 | W68: =IFERROR(__xludf.DUMMYFUNCTION("IFERROR(GOOGLEFINANCE(A68,""priceopen""),"""")"),1280.0) -> 1280 | X68: =IFERROR(__xludf.DUMMYFUNCTION("IFERROR(GOOGLEFINANCE(A68,""high""),"""")"),1315.0) -> 1315 | Y68: =IFERROR(__xludf.DUMMYFUNCTION("IFERROR(GOOGLEFINANCE(A68,""low""),"""")"),1250.0) -> 1250 | Z68: =IFERROR(__xludf.DUMMYFUNCTION("IFERROR(GOOGLEFINANCE(A68,""volume""),"""")"),2.12091E7) -> 21209100 | AA68: =VLOOKUP(A68,Metrik!$C$2:$Y$959,5,0) -> Oil & Gas | AB68: =VLOOKUP(A68,Metrik!$C$2:$Y$959,3,0) -> Energy
A69: AKRA | B69: {=VLOOKUP(A69,{Metrik!$C$2:$C$998,Metrik!$B$2:$B$998},2,0)} -> AKR Corporindo Tbk. | C69: =IFERROR(__xludf.DUMMYFUNCTION("GOOGLEFINANCE(""IDX:""&A69,""price"")"),1250.0) -> 1250 | D69: =IFERROR(__xludf.DUMMYFUNCTION("IF(A69="""","""", SPARKLINE( INDEX( GOOGLEFINANCE(""IDX:""&A69,""close"",TODAY()-365,TODAY()), ,2 ), {""linewidth"",1} )) "),"#N/A") -> #N/A | E69: IDXHIDIV20 | F69: 2 Februari 2027 | G69: =COUNTIFS($B$2:$B$1937,B69,$E$2:$E$1937,"<>") -> 16 | H69: =VLOOKUP(A69,Metrik!$C$2:$Y$959,8,0) -> 9.7 | I69: =VLOOKUP(A69,Metrik!$C$2:$Y$959,9,0) -> 1.5 | J69: =VLOOKUP(A69,Metrik!$C$2:$Y$959,10,0) -> 15.8 | K69: =VLOOKUP(A69,Metrik!$C$2:$Y$959,11,0) -> 6.9 | L69: =VLOOKUP(A69,Metrik!$C$2:$Y$959,12,0) -> 1.3 | M69: =VLOOKUP(A69,Metrik!$C$2:$Y$959,19,0) -> 19.8 | U69: =IFERROR(__xludf.DUMMYFUNCTION("IFERROR(GOOGLEFINANCE(A69,""closeyest""),"""")"),1265.0) -> 1265 | V69: =IFERROR(__xludf.DUMMYFUNCTION("IFERROR(GOOGLEFINANCE(A69,""changepct""),"""")"),-1.19) -> -1.19 | W69: =IFERROR(__xludf.DUMMYFUNCTION("IFERROR(GOOGLEFINANCE(A69,""priceopen""),"""")"),1280.0) -> 1280 | X69: =IFERROR(__xludf.DUMMYFUNCTION("IFERROR(GOOGLEFINANCE(A69,""high""),"""")"),1315.0) -> 1315 | Y69: =IFERROR(__xludf.DUMMYFUNCTION("IFERROR(GOOGLEFINANCE(A69,""low""),"""")"),1250.0) -> 1250 | Z69: =IFERROR(__xludf.DUMMYFUNCTION("IFERROR(GOOGLEFINANCE(A69,""volume""),"""")"),2.12091E7) -> 21209100 | AA69: =VLOOKUP(A69,Metrik!$C$2:$Y$959,5,0) -> Oil & Gas | AB69: =VLOOKUP(A69,Metrik!$C$2:$Y$959,3,0) -> Energy
A70: AKRA | B70: {=VLOOKUP(A70,{Metrik!$C$2:$C$998,Metrik!$B$2:$B$998},2,0)} -> AKR Corporindo Tbk. | C70: =IFERROR(__xludf.DUMMYFUNCTION("GOOGLEFINANCE(""IDX:""&A70,""price"")"),1250.0) -> 1250 | D70: =IFERROR(__xludf.DUMMYFUNCTION("IF(A70="""","""", SPARKLINE( INDEX( GOOGLEFINANCE(""IDX:""&A70,""close"",TODAY()-365,TODAY()), ,2 ), {""linewidth"",1} )) "),"#N/A") -> #N/A | E70: LQ45 | F70: 31 Juli 2026 | G70: =COUNTIFS($B$2:$B$1937,B70,$E$2:$E$1937,"<>") -> 16 | H70: =VLOOKUP(A70,Metrik!$C$2:$Y$959,8,0) -> 9.7 | I70: =VLOOKUP(A70,Metrik!$C$2:$Y$959,9,0) -> 1.5 | J70: =VLOOKUP(A70,Metrik!$C$2:$Y$959,10,0) -> 15.8 | K70: =VLOOKUP(A70,Metrik!$C$2:$Y$959,11,0) -> 6.9 | L70: =VLOOKUP(A70,Metrik!$C$2:$Y$959,12,0) -> 1.3 | M70: =VLOOKUP(A70,Metrik!$C$2:$Y$959,19,0) -> 19.8 | U70: =IFERROR(__xludf.DUMMYFUNCTION("IFERROR(GOOGLEFINANCE(A70,""closeyest""),"""")"),1265.0) -> 1265 | V70: =IFERROR(__xludf.DUMMYFUNCTION("IFERROR(GOOGLEFINANCE(A70,""changepct""),"""")"),-1.19) -> -1.19 | W70: =IFERROR(__xludf.DUMMYFUNCTION("IFERROR(GOOGLEFINANCE(A70,""priceopen""),"""")"),1280.0) -> 1280 | X70: =IFERROR(__xludf.DUMMYFUNCTION("IFERROR(GOOGLEFINANCE(A70,""high""),"""")"),1315.0) -> 1315 | Y70: =IFERROR(__xludf.DUMMYFUNCTION("IFERROR(GOOGLEFINANCE(A70,""low""),"""")"),1250.0) -> 1250 | Z70: =IFERROR(__xludf.DUMMYFUNCTION("IFERROR(GOOGLEFINANCE(A70,""volume""),"""")"),2.12091E7) -> 21209100 | AA70: =VLOOKUP(A70,Metrik!$C$2:$Y$959,5,0) -> Oil & Gas | AB70: =VLOOKUP(A70,Metrik!$C$2:$Y$959,3,0) -> Energy
A71: AKRA | B71: {=VLOOKUP(A71,{Metrik!$C$2:$C$998,Metrik!$B$2:$B$998},2,0)} -> AKR Corporindo Tbk. | C71: =IFERROR(__xludf.DUMMYFUNCTION("GOOGLEFINANCE(""IDX:""&A71,""price"")"),1250.0) -> 1250 | D71: =IFERROR(__xludf.DUMMYFUNCTION("IF(A71="""","""", SPARKLINE( INDEX( GOOGLEFINANCE(""IDX:""&A71,""close"",TODAY()-365,TODAY()), ,2 ), {""linewidth"",1} )) "),"#N/A") -> #N/A | E71: IDX80 | F71: 31 Juli 2026 | G71: =COUNTIFS($B$2:$B$1937,B71,$E$2:$E$1937,"<>") -> 16 | H71: =VLOOKUP(A71,Metrik!$C$2:$Y$959,8,0) -> 9.7 | I71: =VLOOKUP(A71,Metrik!$C$2:$Y$959,9,0) -> 1.5 | J71: =VLOOKUP(A71,Metrik!$C$2:$Y$959,10,0) -> 15.8 | K71: =VLOOKUP(A71,Metrik!$C$2:$Y$959,11,0) -> 6.9 | L71: =VLOOKUP(A71,Metrik!$C$2:$Y$959,12,0) -> 1.3 | M71: =VLOOKUP(A71,Metrik!$C$2:$Y$959,19,0) -> 19.8 | U71: =IFERROR(__xludf.DUMMYFUNCTION("IFERROR(GOOGLEFINANCE(A71,""closeyest""),"""")"),1265.0) -> 1265 | V71: =IFERROR(__xludf.DUMMYFUNCTION("IFERROR(GOOGLEFINANCE(A71,""changepct""),"""")"),-1.19) -> -1.19 | W71: =IFERROR(__xludf.DUMMYFUNCTION("IFERROR(GOOGLEFINANCE(A71,""priceopen""),"""")"),1280.0) -> 1280 | X71: =IFERROR(__xludf.DUMMYFUNCTION("IFERROR(GOOGLEFINANCE(A71,""high""),"""")"),1315.0) -> 1315 | Y71: =IFERROR(__xludf.DUMMYFUNCTION("IFERROR(GOOGLEFINANCE(A71,""low""),"""")"),1250.0) -> 1250 | Z71: =IFERROR(__xludf.DUMMYFUNCTION("IFERROR(GOOGLEFINANCE(A71,""volume""),"""")"),2.12091E7) -> 21209100 | AA71: =VLOOKUP(A71,Metrik!$C$2:$Y$959,5,0) -> Oil & Gas | AB71: =VLOOKUP(A71,Metrik!$C$2:$Y$959,3,0) -> Energy
A72: AKRA | B72: {=VLOOKUP(A72,{Metrik!$C$2:$C$998,Metrik!$B$2:$B$998},2,0)} -> AKR Corporindo Tbk. | C72: =IFERROR(__xludf.DUMMYFUNCTION("GOOGLEFINANCE(""IDX:""&A72,""price"")"),1250.0) -> 1250 | D72: =IFERROR(__xludf.DUMMYFUNCTION("IF(A72="""","""", SPARKLINE( INDEX( GOOGLEFINANCE(""IDX:""&A72,""close"",TODAY()-365,TODAY()), ,2 ), {""linewidth"",1} )) "),"#N/A") -> #N/A | E72: MNC36 | F72: 30 Oktober 2026 | G72: =COUNTIFS($B$2:$B$1937,B72,$E$2:$E$1937,"<>") -> 16 | H72: =VLOOKUP(A72,Metrik!$C$2:$Y$959,8,0) -> 9.7 | I72: =VLOOKUP(A72,Metrik!$C$2:$Y$959,9,0) -> 1.5 | J72: =VLOOKUP(A72,Metrik!$C$2:$Y$959,10,0) -> 15.8 | K72: =VLOOKUP(A72,Metrik!$C$2:$Y$959,11,0) -> 6.9 | L72: =VLOOKUP(A72,Metrik!$C$2:$Y$959,12,0) -> 1.3 | M72: =VLOOKUP(A72,Metrik!$C$2:$Y$959,19,0) -> 19.8 | U72: =IFERROR(__xludf.DUMMYFUNCTION("IFERROR(GOOGLEFINANCE(A72,""closeyest""),"""")"),1265.0) -> 1265 | V72: =IFERROR(__xludf.DUMMYFUNCTION("IFERROR(GOOGLEFINANCE(A72,""changepct""),"""")"),-1.19) -> -1.19 | W72: =IFERROR(__xludf.DUMMYFUNCTION("IFERROR(GOOGLEFINANCE(A72,""priceopen""),"""")"),1280.0) -> 1280 | X72: =IFERROR(__xludf.DUMMYFUNCTION("IFERROR(GOOGLEFINANCE(A72,""high""),"""")"),1315.0) -> 1315 | Y72: =IFERROR(__xludf.DUMMYFUNCTION("IFERROR(GOOGLEFINANCE(A72,""low""),"""")"),1250.0) -> 1250 | Z72: =IFERROR(__xludf.DUMMYFUNCTION("IFERROR(GOOGLEFINANCE(A72,""volume""),"""")"),2.12091E7) -> 21209100 | AA72: =VLOOKUP(A72,Metrik!$C$2:$Y$959,5,0) -> Oil & Gas | AB72: =VLOOKUP(A72,Metrik!$C$2:$Y$959,3,0) -> Energy
A73: AKRA | B73: {=VLOOKUP(A73,{Metrik!$C$2:$C$998,Metrik!$B$2:$B$998},2,0)} -> AKR Corporindo Tbk. | C73: =IFERROR(__xludf.DUMMYFUNCTION("GOOGLEFINANCE(""IDX:""&A73,""price"")"),1250.0) -> 1250 | D73: =IFERROR(__xludf.DUMMYFUNCTION("IF(A73="""","""", SPARKLINE( INDEX( GOOGLEFINANCE(""IDX:""&A73,""close"",TODAY()-365,TODAY()), ,2 ), {""linewidth"",1} )) "),"#N/A") -> #N/A | E73: SMINFRA18 | F73: 30 Oktober 2026 | G73: =COUNTIFS($B$2:$B$1937,B73,$E$2:$E$1937,"<>") -> 16 | H73: =VLOOKUP(A73,Metrik!$C$2:$Y$959,8,0) -> 9.7 | I73: =VLOOKUP(A73,Metrik!$C$2:$Y$959,9,0) -> 1.5 | J73: =VLOOKUP(A73,Metrik!$C$2:$Y$959,10,0) -> 15.8 | K73: =VLOOKUP(A73,Metrik!$C$2:$Y$959,11,0) -> 6.9 | L73: =VLOOKUP(A73,Metrik!$C$2:$Y$959,12,0) -> 1.3 | M73: =VLOOKUP(A73,Metrik!$C$2:$Y$959,19,0) -> 19.8 | U73: =IFERROR(__xludf.DUMMYFUNCTION("IFERROR(GOOGLEFINANCE(A73,""closeyest""),"""")"),1265.0) -> 1265 | V73: =IFERROR(__xludf.DUMMYFUNCTION("IFERROR(GOOGLEFINANCE(A73,""changepct""),"""")"),-1.19) -> -1.19 | W73: =IFERROR(__xludf.DUMMYFUNCTION("IFERROR(GOOGLEFINANCE(A73,""priceopen""),"""")"),1280.0) -> 1280 | X73: =IFERROR(__xludf.DUMMYFUNCTION("IFERROR(GOOGLEFINANCE(A73,""high""),"""")"),1315.0) -> 1315 | Y73: =IFERROR(__xludf.DUMMYFUNCTION("IFERROR(GOOGLEFINANCE(A73,""low""),"""")"),1250.0) -> 1250 | Z73: =IFERROR(__xludf.DUMMYFUNCTION("IFERROR(GOOGLEFINANCE(A73,""volume""),"""")"),2.12091E7) -> 21209100 | AA73: =VLOOKUP(A73,Metrik!$C$2:$Y$959,5,0) -> Oil & Gas | AB73: =VLOOKUP(A73,Metrik!$C$2:$Y$959,3,0) -> Energy
A74: AKRA | B74: {=VLOOKUP(A74,{Metrik!$C$2:$C$998,Metrik!$B$2:$B$998},2,0)} -> AKR Corporindo Tbk. | C74: =IFERROR(__xludf.DUMMYFUNCTION("GOOGLEFINANCE(""IDX:""&A74,""price"")"),1250.0) -> 1250 | D74: =IFERROR(__xludf.DUMMYFUNCTION("IF(A74="""","""", SPARKLINE( INDEX( GOOGLEFINANCE(""IDX:""&A74,""close"",TODAY()-365,TODAY()), ,2 ), {""linewidth"",1} )) "),"#N/A") -> #N/A | E74: Kompas100 | F74: 31 Juli 2026 | G74: =COUNTIFS($B$2:$B$1937,B74,$E$2:$E$1937,"<>") -> 16 | H74: =VLOOKUP(A74,Metrik!$C$2:$Y$959,8,0) -> 9.7 | I74: =VLOOKUP(A74,Metrik!$C$2:$Y$959,9,0) -> 1.5 | J74: =VLOOKUP(A74,Metrik!$C$2:$Y$959,10,0) -> 15.8 | K74: =VLOOKUP(A74,Metrik!$C$2:$Y$959,11,0) -> 6.9 | L74: =VLOOKUP(A74,Metrik!$C$2:$Y$959,12,0) -> 1.3 | M74: =VLOOKUP(A74,Metrik!$C$2:$Y$959,19,0) -> 19.8 | U74: =IFERROR(__xludf.DUMMYFUNCTION("IFERROR(GOOGLEFINANCE(A74,""closeyest""),"""")"),1265.0) -> 1265 | V74: =IFERROR(__xludf.DUMMYFUNCTION("IFERROR(GOOGLEFINANCE(A74,""changepct""),"""")"),-1.19) -> -1.19 | W74: =IFERROR(__xludf.DUMMYFUNCTION("IFERROR(GOOGLEFINANCE(A74,""priceopen""),"""")"),1280.0) -> 1280 | X74: =IFERROR(__xludf.DUMMYFUNCTION("IFERROR(GOOGLEFINANCE(A74,""high""),"""")"),1315.0) -> 1315 | Y74: =IFERROR(__xludf.DUMMYFUNCTION("IFERROR(GOOGLEFINANCE(A74,""low""),"""")"),1250.0) -> 1250 | Z74: =IFERROR(__xludf.DUMMYFUNCTION("IFERROR(GOOGLEFINANCE(A74,""volume""),"""")"),2.12091E7) -> 21209100 | AA74: =VLOOKUP(A74,Metrik!$C$2:$Y$959,5,0) -> Oil & Gas | AB74: =VLOOKUP(A74,Metrik!$C$2:$Y$959,3,0) -> Energy
A75: AKRA | B75: {=VLOOKUP(A75,{Metrik!$C$2:$C$998,Metrik!$B$2:$B$998},2,0)} -> AKR Corporindo Tbk. | C75: =IFERROR(__xludf.DUMMYFUNCTION("GOOGLEFINANCE(""IDX:""&A75,""price"")"),1250.0) -> 1250 | D75: =IFERROR(__xludf.DUMMYFUNCTION("IF(A75="""","""", SPARKLINE( INDEX( GOOGLEFINANCE(""IDX:""&A75,""close"",TODAY()-365,TODAY()), ,2 ), {""linewidth"",1} )) "),"#N/A") -> #N/A | E75: IDXSMC-LIQ | F75: 4 Agustus 2026 | G75: =COUNTIFS($B$2:$B$1937,B75,$E$2:$E$1937,"<>") -> 16 | H75: =VLOOKUP(A75,Metrik!$C$2:$Y$959,8,0) -> 9.7 | I75: =VLOOKUP(A75,Metrik!$C$2:$Y$959,9,0) -> 1.5 | J75: =VLOOKUP(A75,Metrik!$C$2:$Y$959,10,0) -> 15.8 | K75: =VLOOKUP(A75,Metrik!$C$2:$Y$959,11,0) -> 6.9 | L75: =VLOOKUP(A75,Metrik!$C$2:$Y$959,12,0) -> 1.3 | M75: =VLOOKUP(A75,Metrik!$C$2:$Y$959,19,0) -> 19.8 | U75: =IFERROR(__xludf.DUMMYFUNCTION("IFERROR(GOOGLEFINANCE(A75,""closeyest""),"""")"),1265.0) -> 1265 | V75: =IFERROR(__xludf.DUMMYFUNCTION("IFERROR(GOOGLEFINANCE(A75,""changepct""),"""")"),-1.19) -> -1.19 | W75: =IFERROR(__xludf.DUMMYFUNCTION("IFERROR(GOOGLEFINANCE(A75,""priceopen""),"""")"),1280.0) -> 1280 | X75: =IFERROR(__xludf.DUMMYFUNCTION("IFERROR(GOOGLEFINANCE(A75,""high""),"""")"),1315.0) -> 1315 | Y75: =IFERROR(__xludf.DUMMYFUNCTION("IFERROR(GOOGLEFINANCE(A75,""low""),"""")"),1250.0) -> 1250 | Z75: =IFERROR(__xludf.DUMMYFUNCTION("IFERROR(GOOGLEFINANCE(A75,""volume""),"""")"),2.12091E7) -> 21209100 | AA75: =VLOOKUP(A75,Metrik!$C$2:$Y$959,5,0) -> Oil & Gas | AB75: =VLOOKUP(A75,Metrik!$C$2:$Y$959,3,0) -> Energy
A76: AKRA | B76: {=VLOOKUP(A76,{Metrik!$C$2:$C$998,Metrik!$B$2:$B$998},2,0)} -> AKR Corporindo Tbk. | C76: =IFERROR(__xludf.DUMMYFUNCTION("GOOGLEFINANCE(""IDX:""&A76,""price"")"),1250.0) -> 1250 | D76: =IFERROR(__xludf.DUMMYFUNCTION("IF(A76="""","""", SPARKLINE( INDEX( GOOGLEFINANCE(""IDX:""&A76,""close"",TODAY()-365,TODAY()), ,2 ), {""linewidth"",1} )) "),"#N/A") -> #N/A | E76: IDXQ30 | F76: 4 Agustus 2026 | G76: =COUNTIFS($B$2:$B$1937,B76,$E$2:$E$1937,"<>") -> 16 | H76: =VLOOKUP(A76,Metrik!$C$2:$Y$959,8,0) -> 9.7 | I76: =VLOOKUP(A76,Metrik!$C$2:$Y$959,9,0) -> 1.5 | J76: =VLOOKUP(A76,Metrik!$C$2:$Y$959,10,0) -> 15.8 | K76: =VLOOKUP(A76,Metrik!$C$2:$Y$959,11,0) -> 6.9 | L76: =VLOOKUP(A76,Metrik!$C$2:$Y$959,12,0) -> 1.3 | M76: =VLOOKUP(A76,Metrik!$C$2:$Y$959,19,0) -> 19.8 | U76: =IFERROR(__xludf.DUMMYFUNCTION("IFERROR(GOOGLEFINANCE(A76,""closeyest""),"""")"),1265.0) -> 1265 | V76: =IFERROR(__xludf.DUMMYFUNCTION("IFERROR(GOOGLEFINANCE(A76,""changepct""),"""")"),-1.19) -> -1.19 | W76: =IFERROR(__xludf.DUMMYFUNCTION("IFERROR(GOOGLEFINANCE(A76,""priceopen""),"""")"),1280.0) -> 1280 | X76: =IFERROR(__xludf.DUMMYFUNCTION("IFERROR(GOOGLEFINANCE(A76,""high""),"""")"),1315.0) -> 1315 | Y76: =IFERROR(__xludf.DUMMYFUNCTION("IFERROR(GOOGLEFINANCE(A76,""low""),"""")"),1250.0) -> 1250 | Z76: =IFERROR(__xludf.DUMMYFUNCTION("IFERROR(GOOGLEFINANCE(A76,""volume""),"""")"),2.12091E7) -> 21209100 | AA76: =VLOOKUP(A76,Metrik!$C$2:$Y$959,5,0) -> Oil & Gas | AB76: =VLOOKUP(A76,Metrik!$C$2:$Y$959,3,0) -> Energy
A77: AKRA | B77: {=VLOOKUP(A77,{Metrik!$C$2:$C$998,Metrik!$B$2:$B$998},2,0)} -> AKR Corporindo Tbk. | C77: =IFERROR(__xludf.DUMMYFUNCTION("GOOGLEFINANCE(""IDX:""&A77,""price"")"),1250.0) -> 1250 | D77: =IFERROR(__xludf.DUMMYFUNCTION("IF(A77="""","""", SPARKLINE( INDEX( GOOGLEFINANCE(""IDX:""&A77,""close"",TODAY()-365,TODAY()), ,2 ), {""linewidth"",1} )) "),"#N/A") -> #N/A | E77: IDXG30 | F77: 4 Agustus 2026 | G77: =COUNTIFS($B$2:$B$1937,B77,$E$2:$E$1937,"<>") -> 16 | H77: =VLOOKUP(A77,Metrik!$C$2:$Y$959,8,0) -> 9.7 | I77: =VLOOKUP(A77,Metrik!$C$2:$Y$959,9,0) -> 1.5 | J77: =VLOOKUP(A77,Metrik!$C$2:$Y$959,10,0) -> 15.8 | K77: =VLOOKUP(A77,Metrik!$C$2:$Y$959,11,0) -> 6.9 | L77: =VLOOKUP(A77,Metrik!$C$2:$Y$959,12,0) -> 1.3 | M77: =VLOOKUP(A77,Metrik!$C$2:$Y$959,19,0) -> 19.8 | U77: =IFERROR(__xludf.DUMMYFUNCTION("IFERROR(GOOGLEFINANCE(A77,""closeyest""),"""")"),1265.0) -> 1265 | V77: =IFERROR(__xludf.DUMMYFUNCTION("IFERROR(GOOGLEFINANCE(A77,""changepct""),"""")"),-1.19) -> -1.19 | W77: =IFERROR(__xludf.DUMMYFUNCTION("IFERROR(GOOGLEFINANCE(A77,""priceopen""),"""")"),1280.0) -> 1280 | X77: =IFERROR(__xludf.DUMMYFUNCTION("IFERROR(GOOGLEFINANCE(A77,""high""),"""")"),1315.0) -> 1315 | Y77: =IFERROR(__xludf.DUMMYFUNCTION("IFERROR(GOOGLEFINANCE(A77,""low""),"""")"),1250.0) -> 1250 | Z77: =IFERROR(__xludf.DUMMYFUNCTION("IFERROR(GOOGLEFINANCE(A77,""volume""),"""")"),2.12091E7) -> 21209100 | AA77: =VLOOKUP(A77,Metrik!$C$2:$Y$959,5,0) -> Oil & Gas | AB77: =VLOOKUP(A77,Metrik!$C$2:$Y$959,3,0) -> Energy
A78: AKRA | B78: {=VLOOKUP(A78,{Metrik!$C$2:$C$998,Metrik!$B$2:$B$998},2,0)} -> AKR Corporindo Tbk. | C78: =IFERROR(__xludf.DUMMYFUNCTION("GOOGLEFINANCE(""IDX:""&A78,""price"")"),1250.0) -> 1250 | D78: =IFERROR(__xludf.DUMMYFUNCTION("IF(A78="""","""", SPARKLINE( INDEX( GOOGLEFINANCE(""IDX:""&A78,""close"",TODAY()-365,TODAY()), ,2 ), {""linewidth"",1} )) "),"#N/A") -> #N/A | E78: BISNIS-27 | F78: 30 Oktober 2026 | G78: =COUNTIFS($B$2:$B$1937,B78,$E$2:$E$1937,"<>") -> 16 | H78: =VLOOKUP(A78,Metrik!$C$2:$Y$959,8,0) -> 9.7 | I78: =VLOOKUP(A78,Metrik!$C$2:$Y$959,9,0) -> 1.5 | J78: =VLOOKUP(A78,Metrik!$C$2:$Y$959,10,0) -> 15.8 | K78: =VLOOKUP(A78,Metrik!$C$2:$Y$959,11,0) -> 6.9 | L78: =VLOOKUP(A78,Metrik!$C$2:$Y$959,12,0) -> 1.3 | M78: =VLOOKUP(A78,Metrik!$C$2:$Y$959,19,0) -> 19.8 | U78: =IFERROR(__xludf.DUMMYFUNCTION("IFERROR(GOOGLEFINANCE(A78,""closeyest""),"""")"),1265.0) -> 1265 | V78: =IFERROR(__xludf.DUMMYFUNCTION("IFERROR(GOOGLEFINANCE(A78,""changepct""),"""")"),-1.19) -> -1.19 | W78: =IFERROR(__xludf.DUMMYFUNCTION("IFERROR(GOOGLEFINANCE(A78,""priceopen""),"""")"),1280.0) -> 1280 | X78: =IFERROR(__xludf.DUMMYFUNCTION("IFERROR(GOOGLEFINANCE(A78,""high""),"""")"),1315.0) -> 1315 | Y78: =IFERROR(__xludf.DUMMYFUNCTION("IFERROR(GOOGLEFINANCE(A78,""low""),"""")"),1250.0) -> 1250 | Z78: =IFERROR(__xludf.DUMMYFUNCTION("IFERROR(GOOGLEFINANCE(A78,""volume""),"""")"),2.12091E7) -> 21209100 | AA78: =VLOOKUP(A78,Metrik!$C$2:$Y$959,5,0) -> Oil & Gas | AB78: =VLOOKUP(A78,Metrik!$C$2:$Y$959,3,0) -> Energy
A79: AKRA | B79: {=VLOOKUP(A79,{Metrik!$C$2:$C$998,Metrik!$B$2:$B$998},2,0)} -> AKR Corporindo Tbk. | C79: =IFERROR(__xludf.DUMMYFUNCTION("GOOGLEFINANCE(""IDX:""&A79,""price"")"),1250.0) -> 1250 | D79: =IFERROR(__xludf.DUMMYFUNCTION("IF(A79="""","""", SPARKLINE( INDEX( GOOGLEFINANCE(""IDX:""&A79,""close"",TODAY()-365,TODAY()), ,2 ), {""linewidth"",1} )) "),"#N/A") -> #N/A | E79: MSCI Small Cap | F79: 12 Agustus 2026 | G79: =COUNTIFS($B$2:$B$1937,B79,$E$2:$E$1937,"<>") -> 16 | H79: =VLOOKUP(A79,Metrik!$C$2:$Y$959,8,0) -> 9.7 | I79: =VLOOKUP(A79,Metrik!$C$2:$Y$959,9,0) -> 1.5 | J79: =VLOOKUP(A79,Metrik!$C$2:$Y$959,10,0) -> 15.8 | K79: =VLOOKUP(A79,Metrik!$C$2:$Y$959,11,0) -> 6.9 | L79: =VLOOKUP(A79,Metrik!$C$2:$Y$959,12,0) -> 1.3 | M79: =VLOOKUP(A79,Metrik!$C$2:$Y$959,19,0) -> 19.8 | U79: =IFERROR(__xludf.DUMMYFUNCTION("IFERROR(GOOGLEFINANCE(A79,""closeyest""),"""")"),1265.0) -> 1265 | V79: =IFERROR(__xludf.DUMMYFUNCTION("IFERROR(GOOGLEFINANCE(A79,""changepct""),"""")"),-1.19) -> -1.19 | W79: =IFERROR(__xludf.DUMMYFUNCTION("IFERROR(GOOGLEFINANCE(A79,""priceopen""),"""")"),1280.0) -> 1280 | X79: =IFERROR(__xludf.DUMMYFUNCTION("IFERROR(GOOGLEFINANCE(A79,""high""),"""")"),1315.0) -> 1315 | Y79: =IFERROR(__xludf.DUMMYFUNCTION("IFERROR(GOOGLEFINANCE(A79,""low""),"""")"),1250.0) -> 1250 | Z79: =IFERROR(__xludf.DUMMYFUNCTION("IFERROR(GOOGLEFINANCE(A79,""volume""),"""")"),2.12091E7) -> 21209100 | AA79: =VLOOKUP(A79,Metrik!$C$2:$Y$959,5,0) -> Oil & Gas | AB79: =VLOOKUP(A79,Metrik!$C$2:$Y$959,3,0) -> Energy
A80: AKRA | B80: {=VLOOKUP(A80,{Metrik!$C$2:$C$998,Metrik!$B$2:$B$998},2,0)} -> AKR Corporindo Tbk. | C80: =IFERROR(__xludf.DUMMYFUNCTION("GOOGLEFINANCE(""IDX:""&A80,""price"")"),1250.0) -> 1250 | D80: =IFERROR(__xludf.DUMMYFUNCTION("IF(A80="""","""", SPARKLINE( INDEX( GOOGLEFINANCE(""IDX:""&A80,""close"",TODAY()-365,TODAY()), ,2 ), {""linewidth"",1} )) "),"#N/A") -> #N/A | E80: ESGSKEHATI | F80: 46356 | G80: =COUNTIFS($B$2:$B$1937,B80,$E$2:$E$1937,"<>") -> 16 | H80: =VLOOKUP(A80,Metrik!$C$2:$Y$959,8,0) -> 9.7 | I80: =VLOOKUP(A80,Metrik!$C$2:$Y$959,9,0) -> 1.5 | J80: =VLOOKUP(A80,Metrik!$C$2:$Y$959,10,0) -> 15.8 | K80: =VLOOKUP(A80,Metrik!$C$2:$Y$959,11,0) -> 6.9 | L80: =VLOOKUP(A80,Metrik!$C$2:$Y$959,12,0) -> 1.3 | M80: =VLOOKUP(A80,Metrik!$C$2:$Y$959,19,0) -> 19.8 | U80: =IFERROR(__xludf.DUMMYFUNCTION("IFERROR(GOOGLEFINANCE(A80,""closeyest""),"""")"),1265.0) -> 1265 | V80: =IFERROR(__xludf.DUMMYFUNCTION("IFERROR(GOOGLEFINANCE(A80,""changepct""),"""")"),-1.19) -> -1.19 | W80: =IFERROR(__xludf.DUMMYFUNCTION("IFERROR(GOOGLEFINANCE(A80,""priceopen""),"""")"),1280.0) -> 1280 | X80: =IFERROR(__xludf.DUMMYFUNCTION("IFERROR(GOOGLEFINANCE(A80,""high""),"""")"),1315.0) -> 1315 | Y80: =IFERROR(__xludf.DUMMYFUNCTION("IFERROR(GOOGLEFINANCE(A80,""low""),"""")"),1250.0) -> 1250 | Z80: =IFERROR(__xludf.DUMMYFUNCTION("IFERROR(GOOGLEFINANCE(A80,""volume""),"""")"),2.12091E7) -> 21209100 | AA80: =VLOOKUP(A80,Metrik!$C$2:$Y$959,5,0) -> Oil & Gas | AB80: =VLOOKUP(A80,Metrik!$C$2:$Y$959,3,0) -> Energy
A81: AKRA | B81: {=VLOOKUP(A81,{Metrik!$C$2:$C$998,Metrik!$B$2:$B$998},2,0)} -> AKR Corporindo Tbk. | C81: =IFERROR(__xludf.DUMMYFUNCTION("GOOGLEFINANCE(""IDX:""&A81,""price"")"),1250.0) -> 1250 | D81: =IFERROR(__xludf.DUMMYFUNCTION("IF(A81="""","""", SPARKLINE( INDEX( GOOGLEFINANCE(""IDX:""&A81,""close"",TODAY()-365,TODAY()), ,2 ), {""linewidth"",1} )) "),"#N/A") -> #N/A | E81: SRI-KEHATI | F81: 46356 | G81: =COUNTIFS($B$2:$B$1937,B81,$E$2:$E$1937,"<>") -> 16 | H81: =VLOOKUP(A81,Metrik!$C$2:$Y$959,8,0) -> 9.7 | I81: =VLOOKUP(A81,Metrik!$C$2:$Y$959,9,0) -> 1.5 | J81: =VLOOKUP(A81,Metrik!$C$2:$Y$959,10,0) -> 15.8 | K81: =VLOOKUP(A81,Metrik!$C$2:$Y$959,11,0) -> 6.9 | L81: =VLOOKUP(A81,Metrik!$C$2:$Y$959,12,0) -> 1.3 | M81: =VLOOKUP(A81,Metrik!$C$2:$Y$959,19,0) -> 19.8 | U81: =IFERROR(__xludf.DUMMYFUNCTION("IFERROR(GOOGLEFINANCE(A81,""closeyest""),"""")"),1265.0) -> 1265 | V81: =IFERROR(__xludf.DUMMYFUNCTION("IFERROR(GOOGLEFINANCE(A81,""changepct""),"""")"),-1.19) -> -1.19 | W81: =IFERROR(__xludf.DUMMYFUNCTION("IFERROR(GOOGLEFINANCE(A81,""priceopen""),"""")"),1280.0) -> 1280 | X81: =IFERROR(__xludf.DUMMYFUNCTION("IFERROR(GOOGLEFINANCE(A81,""high""),"""")"),1315.0) -> 1315 | Y81: =IFERROR(__xludf.DUMMYFUNCTION("IFERROR(GOOGLEFINANCE(A81,""low""),"""")"),1250.0) -> 1250 | Z81: =IFERROR(__xludf.DUMMYFUNCTION("IFERROR(GOOGLEFINANCE(A81,""volume""),"""")"),2.12091E7) -> 21209100 | AA81: =VLOOKUP(A81,Metrik!$C$2:$Y$959,5,0) -> Oil & Gas | AB81: =VLOOKUP(A81,Metrik!$C$2:$Y$959,3,0) -> Energy
A82: AKRA | B82: {=VLOOKUP(A82,{Metrik!$C$2:$C$998,Metrik!$B$2:$B$998},2,0)} -> AKR Corporindo Tbk. | C82: =IFERROR(__xludf.DUMMYFUNCTION("GOOGLEFINANCE(""IDX:""&A82,""price"")"),1250.0) -> 1250 | D82: =IFERROR(__xludf.DUMMYFUNCTION("IF(A82="""","""", SPARKLINE( INDEX( GOOGLEFINANCE(""IDX:""&A82,""close"",TODAY()-365,TODAY()), ,2 ), {""linewidth"",1} )) "),"#N/A") -> #N/A | E82: Investor33 | F82: 46356 | G82: =COUNTIFS($B$2:$B$1937,B82,$E$2:$E$1937,"<>") -> 16 | H82: =VLOOKUP(A82,Metrik!$C$2:$Y$959,8,0) -> 9.7 | I82: =VLOOKUP(A82,Metrik!$C$2:$Y$959,9,0) -> 1.5 | J82: =VLOOKUP(A82,Metrik!$C$2:$Y$959,10,0) -> 15.8 | K82: =VLOOKUP(A82,Metrik!$C$2:$Y$959,11,0) -> 6.9 | L82: =VLOOKUP(A82,Metrik!$C$2:$Y$959,12,0) -> 1.3 | M82: =VLOOKUP(A82,Metrik!$C$2:$Y$959,19,0) -> 19.8 | U82: =IFERROR(__xludf.DUMMYFUNCTION("IFERROR(GOOGLEFINANCE(A82,""closeyest""),"""")"),1265.0) -> 1265 | V82: =IFERROR(__xludf.DUMMYFUNCTION("IFERROR(GOOGLEFINANCE(A82,""changepct""),"""")"),-1.19) -> -1.19 | W82: =IFERROR(__xludf.DUMMYFUNCTION("IFERROR(GOOGLEFINANCE(A82,""priceopen""),"""")"),1280.0) -> 1280 | X82: =IFERROR(__xludf.DUMMYFUNCTION("IFERROR(GOOGLEFINANCE(A82,""high""),"""")"),1315.0) -> 1315 | Y82: =IFERROR(__xludf.DUMMYFUNCTION("IFERROR(GOOGLEFINANCE(A82,""low""),"""")"),1250.0) -> 1250 | Z82: =IFERROR(__xludf.DUMMYFUNCTION("IFERROR(GOOGLEFINANCE(A82,""volume""),"""")"),2.12091E7) -> 21209100 | AA82: =VLOOKUP(A82,Metrik!$C$2:$Y$959,5,0) -> Oil & Gas | AB82: =VLOOKUP(A82,Metrik!$C$2:$Y$959,3,0) -> Energy
A83: AKRA | B83: {=VLOOKUP(A83,{Metrik!$C$2:$C$998,Metrik!$B$2:$B$998},2,0)} -> AKR Corporindo Tbk. | C83: =IFERROR(__xludf.DUMMYFUNCTION("GOOGLEFINANCE(""IDX:""&A83,""price"")"),1250.0) -> 1250 | D83: =IFERROR(__xludf.DUMMYFUNCTION("IF(A83="""","""", SPARKLINE( INDEX( GOOGLEFINANCE(""IDX:""&A83,""close"",TODAY()-365,TODAY()), ,2 ), {""linewidth"",1} )) "),"#N/A") -> #N/A | E83: JII70 | F83: 46356 | G83: =COUNTIFS($B$2:$B$1937,B83,$E$2:$E$1937,"<>") -> 16 | H83: =VLOOKUP(A83,Metrik!$C$2:$Y$959,8,0) -> 9.7 | I83: =VLOOKUP(A83,Metrik!$C$2:$Y$959,9,0) -> 1.5 | J83: =VLOOKUP(A83,Metrik!$C$2:$Y$959,10,0) -> 15.8 | K83: =VLOOKUP(A83,Metrik!$C$2:$Y$959,11,0) -> 6.9 | L83: =VLOOKUP(A83,Metrik!$C$2:$Y$959,12,0) -> 1.3 | M83: =VLOOKUP(A83,Metrik!$C$2:$Y$959,19,0) -> 19.8 | U83: =IFERROR(__xludf.DUMMYFUNCTION("IFERROR(GOOGLEFINANCE(A83,""closeyest""),"""")"),1265.0) -> 1265 | V83: =IFERROR(__xludf.DUMMYFUNCTION("IFERROR(GOOGLEFINANCE(A83,""changepct""),"""")"),-1.19) -> -1.19 | W83: =IFERROR(__xludf.DUMMYFUNCTION("IFERROR(GOOGLEFINANCE(A83,""priceopen""),"""")"),1280.0) -> 1280 | X83: =IFERROR(__xludf.DUMMYFUNCTION("IFERROR(GOOGLEFINANCE(A83,""high""),"""")"),1315.0) -> 1315 | Y83: =IFERROR(__xludf.DUMMYFUNCTION("IFERROR(GOOGLEFINANCE(A83,""low""),"""")"),1250.0) -> 1250 | Z83: =IFERROR(__xludf.DUMMYFUNCTION("IFERROR(GOOGLEFINANCE(A83,""volume""),"""")"),2.12091E7) -> 21209100 | AA83: =VLOOKUP(A83,Metrik!$C$2:$Y$959,5,0) -> Oil & Gas | AB83: =VLOOKUP(A83,Metrik!$C$2:$Y$959,3,0) -> Energy
A84: AKSI | B84: {=VLOOKUP(A84,{Metrik!$C$2:$C$998,Metrik!$B$2:$B$998},2,0)} -> PT Maming Enam Sembilan Mineral Tbk. | C84: =IFERROR(__xludf.DUMMYFUNCTION("GOOGLEFINANCE(""IDX:""&A84,""price"")"),183.0) -> 183 | D84: =IFERROR(__xludf.DUMMYFUNCTION("IF(A84="""","""", SPARKLINE( INDEX( GOOGLEFINANCE(""IDX:""&A84,""close"",TODAY()-365,TODAY()), ,2 ), {""linewidth"",1} )) "),"#N/A") -> #N/A | G84: =COUNTIFS($B$2:$B$1937,B84,$E$2:$E$1937,"<>") -> 0 | H84: =VLOOKUP(A84,Metrik!$C$2:$Y$959,8,0) -> -16.7 | I84: =VLOOKUP(A84,Metrik!$C$2:$Y$959,9,0) -> 1 | J84: =VLOOKUP(A84,Metrik!$C$2:$Y$959,10,0) -> -6.2 | K84: =VLOOKUP(A84,Metrik!$C$2:$Y$959,11,0) -> -3.2 | L84: =VLOOKUP(A84,Metrik!$C$2:$Y$959,12,0) -> 0.97 | M84: =VLOOKUP(A84,Metrik!$C$2:$Y$959,19,0) -> -12.7 | U84: =IFERROR(__xludf.DUMMYFUNCTION("IFERROR(GOOGLEFINANCE(A84,""closeyest""),"""")"),177.0) -> 177 | V84: =IFERROR(__xludf.DUMMYFUNCTION("IFERROR(GOOGLEFINANCE(A84,""changepct""),"""")"),3.39) -> 3.39 | W84: =IFERROR(__xludf.DUMMYFUNCTION("IFERROR(GOOGLEFINANCE(A84,""priceopen""),"""")"),"") | X84: =IFERROR(__xludf.DUMMYFUNCTION("IFERROR(GOOGLEFINANCE(A84,""high""),"""")"),192.0) -> 192 | Y84: =IFERROR(__xludf.DUMMYFUNCTION("IFERROR(GOOGLEFINANCE(A84,""low""),"""")"),178.0) -> 178 | Z84: =IFERROR(__xludf.DUMMYFUNCTION("IFERROR(GOOGLEFINANCE(A84,""volume""),"""")"),667600.0) -> 667600 | AA84: =VLOOKUP(A84,Metrik!$C$2:$Y$959,5,0) -> Logistics & Deliveries | AB84: =VLOOKUP(A84,Metrik!$C$2:$Y$959,3,0) -> Transportation & Logistic
A85: ALDO | B85: {=VLOOKUP(A85,{Metrik!$C$2:$C$998,Metrik!$B$2:$B$998},2,0)} -> Alkindo Naratama Tbk. | C85: =IFERROR(__xludf.DUMMYFUNCTION("GOOGLEFINANCE(""IDX:""&A85,""price"")"),705.0) -> 705 | D85: =IFERROR(__xludf.DUMMYFUNCTION("IF(A85="""","""", SPARKLINE( INDEX( GOOGLEFINANCE(""IDX:""&A85,""close"",TODAY()-365,TODAY()), ,2 ), {""linewidth"",1} )) "),"#N/A") -> #N/A | G85: =COUNTIFS($B$2:$B$1937,B85,$E$2:$E$1937,"<>") -> 0 | H85: =VLOOKUP(A85,Metrik!$C$2:$Y$959,8,0) -> 44.4 | I85: =VLOOKUP(A85,Metrik!$C$2:$Y$959,9,0) -> 1.7 | J85: =VLOOKUP(A85,Metrik!$C$2:$Y$959,10,0) -> 3.9 | K85: =VLOOKUP(A85,Metrik!$C$2:$Y$959,11,0) -> 2 | L85: =VLOOKUP(A85,Metrik!$C$2:$Y$959,12,0) -> 0.97 | M85: =VLOOKUP(A85,Metrik!$C$2:$Y$959,19,0) -> 7.8 | U85: =IFERROR(__xludf.DUMMYFUNCTION("IFERROR(GOOGLEFINANCE(A85,""closeyest""),"""")"),"") | V85: =IFERROR(__xludf.DUMMYFUNCTION("IFERROR(GOOGLEFINANCE(A85,""changepct""),"""")"),-1.4) -> -1.4 | W85: =IFERROR(__xludf.DUMMYFUNCTION("IFERROR(GOOGLEFINANCE(A85,""priceopen""),"""")"),685.0) -> 685 | X85: =IFERROR(__xludf.DUMMYFUNCTION("IFERROR(GOOGLEFINANCE(A85,""high""),"""")"),715.0) -> 715 | Y85: =IFERROR(__xludf.DUMMYFUNCTION("IFERROR(GOOGLEFINANCE(A85,""low""),"""")"),685.0) -> 685 | Z85: =IFERROR(__xludf.DUMMYFUNCTION("IFERROR(GOOGLEFINANCE(A85,""volume""),"""")"),38000.0) -> 38000 | AA85: =VLOOKUP(A85,Metrik!$C$2:$Y$959,5,0) -> Containers & Packaging | AB85: =VLOOKUP(A85,Metrik!$C$2:$Y$959,3,0) -> Basic Materials
A86: ALII | B86: {=VLOOKUP(A86,{Metrik!$C$2:$C$998,Metrik!$B$2:$B$998},2,0)} -> Ancara Logistics Indonesia Tbk. | C86: =IFERROR(__xludf.DUMMYFUNCTION("GOOGLEFINANCE(""IDX:""&A86,""price"")"),835.0) -> 835 | D86: =IFERROR(__xludf.DUMMYFUNCTION("IF(A86="""","""", SPARKLINE( INDEX( GOOGLEFINANCE(""IDX:""&A86,""close"",TODAY()-365,TODAY()), ,2 ), {""linewidth"",1} )) "),"#N/A") -> #N/A | G86: =COUNTIFS($B$2:$B$1937,B86,$E$2:$E$1937,"<>") -> 0 | H86: =VLOOKUP(A86,Metrik!$C$2:$Y$959,8,0) -> 35.1 | I86: =VLOOKUP(A86,Metrik!$C$2:$Y$959,9,0) -> 5.8 | J86: =VLOOKUP(A86,Metrik!$C$2:$Y$959,10,0) -> 16.4 | K86: =VLOOKUP(A86,Metrik!$C$2:$Y$959,11,0) -> 12.8 | L86: =VLOOKUP(A86,Metrik!$C$2:$Y$959,12,0) -> 0.28 | M86: =VLOOKUP(A86,Metrik!$C$2:$Y$959,19,0) -> 140 | U86: =IFERROR(__xludf.DUMMYFUNCTION("IFERROR(GOOGLEFINANCE(A86,""closeyest""),"""")"),785.0) -> 785 | V86: =IFERROR(__xludf.DUMMYFUNCTION("IFERROR(GOOGLEFINANCE(A86,""changepct""),"""")"),6.37) -> 6.37 | W86: =IFERROR(__xludf.DUMMYFUNCTION("IFERROR(GOOGLEFINANCE(A86,""priceopen""),"""")"),785.0) -> 785 | X86: =IFERROR(__xludf.DUMMYFUNCTION("IFERROR(GOOGLEFINANCE(A86,""high""),"""")"),850.0) -> 850 | Y86: =IFERROR(__xludf.DUMMYFUNCTION("IFERROR(GOOGLEFINANCE(A86,""low""),"""")"),785.0) -> 785 | Z86: =IFERROR(__xludf.DUMMYFUNCTION("IFERROR(GOOGLEFINANCE(A86,""volume""),"""")"),1472800.0) -> 1472800 | AA86: =VLOOKUP(A86,Metrik!$C$2:$Y$959,5,0) -> Coal | AB86: =VLOOKUP(A86,Metrik!$C$2:$Y$959,3,0) -> Energy
A87: ALKA | B87: {=VLOOKUP(A87,{Metrik!$C$2:$C$998,Metrik!$B$2:$B$998},2,0)} -> Alakasa Industrindo Tbk | C87: =IFERROR(__xludf.DUMMYFUNCTION("GOOGLEFINANCE(""IDX:""&A87,""price"")"),605.0) -> 605 | D87: =IFERROR(__xludf.DUMMYFUNCTION("IF(A87="""","""", SPARKLINE( INDEX( GOOGLEFINANCE(""IDX:""&A87,""close"",TODAY()-365,TODAY()), ,2 ), {""linewidth"",1} )) "),"#N/A") -> #N/A | G87: =COUNTIFS($B$2:$B$1937,B87,$E$2:$E$1937,"<>") -> 0 | H87: =VLOOKUP(A87,Metrik!$C$2:$Y$959,8,0) -> 16.7 | I87: =VLOOKUP(A87,Metrik!$C$2:$Y$959,9,0) -> 1.2 | J87: =VLOOKUP(A87,Metrik!$C$2:$Y$959,10,0) -> 7.3 | K87: =VLOOKUP(A87,Metrik!$C$2:$Y$959,11,0) -> 6.4 | L87: =VLOOKUP(A87,Metrik!$C$2:$Y$959,12,0) -> 0.13 | M87: =VLOOKUP(A87,Metrik!$C$2:$Y$959,19,0) -> 90.1 | U87: =IFERROR(__xludf.DUMMYFUNCTION("IFERROR(GOOGLEFINANCE(A87,""closeyest""),"""")"),615.0) -> 615 | V87: =IFERROR(__xludf.DUMMYFUNCTION("IFERROR(GOOGLEFINANCE(A87,""changepct""),"""")"),-1.63) -> -1.63 | W87: =IFERROR(__xludf.DUMMYFUNCTION("IFERROR(GOOGLEFINANCE(A87,""priceopen""),"""")"),625.0) -> 625 | X87: =IFERROR(__xludf.DUMMYFUNCTION("IFERROR(GOOGLEFINANCE(A87,""high""),"""")"),645.0) -> 645 | Y87: =IFERROR(__xludf.DUMMYFUNCTION("IFERROR(GOOGLEFINANCE(A87,""low""),"""")"),605.0) -> 605 | Z87: =IFERROR(__xludf.DUMMYFUNCTION("IFERROR(GOOGLEFINANCE(A87,""volume""),"""")"),182200.0) -> 182200 | AA87: =VLOOKUP(A87,Metrik!$C$2:$Y$959,5,0) -> Metals & Minerals | AB87: =VLOOKUP(A87,Metrik!$C$2:$Y$959,3,0) -> Basic Materials
A88: ALMI | B88: {=VLOOKUP(A88,{Metrik!$C$2:$C$998,Metrik!$B$2:$B$998},2,0)} -> Alumindo Light Metal Industry Tbk. | C88: =IFERROR(__xludf.DUMMYFUNCTION("GOOGLEFINANCE(""IDX:""&A88,""price"")"),74.0) -> 74 | D88: =IFERROR(__xludf.DUMMYFUNCTION("IF(A88="""","""", SPARKLINE( INDEX( GOOGLEFINANCE(""IDX:""&A88,""close"",TODAY()-365,TODAY()), ,2 ), {""linewidth"",1} )) "),"#N/A") -> #N/A | G88: =COUNTIFS($B$2:$B$1937,B88,$E$2:$E$1937,"<>") -> 0 | H88: =VLOOKUP(A88,Metrik!$C$2:$Y$959,8,0) -> -5.3 | I88: =VLOOKUP(A88,Metrik!$C$2:$Y$959,9,0) -> 3.6 | J88: =VLOOKUP(A88,Metrik!$C$2:$Y$959,10,0) -> -67.6 | K88: =VLOOKUP(A88,Metrik!$C$2:$Y$959,11,0) -> -11.9 | L88: =VLOOKUP(A88,Metrik!$C$2:$Y$959,12,0) -> 4.7 | M88: =VLOOKUP(A88,Metrik!$C$2:$Y$959,19,0) -> 0 | U88: =IFERROR(__xludf.DUMMYFUNCTION("IFERROR(GOOGLEFINANCE(A88,""closeyest""),"""")"),74.0) -> 74 | V88: =IFERROR(__xludf.DUMMYFUNCTION("IFERROR(GOOGLEFINANCE(A88,""changepct""),"""")"),0.0) -> 0 | W88: =IFERROR(__xludf.DUMMYFUNCTION("IFERROR(GOOGLEFINANCE(A88,""priceopen""),"""")"),"") | X88: =IFERROR(__xludf.DUMMYFUNCTION("IFERROR(GOOGLEFINANCE(A88,""high""),"""")"),"") | Y88: =IFERROR(__xludf.DUMMYFUNCTION("IFERROR(GOOGLEFINANCE(A88,""low""),"""")"),"") | Z88: =IFERROR(__xludf.DUMMYFUNCTION("IFERROR(GOOGLEFINANCE(A88,""volume""),"""")"),0.0) -> 0 | AA88: =VLOOKUP(A88,Metrik!$C$2:$Y$959,5,0) -> Metals & Minerals | AB88: =VLOOKUP(A88,Metrik!$C$2:$Y$959,3,0) -> Basic Materials
A89: ALTO | B89: {=VLOOKUP(A89,{Metrik!$C$2:$C$998,Metrik!$B$2:$B$998},2,0)} -> Tri Banyan Tirta Tbk. | C89: =IFERROR(__xludf.DUMMYFUNCTION("GOOGLEFINANCE(""IDX:""&A89,""price"")"),18.0) -> 18 | D89: =IFERROR(__xludf.DUMMYFUNCTION("IF(A89="""","""", SPARKLINE( INDEX( GOOGLEFINANCE(""IDX:""&A89,""close"",TODAY()-365,TODAY()), ,2 ), {""linewidth"",1} )) "),"#N/A") -> #N/A | G89: =COUNTIFS($B$2:$B$1937,B89,$E$2:$E$1937,"<>") -> 0 | H89: =VLOOKUP(A89,Metrik!$C$2:$Y$959,8,0) -> 0 | I89: =VLOOKUP(A89,Metrik!$C$2:$Y$959,9,0) -> 0.13 | J89: =VLOOKUP(A89,Metrik!$C$2:$Y$959,10,0) -> -14.3 | K89: =VLOOKUP(A89,Metrik!$C$2:$Y$959,11,0) -> -4.6 | L89: =VLOOKUP(A89,Metrik!$C$2:$Y$959,12,0) -> 2.1 | M89: =VLOOKUP(A89,Metrik!$C$2:$Y$959,19,0) -> -71.9 | U89: =IFERROR(__xludf.DUMMYFUNCTION("IFERROR(GOOGLEFINANCE(A89,""closeyest""),"""")"),5.65) -> 5.65 | V89: =IFERROR(__xludf.DUMMYFUNCTION("IFERROR(GOOGLEFINANCE(A89,""changepct""),"""")"),0.88) -> 0.88 | W89: =IFERROR(__xludf.DUMMYFUNCTION("IFERROR(GOOGLEFINANCE(A89,""priceopen""),"""")"),5.69) -> 5.69 | X89: =IFERROR(__xludf.DUMMYFUNCTION("IFERROR(GOOGLEFINANCE(A89,""high""),"""")"),5.85) -> 5.85 | Y89: =IFERROR(__xludf.DUMMYFUNCTION("IFERROR(GOOGLEFINANCE(A89,""low""),"""")"),5.68) -> 5.68 | Z89: =IFERROR(__xludf.DUMMYFUNCTION("IFERROR(GOOGLEFINANCE(A89,""volume""),"""")"),1626662.0) -> 1626662 | AA89: =VLOOKUP(A89,Metrik!$C$2:$Y$959,5,0) -> Beverages | AB89: =VLOOKUP(A89,Metrik!$C$2:$Y$959,3,0) -> Consumer Non-Cyclicals
A90: AMAG | B90: {=VLOOKUP(A90,{Metrik!$C$2:$C$998,Metrik!$B$2:$B$998},2,0)} -> Asuransi Multi Artha Guna Tbk. | C90: =IFERROR(__xludf.DUMMYFUNCTION("GOOGLEFINANCE(""IDX:""&A90,""price"")"),390.0) -> 390 | D90: =IFERROR(__xludf.DUMMYFUNCTION("IF(A90="""","""", SPARKLINE( INDEX( GOOGLEFINANCE(""IDX:""&A90,""close"",TODAY()-365,TODAY()), ,2 ), {""linewidth"",1} )) "),"#N/A") -> #N/A | G90: =COUNTIFS($B$2:$B$1937,B90,$E$2:$E$1937,"<>") -> 0 | H90: =VLOOKUP(A90,Metrik!$C$2:$Y$959,8,0) -> 9.6 | I90: =VLOOKUP(A90,Metrik!$C$2:$Y$959,9,0) -> 0.91 | J90: =VLOOKUP(A90,Metrik!$C$2:$Y$959,10,0) -> 9.4 | K90: =VLOOKUP(A90,Metrik!$C$2:$Y$959,11,0) -> 3.6 | L90: =VLOOKUP(A90,Metrik!$C$2:$Y$959,12,0) -> 1.7 | M90: =VLOOKUP(A90,Metrik!$C$2:$Y$959,19,0) -> 26.1 | U90: =IFERROR(__xludf.DUMMYFUNCTION("IFERROR(GOOGLEFINANCE(A90,""closeyest""),"""")"),378.0) -> 378 | V90: =IFERROR(__xludf.DUMMYFUNCTION("IFERROR(GOOGLEFINANCE(A90,""changepct""),"""")"),3.17) -> 3.17 | W90: =IFERROR(__xludf.DUMMYFUNCTION("IFERROR(GOOGLEFINANCE(A90,""priceopen""),"""")"),390.0) -> 390 | X90: =IFERROR(__xludf.DUMMYFUNCTION("IFERROR(GOOGLEFINANCE(A90,""high""),"""")"),390.0) -> 390 | Y90: =IFERROR(__xludf.DUMMYFUNCTION("IFERROR(GOOGLEFINANCE(A90,""low""),"""")"),380.0) -> 380 | Z90: =IFERROR(__xludf.DUMMYFUNCTION("IFERROR(GOOGLEFINANCE(A90,""volume""),"""")"),12000.0) -> 12000 | AA90: =VLOOKUP(A90,Metrik!$C$2:$Y$959,5,0) -> Insurance | AB90: =VLOOKUP(A90,Metrik!$C$2:$Y$959,3,0) -> Financials
A91: AMAN | B91: {=VLOOKUP(A91,{Metrik!$C$2:$C$998,Metrik!$B$2:$B$998},2,0)} -> Makmur Berkah Amanda Tbk. | C91: =IFERROR(__xludf.DUMMYFUNCTION("GOOGLEFINANCE(""IDX:""&A91,""price"")"),250.0) -> 250 | D91: =IFERROR(__xludf.DUMMYFUNCTION("IF(A91="""","""", SPARKLINE( INDEX( GOOGLEFINANCE(""IDX:""&A91,""close"",TODAY()-365,TODAY()), ,2 ), {""linewidth"",1} )) "),"#N/A") -> #N/A | G91: =COUNTIFS($B$2:$B$1937,B91,$E$2:$E$1937,"<>") -> 0 | H91: =VLOOKUP(A91,Metrik!$C$2:$Y$959,8,0) -> 22.2 | I91: =VLOOKUP(A91,Metrik!$C$2:$Y$959,9,0) -> 1.2 | J91: =VLOOKUP(A91,Metrik!$C$2:$Y$959,10,0) -> 5.3 | K91: =VLOOKUP(A91,Metrik!$C$2:$Y$959,11,0) -> 3 | L91: =VLOOKUP(A91,Metrik!$C$2:$Y$959,12,0) -> 0.76 | M91: =VLOOKUP(A91,Metrik!$C$2:$Y$959,19,0) -> 60.7 | U91: =IFERROR(__xludf.DUMMYFUNCTION("IFERROR(GOOGLEFINANCE(A91,""closeyest""),"""")"),10.08) -> 10.08 | V91: =IFERROR(__xludf.DUMMYFUNCTION("IFERROR(GOOGLEFINANCE(A91,""changepct""),"""")"),0.2) -> 0.2 | W91: =IFERROR(__xludf.DUMMYFUNCTION("IFERROR(GOOGLEFINANCE(A91,""priceopen""),"""")"),10.08) -> 10.08 | X91: =IFERROR(__xludf.DUMMYFUNCTION("IFERROR(GOOGLEFINANCE(A91,""high""),"""")"),10.13) -> 10.13 | Y91: =IFERROR(__xludf.DUMMYFUNCTION("IFERROR(GOOGLEFINANCE(A91,""low""),"""")"),10.07) -> 10.07 | Z91: =IFERROR(__xludf.DUMMYFUNCTION("IFERROR(GOOGLEFINANCE(A91,""volume""),"""")"),21421.0) -> 21421 | AA91: =VLOOKUP(A91,Metrik!$C$2:$Y$959,5,0) -> Real Estate Management & Development | AB91: =VLOOKUP(A91,Metrik!$C$2:$Y$959,3,0) -> Properties & Real Estate
A92: AMAR | B92: {=VLOOKUP(A92,{Metrik!$C$2:$C$998,Metrik!$B$2:$B$998},2,0)} -> Bank Amar Indonesia Tbk. | C92: =IFERROR(__xludf.DUMMYFUNCTION("GOOGLEFINANCE(""IDX:""&A92,""price"")"),198.0) -> 198 | D92: =IFERROR(__xludf.DUMMYFUNCTION("IF(A92="""","""", SPARKLINE( INDEX( GOOGLEFINANCE(""IDX:""&A92,""close"",TODAY()-365,TODAY()), ,2 ), {""linewidth"",1} )) "),"#N/A") -> #N/A | G92: =COUNTIFS($B$2:$B$1937,B92,$E$2:$E$1937,"<>") -> 0 | H92: =VLOOKUP(A92,Metrik!$C$2:$Y$959,8,0) -> 14.1 | I92: =VLOOKUP(A92,Metrik!$C$2:$Y$959,9,0) -> 1 | J92: =VLOOKUP(A92,Metrik!$C$2:$Y$959,10,0) -> 7.3 | K92: =VLOOKUP(A92,Metrik!$C$2:$Y$959,11,0) -> 3.7 | L92: =VLOOKUP(A92,Metrik!$C$2:$Y$959,12,0) -> 0.99 | M92: =VLOOKUP(A92,Metrik!$C$2:$Y$959,19,0) -> 60.8 | N92: 24.03 | O92: 98.47 | P92: 142.67 | Q92: 8.11 | R92: 85.22 | S92: 101 | T92: 11.28 | U92: =IFERROR(__xludf.DUMMYFUNCTION("IFERROR(GOOGLEFINANCE(A92,""closeyest""),"""")"),191.0) -> 191 | V92: =IFERROR(__xludf.DUMMYFUNCTION("IFERROR(GOOGLEFINANCE(A92,""changepct""),"""")"),3.66) -> 3.66 | W92: =IFERROR(__xludf.DUMMYFUNCTION("IFERROR(GOOGLEFINANCE(A92,""priceopen""),"""")"),187.0) -> 187 | X92: =IFERROR(__xludf.DUMMYFUNCTION("IFERROR(GOOGLEFINANCE(A92,""high""),"""")"),198.0) -> 198 | Y92: =IFERROR(__xludf.DUMMYFUNCTION("IFERROR(GOOGLEFINANCE(A92,""low""),"""")"),187.0) -> 187 | Z92: =IFERROR(__xludf.DUMMYFUNCTION("IFERROR(GOOGLEFINANCE(A92,""volume""),"""")"),567600.0) -> 567600 | AA92: =VLOOKUP(A92,Metrik!$C$2:$Y$959,5,0) -> Banks | AB92: =VLOOKUP(A92,Metrik!$C$2:$Y$959,3,0) -> Financials
A93: AMFG | B93: {=VLOOKUP(A93,{Metrik!$C$2:$C$998,Metrik!$B$2:$B$998},2,0)} -> Asahimas Flat Glass Tbk. | C93: =IFERROR(__xludf.DUMMYFUNCTION("GOOGLEFINANCE(""IDX:""&A93,""price"")"),3190.0) -> 3190 | D93: =IFERROR(__xludf.DUMMYFUNCTION("IF(A93="""","""", SPARKLINE( INDEX( GOOGLEFINANCE(""IDX:""&A93,""close"",TODAY()-365,TODAY()), ,2 ), {""linewidth"",1} )) "),"#N/A") -> #N/A | G93: =COUNTIFS($B$2:$B$1937,B93,$E$2:$E$1937,"<>") -> 0 | H93: =VLOOKUP(A93,Metrik!$C$2:$Y$959,8,0) -> 53.1 | I93: =VLOOKUP(A93,Metrik!$C$2:$Y$959,9,0) -> 0.29 | J93: =VLOOKUP(A93,Metrik!$C$2:$Y$959,10,0) -> 0.55 | K93: =VLOOKUP(A93,Metrik!$C$2:$Y$959,11,0) -> 0.36 | L93: =VLOOKUP(A93,Metrik!$C$2:$Y$959,12,0) -> 0.53 | M93: =VLOOKUP(A93,Metrik!$C$2:$Y$959,19,0) -> 2.1 | U93: =IFERROR(__xludf.DUMMYFUNCTION("IFERROR(GOOGLEFINANCE(A93,""closeyest""),"""")"),2840.0) -> 2840 | V93: =IFERROR(__xludf.DUMMYFUNCTION("IFERROR(GOOGLEFINANCE(A93,""changepct""),"""")"),12.32) -> 12.32 | W93: =IFERROR(__xludf.DUMMYFUNCTION("IFERROR(GOOGLEFINANCE(A93,""priceopen""),"""")"),2840.0) -> 2840 | X93: =IFERROR(__xludf.DUMMYFUNCTION("IFERROR(GOOGLEFINANCE(A93,""high""),"""")"),"") | Y93: =IFERROR(__xludf.DUMMYFUNCTION("IFERROR(GOOGLEFINANCE(A93,""low""),"""")"),"") | Z93: =IFERROR(__xludf.DUMMYFUNCTION("IFERROR(GOOGLEFINANCE(A93,""volume""),"""")"),18600.0) -> 18600 | AA93: =VLOOKUP(A93,Metrik!$C$2:$Y$959,5,0) -> Building Products & Fixtures | AB93: =VLOOKUP(A93,Metrik!$C$2:$Y$959,3,0) -> Industrials
A94: AMIN | B94: {=VLOOKUP(A94,{Metrik!$C$2:$C$998,Metrik!$B$2:$B$998},2,0)} -> PT Ateliers Mecaniques D Indonesie Tbk. | C94: =IFERROR(__xludf.DUMMYFUNCTION("GOOGLEFINANCE(""IDX:""&A94,""price"")"),260.0) -> 260 | D94: =IFERROR(__xludf.DUMMYFUNCTION("IF(A94="""","""", SPARKLINE( INDEX( GOOGLEFINANCE(""IDX:""&A94,""close"",TODAY()-365,TODAY()), ,2 ), {""linewidth"",1} )) "),"#N/A") -> #N/A | G94: =COUNTIFS($B$2:$B$1937,B94,$E$2:$E$1937,"<>") -> 0 | H94: =VLOOKUP(A94,Metrik!$C$2:$Y$959,8,0) -> 11.5 | I94: =VLOOKUP(A94,Metrik!$C$2:$Y$959,9,0) -> 1.4 | J94: =VLOOKUP(A94,Metrik!$C$2:$Y$959,10,0) -> 12.3 | K94: =VLOOKUP(A94,Metrik!$C$2:$Y$959,11,0) -> 8.1 | L94: =VLOOKUP(A94,Metrik!$C$2:$Y$959,12,0) -> 0.52 | M94: =VLOOKUP(A94,Metrik!$C$2:$Y$959,19,0) -> 44.9 | U94: =IFERROR(__xludf.DUMMYFUNCTION("IFERROR(GOOGLEFINANCE(A94,""closeyest""),"""")"),0.1) -> 0.1 | V94: =IFERROR(__xludf.DUMMYFUNCTION("IFERROR(GOOGLEFINANCE(A94,""changepct""),"""")"),0.0) -> 0 | W94: =IFERROR(__xludf.DUMMYFUNCTION("IFERROR(GOOGLEFINANCE(A94,""priceopen""),"""")"),"") | X94: =IFERROR(__xludf.DUMMYFUNCTION("IFERROR(GOOGLEFINANCE(A94,""high""),"""")"),"") | Y94: =IFERROR(__xludf.DUMMYFUNCTION("IFERROR(GOOGLEFINANCE(A94,""low""),"""")"),"") | Z94: =IFERROR(__xludf.DUMMYFUNCTION("IFERROR(GOOGLEFINANCE(A94,""volume""),"""")"),0.0) -> 0 | AA94: =VLOOKUP(A94,Metrik!$C$2:$Y$959,5,0) -> Machinery | AB94: =VLOOKUP(A94,Metrik!$C$2:$Y$959,3,0) -> Industrials
A95: AMMN | B95: {=VLOOKUP(A95,{Metrik!$C$2:$C$998,Metrik!$B$2:$B$998},2,0)} -> PT Amman Mineral Internasional Tbk. | C95: =IFERROR(__xludf.DUMMYFUNCTION("GOOGLEFINANCE(""IDX:""&A95,""price"")"),3450.0) -> 3450 | D95: =IFERROR(__xludf.DUMMYFUNCTION("IF(A95="""","""", SPARKLINE( INDEX( GOOGLEFINANCE(""IDX:""&A95,""close"",TODAY()-365,TODAY()), ,2 ), {""linewidth"",1} )) "),"#N/A") -> #N/A | E95: IDX80 | F95: 31 Juli 2026 | G95: =COUNTIFS($B$2:$B$1937,B95,$E$2:$E$1937,"<>") -> 5 | H95: =VLOOKUP(A95,Metrik!$C$2:$Y$959,8,0) -> 26 | I95: =VLOOKUP(A95,Metrik!$C$2:$Y$959,9,0) -> 2.5 | J95: =VLOOKUP(A95,Metrik!$C$2:$Y$959,10,0) -> 9.7 | K95: =VLOOKUP(A95,Metrik!$C$2:$Y$959,11,0) -> 3.9 | L95: =VLOOKUP(A95,Metrik!$C$2:$Y$959,12,0) -> 1.5 | M95: =VLOOKUP(A95,Metrik!$C$2:$Y$959,19,0) -> 67 | U95: =IFERROR(__xludf.DUMMYFUNCTION("IFERROR(GOOGLEFINANCE(A95,""closeyest""),"""")"),3060.0) -> 3060 | V95: =IFERROR(__xludf.DUMMYFUNCTION("IFERROR(GOOGLEFINANCE(A95,""changepct""),"""")"),12.75) -> 12.75 | W95: =IFERROR(__xludf.DUMMYFUNCTION("IFERROR(GOOGLEFINANCE(A95,""priceopen""),"""")"),3150.0) -> 3150 | X95: =IFERROR(__xludf.DUMMYFUNCTION("IFERROR(GOOGLEFINANCE(A95,""high""),"""")"),3540.0) -> 3540 | Y95: =IFERROR(__xludf.DUMMYFUNCTION("IFERROR(GOOGLEFINANCE(A95,""low""),"""")"),3110.0) -> 3110 | Z95: =IFERROR(__xludf.DUMMYFUNCTION("IFERROR(GOOGLEFINANCE(A95,""volume""),"""")"),1.703576E8) -> 170357600 | AA95: =VLOOKUP(A95,Metrik!$C$2:$Y$959,5,0) -> Metals & Minerals | AB95: =VLOOKUP(A95,Metrik!$C$2:$Y$959,3,0) -> Basic Materials
A96: AMMN | B96: {=VLOOKUP(A96,{Metrik!$C$2:$C$998,Metrik!$B$2:$B$998},2,0)} -> PT Amman Mineral Internasional Tbk. | C96: =IFERROR(__xludf.DUMMYFUNCTION("GOOGLEFINANCE(""IDX:""&A96,""price"")"),3450.0) -> 3450 | D96: =IFERROR(__xludf.DUMMYFUNCTION("IF(A96="""","""", SPARKLINE( INDEX( GOOGLEFINANCE(""IDX:""&A96,""close"",TODAY()-365,TODAY()), ,2 ), {""linewidth"",1} )) "),"#N/A") -> #N/A | E96: LQ45 | F96: 31 Juli 2026 | G96: =COUNTIFS($B$2:$B$1937,B96,$E$2:$E$1937,"<>") -> 5 | H96: =VLOOKUP(A96,Metrik!$C$2:$Y$959,8,0) -> 26 | I96: =VLOOKUP(A96,Metrik!$C$2:$Y$959,9,0) -> 2.5 | J96: =VLOOKUP(A96,Metrik!$C$2:$Y$959,10,0) -> 9.7 | K96: =VLOOKUP(A96,Metrik!$C$2:$Y$959,11,0) -> 3.9 | L96: =VLOOKUP(A96,Metrik!$C$2:$Y$959,12,0) -> 1.5 | M96: =VLOOKUP(A96,Metrik!$C$2:$Y$959,19,0) -> 67 | U96: =IFERROR(__xludf.DUMMYFUNCTION("IFERROR(GOOGLEFINANCE(A96,""closeyest""),"""")"),3060.0) -> 3060 | V96: =IFERROR(__xludf.DUMMYFUNCTION("IFERROR(GOOGLEFINANCE(A96,""changepct""),"""")"),12.75) -> 12.75 | W96: =IFERROR(__xludf.DUMMYFUNCTION("IFERROR(GOOGLEFINANCE(A96,""priceopen""),"""")"),3150.0) -> 3150 | X96: =IFERROR(__xludf.DUMMYFUNCTION("IFERROR(GOOGLEFINANCE(A96,""high""),"""")"),3540.0) -> 3540 | Y96: =IFERROR(__xludf.DUMMYFUNCTION("IFERROR(GOOGLEFINANCE(A96,""low""),"""")"),3110.0) -> 3110 | Z96: =IFERROR(__xludf.DUMMYFUNCTION("IFERROR(GOOGLEFINANCE(A96,""volume""),"""")"),1.703576E8) -> 170357600 | AA96: =VLOOKUP(A96,Metrik!$C$2:$Y$959,5,0) -> Metals & Minerals | AB96: =VLOOKUP(A96,Metrik!$C$2:$Y$959,3,0) -> Basic Materials
A97: AMMN | B97: {=VLOOKUP(A97,{Metrik!$C$2:$C$998,Metrik!$B$2:$B$998},2,0)} -> PT Amman Mineral Internasional Tbk. | C97: =IFERROR(__xludf.DUMMYFUNCTION("GOOGLEFINANCE(""IDX:""&A97,""price"")"),3450.0) -> 3450 | D97: =IFERROR(__xludf.DUMMYFUNCTION("IF(A97="""","""", SPARKLINE( INDEX( GOOGLEFINANCE(""IDX:""&A97,""close"",TODAY()-365,TODAY()), ,2 ), {""linewidth"",1} )) "),"#N/A") -> #N/A | E97: Kompas100 | F97: 31 Juli 2026 | G97: =COUNTIFS($B$2:$B$1937,B97,$E$2:$E$1937,"<>") -> 5 | H97: =VLOOKUP(A97,Metrik!$C$2:$Y$959,8,0) -> 26 | I97: =VLOOKUP(A97,Metrik!$C$2:$Y$959,9,0) -> 2.5 | J97: =VLOOKUP(A97,Metrik!$C$2:$Y$959,10,0) -> 9.7 | K97: =VLOOKUP(A97,Metrik!$C$2:$Y$959,11,0) -> 3.9 | L97: =VLOOKUP(A97,Metrik!$C$2:$Y$959,12,0) -> 1.5 | M97: =VLOOKUP(A97,Metrik!$C$2:$Y$959,19,0) -> 67 | U97: =IFERROR(__xludf.DUMMYFUNCTION("IFERROR(GOOGLEFINANCE(A97,""closeyest""),"""")"),3060.0) -> 3060 | V97: =IFERROR(__xludf.DUMMYFUNCTION("IFERROR(GOOGLEFINANCE(A97,""changepct""),"""")"),12.75) -> 12.75 | W97: =IFERROR(__xludf.DUMMYFUNCTION("IFERROR(GOOGLEFINANCE(A97,""priceopen""),"""")"),3150.0) -> 3150 | X97: =IFERROR(__xludf.DUMMYFUNCTION("IFERROR(GOOGLEFINANCE(A97,""high""),"""")"),3540.0) -> 3540 | Y97: =IFERROR(__xludf.DUMMYFUNCTION("IFERROR(GOOGLEFINANCE(A97,""low""),"""")"),3110.0) -> 3110 | Z97: =IFERROR(__xludf.DUMMYFUNCTION("IFERROR(GOOGLEFINANCE(A97,""volume""),"""")"),1.703576E8) -> 170357600 | AA97: =VLOOKUP(A97,Metrik!$C$2:$Y$959,5,0) -> Metals & Minerals | AB97: =VLOOKUP(A97,Metrik!$C$2:$Y$959,3,0) -> Basic Materials
A98: AMMN | B98: {=VLOOKUP(A98,{Metrik!$C$2:$C$998,Metrik!$B$2:$B$998},2,0)} -> PT Amman Mineral Internasional Tbk. | C98: =IFERROR(__xludf.DUMMYFUNCTION("GOOGLEFINANCE(""IDX:""&A98,""price"")"),3450.0) -> 3450 | D98: =IFERROR(__xludf.DUMMYFUNCTION("IF(A98="""","""", SPARKLINE( INDEX( GOOGLEFINANCE(""IDX:""&A98,""close"",TODAY()-365,TODAY()), ,2 ), {""linewidth"",1} )) "),"#N/A") -> #N/A | E98: ECONOMIC30 | F98: 31 Agustus 2026 | G98: =COUNTIFS($B$2:$B$1937,B98,$E$2:$E$1937,"<>") -> 5 | H98: =VLOOKUP(A98,Metrik!$C$2:$Y$959,8,0) -> 26 | I98: =VLOOKUP(A98,Metrik!$C$2:$Y$959,9,0) -> 2.5 | J98: =VLOOKUP(A98,Metrik!$C$2:$Y$959,10,0) -> 9.7 | K98: =VLOOKUP(A98,Metrik!$C$2:$Y$959,11,0) -> 3.9 | L98: =VLOOKUP(A98,Metrik!$C$2:$Y$959,12,0) -> 1.5 | M98: =VLOOKUP(A98,Metrik!$C$2:$Y$959,19,0) -> 67 | U98: =IFERROR(__xludf.DUMMYFUNCTION("IFERROR(GOOGLEFINANCE(A98,""closeyest""),"""")"),3060.0) -> 3060 | V98: =IFERROR(__xludf.DUMMYFUNCTION("IFERROR(GOOGLEFINANCE(A98,""changepct""),"""")"),12.75) -> 12.75 | W98: =IFERROR(__xludf.DUMMYFUNCTION("IFERROR(GOOGLEFINANCE(A98,""priceopen""),"""")"),3150.0) -> 3150 | X98: =IFERROR(__xludf.DUMMYFUNCTION("IFERROR(GOOGLEFINANCE(A98,""high""),"""")"),3540.0) -> 3540 | Y98: =IFERROR(__xludf.DUMMYFUNCTION("IFERROR(GOOGLEFINANCE(A98,""low""),"""")"),3110.0) -> 3110 | Z98: =IFERROR(__xludf.DUMMYFUNCTION("IFERROR(GOOGLEFINANCE(A98,""volume""),"""")"),1.703576E8) -> 170357600 | AA98: =VLOOKUP(A98,Metrik!$C$2:$Y$959,5,0) -> Metals & Minerals | AB98: =VLOOKUP(A98,Metrik!$C$2:$Y$959,3,0) -> Basic Materials
A99: AMMN | B99: {=VLOOKUP(A99,{Metrik!$C$2:$C$998,Metrik!$B$2:$B$998},2,0)} -> PT Amman Mineral Internasional Tbk. | C99: =IFERROR(__xludf.DUMMYFUNCTION("GOOGLEFINANCE(""IDX:""&A99,""price"")"),3450.0) -> 3450 | D99: =IFERROR(__xludf.DUMMYFUNCTION("IF(A99="""","""", SPARKLINE( INDEX( GOOGLEFINANCE(""IDX:""&A99,""close"",TODAY()-365,TODAY()), ,2 ), {""linewidth"",1} )) "),"#N/A") -> #N/A | E99: FTSE Large Cap | F99: Juni 2026 | G99: =COUNTIFS($B$2:$B$1937,B99,$E$2:$E$1937,"<>") -> 5 | H99: =VLOOKUP(A99,Metrik!$C$2:$Y$959,8,0) -> 26 | I99: =VLOOKUP(A99,Metrik!$C$2:$Y$959,9,0) -> 2.5 | J99: =VLOOKUP(A99,Metrik!$C$2:$Y$959,10,0) -> 9.7 | K99: =VLOOKUP(A99,Metrik!$C$2:$Y$959,11,0) -> 3.9 | L99: =VLOOKUP(A99,Metrik!$C$2:$Y$959,12,0) -> 1.5 | M99: =VLOOKUP(A99,Metrik!$C$2:$Y$959,19,0) -> 67 | U99: =IFERROR(__xludf.DUMMYFUNCTION("IFERROR(GOOGLEFINANCE(A99,""closeyest""),"""")"),3060.0) -> 3060 | V99: =IFERROR(__xludf.DUMMYFUNCTION("IFERROR(GOOGLEFINANCE(A99,""changepct""),"""")"),12.75) -> 12.75 | W99: =IFERROR(__xludf.DUMMYFUNCTION("IFERROR(GOOGLEFINANCE(A99,""priceopen""),"""")"),3150.0) -> 3150 | X99: =IFERROR(__xludf.DUMMYFUNCTION("IFERROR(GOOGLEFINANCE(A99,""high""),"""")"),3540.0) -> 3540 | Y99: =IFERROR(__xludf.DUMMYFUNCTION("IFERROR(GOOGLEFINANCE(A99,""low""),"""")"),3110.0) -> 3110 | Z99: =IFERROR(__xludf.DUMMYFUNCTION("IFERROR(GOOGLEFINANCE(A99,""volume""),"""")"),1.703576E8) -> 170357600 | AA99: =VLOOKUP(A99,Metrik!$C$2:$Y$959,5,0) -> Metals & Minerals | AB99: =VLOOKUP(A99,Metrik!$C$2:$Y$959,3,0) -> Basic Materials
A100: AMMS | B100: {=VLOOKUP(A100,{Metrik!$C$2:$C$998,Metrik!$B$2:$B$998},2,0)} -> Agung Menjangan Mas Tbk. | C100: =IFERROR(__xludf.DUMMYFUNCTION("GOOGLEFINANCE(""IDX:""&A100,""price"")"),328.0) -> 328 | D100: =IFERROR(__xludf.DUMMYFUNCTION("IF(A100="""","""", SPARKLINE( INDEX( GOOGLEFINANCE(""IDX:""&A100,""close"",TODAY()-365,TODAY()), ,2 ), {""linewidth"",1} )) "),"#N/A") -> #N/A | G100: =COUNTIFS($B$2:$B$1937,B100,$E$2:$E$1937,"<>") -> 0 | H100: =VLOOKUP(A100,Metrik!$C$2:$Y$959,8,0) -> -1020 | I100: =VLOOKUP(A100,Metrik!$C$2:$Y$959,9,0) -> 6.5 | J100: =VLOOKUP(A100,Metrik!$C$2:$Y$959,10,0) -> -0.63 | K100: =VLOOKUP(A100,Metrik!$C$2:$Y$959,11,0) -> -0.63 | L100: =VLOOKUP(A100,Metrik!$C$2:$Y$959,12,0) -> 0.01 | M100: =VLOOKUP(A100,Metrik!$C$2:$Y$959,19,0) -> -2.9 | U100: =IFERROR(__xludf.DUMMYFUNCTION("IFERROR(GOOGLEFINANCE(A100,""closeyest""),"""")"),320.0) -> 320 | V100: =IFERROR(__xludf.DUMMYFUNCTION("IFERROR(GOOGLEFINANCE(A100,""changepct""),"""")"),2.5) -> 2.5 | W100: =IFERROR(__xludf.DUMMYFUNCTION("IFERROR(GOOGLEFINANCE(A100,""priceopen""),"""")"),320.0) -> 320 | X100: =IFERROR(__xludf.DUMMYFUNCTION("IFERROR(GOOGLEFINANCE(A100,""high""),"""")"),352.0) -> 352 | Y100: =IFERROR(__xludf.DUMMYFUNCTION("IFERROR(GOOGLEFINANCE(A100,""low""),"""")"),320.0) -> 320 | Z100: =IFERROR(__xludf.DUMMYFUNCTION("IFERROR(GOOGLEFINANCE(A100,""volume""),"""")"),504900.0) -> 504900 | AA100: =VLOOKUP(A100,Metrik!$C$2:$Y$959,5,0) -> Agricultural Products | AB100: =VLOOKUP(A100,Metrik!$C$2:$Y$959,3,0) -> Consumer Non-Cyclicals
...

Sheet NonBank
A1: Kode | B1: Nama Perusahaan | C1: Penutupan | D1: =IFERROR(__xludf.DUMMYFUNCTION("""Last Update: "" & TEXT(NOW() - GOOGLEFINANCE(""IDX:BBCA"",""datadelay"")/1440, ""dddd, yyyymmdd HH:mm"")"),"Last Update: Minggu, 20260614 14:19") -> Last Update: Minggu, 20260614 14:19 | E1: Index | F1: Index Expired | G1: ∑i ≥ 7 | H1: PER ≤ 15 | I1: PBV ≤ 3 | J1: ROE ≥ 12% | K1: ROA ≥ 7% | L1: DER ≤ 1.5 | M1: NPM ≥ 7% | N1: NIM ≥ 5% | O1: CAR ≥ 16% | P1: LDR 85-92% | Q1: NPL ≤ 2% | R1: BOPO ≤ 75% | S1: CIR ≤ 50% | T1: LAR ≤ 8% | U1: Sebelumnya | V1: %Change | W1: Open | X1: High | Y1: Low | Z1: Volume | AA1: Industry | AB1: Sektor
A2: =Ringkasan!A5 -> AADI | B2: =Ringkasan!B5 -> Adaro Andalan Indonesia Tbk. | C2: =Ringkasan!C5 -> 8650 | D2: =Ringkasan!D5 -> #N/A | E2: =Ringkasan!E5 -> Kompas100 | F2: =Ringkasan!F5 -> 31 Juli 2026 | G2: =Ringkasan!G5 -> 9 | H2: =Ringkasan!H5 -> 5.5 | ... AB2: =Ringkasan!AB5 -> Energy
A3: =Ringkasan!A2 -> AADI | B3: =Ringkasan!B2 -> Adaro Andalan Indonesia Tbk. | C3: =Ringkasan!C2 -> 8650 | D3: =Ringkasan!D2 -> #N/A | E3: =Ringkasan!E2 -> IDX80 | F3: =Ringkasan!F2 -> 31 Juli 2026 | G3: =Ringkasan!G2 -> 9 | H3: =Ringkasan!H2 -> 5.5 | ... AB3: =Ringkasan!AB2 -> Energy
A4: =Ringkasan!A3 -> AADI | B4: =Ringkasan!B3 -> Adaro Andalan Indonesia Tbk. | C4: =Ringkasan!C3 -> 8650 | D4: =Ringkasan!D3 -> #N/A | E4: =Ringkasan!E3 -> IDX30 | F4: =Ringkasan!F3 -> 31 Juli 2026 | G4: =Ringkasan!G3 -> 9 | H4: =Ringkasan!H3 -> 5.5 | ... AB4: =Ringkasan!AB3 -> Energy
A5: =Ringkasan!A4 -> AADI | B5: =Ringkasan!B4 -> Adaro Andalan Indonesia Tbk. | C5: =Ringkasan!C4 -> 8650 | D5: =Ringkasan!D4 -> #N/A | E5: =Ringkasan!E4 -> LQ45 | F5: =Ringkasan!F4 -> 31 Juli 2026 | G5: =Ringkasan!G4 -> 9 | H5: =Ringkasan!H4 -> 5.5 | ... AB5: =Ringkasan!AB4 -> Energy
A6: =Ringkasan!A6 -> AADI | B6: =Ringkasan!B6 -> Adaro Andalan Indonesia Tbk. | C6: =Ringkasan!C6 -> 8650 | D6: =Ringkasan!D6 -> #N/A | E6: =Ringkasan!E6 -> IDXV30 | F6: =Ringkasan!F6 -> 4 Agustus 2026 | G6: =Ringkasan!G6 -> 9 | H6: =Ringkasan!H6 -> 5.5 | ... AB6: =Ringkasan!AB6 -> Energy
A7: =Ringkasan!A7 -> AADI | B7: =Ringkasan!B7 -> Adaro Andalan Indonesia Tbk. | C7: =Ringkasan!C7 -> 8650 | D7: =Ringkasan!D7 -> #N/A | E7: =Ringkasan!E7 -> MSCI Small Cap | F7: =Ringkasan!F7 -> 12 Agustus 2026 | G7: =Ringkasan!G7 -> 9 | H7: =Ringkasan!H7 -> 5.5 | ... AB7: =Ringkasan!AB7 -> Energy
A8: =Ringkasan!A8 -> AADI | B8: =Ringkasan!B8 -> Adaro Andalan Indonesia Tbk. | C8: =Ringkasan!C8 -> 8650 | D8: =Ringkasan!D8 -> #N/A | E8: =Ringkasan!E8 -> FTSE Small Cap | F8: =Ringkasan!F8 -> 12 Agustus 2026 | G8: =Ringkasan!G8 -> 9 | H8: =Ringkasan!H8 -> 5.5 | ... AB8: =Ringkasan!AB8 -> Energy
A9: =Ringkasan!A9 -> AADI | B9: =Ringkasan!B9 -> Adaro Andalan Indonesia Tbk. | C9: =Ringkasan!C9 -> 8650 | D9: =Ringkasan!D9 -> #N/A | E9: =Ringkasan!E9 -> JII30 | F9: =Ringkasan!F9 -> 46356 | G9: =Ringkasan!G9 -> 9 | H9: =Ringkasan!H9 -> 5.5 | ... AB9: =Ringkasan!AB9 -> Energy
A10: =Ringkasan!A10 -> AADI | B10: =Ringkasan!B10 -> Adaro Andalan Indonesia Tbk. | C10: =Ringkasan!C10 -> 8650 | D10: =Ringkasan!D10 -> #N/A | E10: =Ringkasan!E10 -> JII70 | F10: =Ringkasan!F10 -> 46356 | G10: =Ringkasan!G10 -> 9 | H10: =Ringkasan!H10 -> 5.5 | ... AB10: =Ringkasan!AB10 -> Energy
A11: =#REF! -> #REF! | B11: =#REF! -> #REF! | C11: =#REF! -> #REF! | D11: =#REF! -> #REF! | E11: =#REF! -> #REF! | F11: =#REF! -> #REF! | G11: =#REF! -> #REF! | H11: =#REF! -> #REF! | ... AB11: =#REF! -> #REF!
A12: =Ringkasan!A11 -> AALI | B12: =Ringkasan!B11 -> Astra Agro Lestari Tbk | C12: =Ringkasan!C11 -> 6175 | D12: =Ringkasan!D11 -> #N/A | E12: =Ringkasan!E11 -> IDXSMC-LIQ | F12: =Ringkasan!F11 -> 4 Agustus 2026 | G12: =Ringkasan!G11 -> 2 | H12: =Ringkasan!H11 -> 8 | ... AB12: =Ringkasan!AB11 -> Consumer Non-Cyclicals
A13: =Ringkasan!A12 -> AALI | B13: =Ringkasan!B12 -> Astra Agro Lestari Tbk | C13: =Ringkasan!C12 -> 6175 | D13: =Ringkasan!D12 -> #N/A | E13: =Ringkasan!E12 -> Investor33 | F13: =Ringkasan!F12 -> 46356 | G13: =Ringkasan!G12 -> 2 | H13: =Ringkasan!H12 -> 8 | ... AB13: =Ringkasan!AB12 -> Consumer Non-Cyclicals
A14: =Ringkasan!A230 -> BBCA | B14: =Ringkasan!B230 -> Bank Central Asia Tbk. | C14: =Ringkasan!C230 -> #N/A | D14: =Ringkasan!D230 -> #N/A | E14: =Ringkasan!E230 -> MNC36 | F14: =Ringkasan!F230 -> 30 Oktober 2026 | G14: =Ringkasan!G230 -> 21 | H14: =Ringkasan!H230 -> 12.1 | ... AB14: =Ringkasan!AB230 -> Financials
A15: =Ringkasan!A653 -> ELTY | B15: =Ringkasan!B653 -> Bakrieland Development Tbk. | C15: =Ringkasan!C653 -> 26 | D15: =Ringkasan!D653 -> #N/A | E15: =Ringkasan!E653 | F15: =Ringkasan!F653 | G15: =Ringkasan!G653 -> 0 | H15: =Ringkasan!H653 -> 220 | ... AB15: =Ringkasan!AB653 -> Properties & Real Estate
A16: =Ringkasan!A15 -> ABMM | B16: =Ringkasan!B15 -> ABM Investama Tbk | C16: =Ringkasan!C15 -> 2420 | D16: =Ringkasan!D15 -> #N/A | E16: =Ringkasan!E15 | F16: =Ringkasan!F15 | G16: =Ringkasan!G15 -> 0 | H16: =Ringkasan!H15 -> 6.2 | ... AB16: =Ringkasan!AB15 -> Industrials
A17: =Ringkasan!A16 -> ACES | B17: =Ringkasan!B16 -> Aspirasi Hidup Indonesia Tbk. | C17: =Ringkasan!C16 -> 356 | D17: =Ringkasan!D16 -> #N/A | E17: =Ringkasan!E16 -> ESGQKEHATI | F17: =Ringkasan!F16 -> 46356 | G17: =Ringkasan!G16 -> 11 | H17: =Ringkasan!H16 -> 8.6 | ... AB17: =Ringkasan!AB16 -> Consumer Cyclicals
A18: =Ringkasan!A17 -> ACES | B18: =Ringkasan!B17 -> Aspirasi Hidup Indonesia Tbk. | C18: =Ringkasan!C17 -> 356 | D18: =Ringkasan!D17 -> #N/A | E18: =Ringkasan!E17 -> IDXHIDIV20 | F18: =Ringkasan!F17 -> 2 Februari 2027 | G18: =Ringkasan!G17 -> 11 | H18: =Ringkasan!H17 -> 8.6 | ... AB18: =Ringkasan!AB17 -> Consumer Cyclicals
A19: =Ringkasan!A18 -> ACES | B19: =Ringkasan!B18 -> Aspirasi Hidup Indonesia Tbk. | C19: =Ringkasan!C18 -> 356 | D19: =Ringkasan!D18 -> #N/A | E19: =Ringkasan!E18 -> IDX80 | F19: =Ringkasan!F18 -> 31 Juli 2026 | G19: =Ringkasan!G18 -> 11 | H19: =Ringkasan!H18 -> 8.6 | ... AB19: =Ringkasan!AB18 -> Consumer Cyclicals
A20: =Ringkasan!A683 -> ERAA | B20: =Ringkasan!B683 -> Erajaya Swasembada Tbk. | C20: =Ringkasan!C683 -> 364 | D20: =Ringkasan!D683 -> #N/A | E20: =Ringkasan!E683 -> IDXSHAGROW | F20: =Ringkasan!F683 -> 46356 | G20: =Ringkasan!G683 -> 10 | H20: =Ringkasan!H683 -> 4.1 | ... AB20: =Ringkasan!AB683 -> Consumer Cyclicals
A21: =Ringkasan!A20 -> ACES | B21: =Ringkasan!B20 -> Aspirasi Hidup Indonesia Tbk. | C21: =Ringkasan!C20 -> 356 | D21: =Ringkasan!D20 -> #N/A | E21: =Ringkasan!E20 -> ECONOMIC30 | F21: =Ringkasan!F20 -> 31 Agustus 2026 | G21: =Ringkasan!G20 -> 11 | H21: =Ringkasan!H20 -> 8.6 | ... AB21: =Ringkasan!AB20 -> Consumer Cyclicals
A22: =Ringkasan!A21 -> ACES | B22: =Ringkasan!B21 -> Aspirasi Hidup Indonesia Tbk. | C22: =Ringkasan!C21 -> 356 | D22: =Ringkasan!D21 -> #N/A | E22: =Ringkasan!E21 -> Kompas100 | F22: =Ringkasan!F21 -> 31 Juli 2026 | G22: =Ringkasan!G21 -> 11 | H22: =Ringkasan!H21 -> 8.6 | ... AB22: =Ringkasan!AB21 -> Consumer Cyclicals
A23: =Ringkasan!A22 -> ACES | B23: =Ringkasan!B22 -> Aspirasi Hidup Indonesia Tbk. | C23: =Ringkasan!C22 -> 356 | D23: =Ringkasan!D22 -> #N/A | E23: =Ringkasan!E22 -> IDXQ30 | F23: =Ringkasan!F22 -> 4 Agustus 2026 | G23: =Ringkasan!G22 -> 11 | H23: =Ringkasan!H22 -> 8.6 | ... AB23: =Ringkasan!AB22 -> Consumer Cyclicals
A24: =Ringkasan!A23 -> ACES | B24: =Ringkasan!B23 -> Aspirasi Hidup Indonesia Tbk. | C24: =Ringkasan!C23 -> 356 | D24: =Ringkasan!D23 -> #N/A | E24: =Ringkasan!E23 -> IDXSMC-LIQ | F24: =Ringkasan!F23 -> 4 Agustus 2026 | G24: =Ringkasan!G23 -> 11 | H24: =Ringkasan!H23 -> 8.6 | ... AB24: =Ringkasan!AB23 -> Consumer Cyclicals
A25: =Ringkasan!A24 -> ACES | B25: =Ringkasan!B24 -> Aspirasi Hidup Indonesia Tbk. | C25: =Ringkasan!C24 -> 356 | D25: =Ringkasan!D24 -> #N/A | E25: =Ringkasan!E24 -> IDXV30 | F25: =Ringkasan!F24 -> 4 Agustus 2026 | G25: =Ringkasan!G24 -> 11 | H25: =Ringkasan!H24 -> 8.6 | ... AB25: =Ringkasan!AB24 -> Consumer Cyclicals
A26: =Ringkasan!A25 -> ACES | B26: =Ringkasan!B25 -> Aspirasi Hidup Indonesia Tbk. | C26: =Ringkasan!C25 -> 356 | D26: =Ringkasan!D25 -> #N/A | E26: =Ringkasan!E25 -> ESGSKEHATI | F26: =Ringkasan!F25 -> 46356 | G26: =Ringkasan!G25 -> 11 | H26: =Ringkasan!H25 -> 8.6 | ... AB26: =Ringkasan!AB25 -> Consumer Cyclicals
A27: =Ringkasan!A26 -> ACES | B27: =Ringkasan!B26 -> Aspirasi Hidup Indonesia Tbk. | C27: =Ringkasan!C26 -> 356 | D27: =Ringkasan!D26 -> #N/A | E27: =Ringkasan!E26 -> JII70 | F27: =Ringkasan!F26 -> 46356 | G27: =Ringkasan!G26 -> 11 | H27: =Ringkasan!H26 -> 8.6 | ... AB27: =Ringkasan!AB26 -> Consumer Cyclicals
A28: =Ringkasan!A753 -> GLOB | B28: =Ringkasan!B753 -> Globe Kita Terang Tbk. | C28: =Ringkasan!C753 -> 155 | D28: =Ringkasan!D753 -> #N/A | E28: =Ringkasan!E753 | F28: =Ringkasan!F753 | G28: =Ringkasan!G753 -> 0 | H28: =Ringkasan!H753 -> -1.6 | ... AB28: =Ringkasan!AB753 -> Consumer Cyclicals
A29: =Ringkasan!A853 -> IKAN | B29: =Ringkasan!B853 -> Era Mandiri Cemerlang Tbk. | C29: =Ringkasan!C853 -> 72 | D29: =Ringkasan!D853 -> #N/A | E29: =Ringkasan!E853 | F29: =Ringkasan!F853 | G29: =Ringkasan!G853 -> 0 | H29: =Ringkasan!H853 -> -170 | ... AB29: =Ringkasan!AB853 -> Consumer Non-Cyclicals
A30: =Ringkasan!A29 -> ADCP | B30: =Ringkasan!B29 -> Adhi Commuter Properti Tbk. | C30: =Ringkasan!C29 -> 50 | D30: =Ringkasan!D29 -> #N/A | E30: =Ringkasan!E29 | F30: =Ringkasan!F29 | G30: =Ringkasan!G29 -> 0 | H30: =Ringkasan!H29 -> -0.52 | ... AB30: =Ringkasan!AB29 -> Properties & Real Estate
A31: =Ringkasan!A30 -> ADES | B31: =Ringkasan!B30 -> Akasha Wira International Tbk. | C31: =Ringkasan!C30 -> 22000 | D31: =Ringkasan!D30 -> #N/A | E31: =Ringkasan!E30 | F31: =Ringkasan!F30 | G31: =Ringkasan!G30 -> 0 | H31: =Ringkasan!H30 -> 14.6 | ... AB31: =Ringkasan!AB30 -> Consumer Non-Cyclicals
A32: =Ringkasan!A1801 -> UNTR | B32: =Ringkasan!B1801 -> United Tractors Tbk. | C32: =Ringkasan!C1801 -> 22500 | D32: =Ringkasan!D1801 -> #N/A | E32: =Ringkasan!E1801 -> IDXVESTA28 | F32: =Ringkasan!F1801 -> 31 Agustus 2026 | G32: =Ringkasan!G1801 -> 20 | H32: =Ringkasan!H1801 -> 7 | ... AB32: =Ringkasan!AB1801 -> Industrials
A33: =Ringkasan!A32 -> ADMF | B33: =Ringkasan!B32 -> Adira Dinamika Multi Finance Tbk. | C33: =Ringkasan!C32 -> 8200 | D33: =Ringkasan!D32 -> #N/A | E33: =Ringkasan!E32 | F33: =Ringkasan!F32 | G33: =Ringkasan!G32 -> 0 | H33: =Ringkasan!H32 -> 5.9 | ... AB33: =Ringkasan!AB32 -> Financials
A34: =Ringkasan!A33 -> ADMG | B34: =Ringkasan!B33 -> Polychem Indonesia Tbk | C34: =Ringkasan!C33 -> 200 | D34: =Ringkasan!D33 -> #N/A | E34: =Ringkasan!E33 | F34: =Ringkasan!F33 | G34: =Ringkasan!G33 -> 0 | H34: =Ringkasan!H33 -> -250 | ... AB34: =Ringkasan!AB33 -> Basic Materials
A35: =Ringkasan!A34 -> ADMR | B35: =Ringkasan!B34 -> Alamtri Minerals Indonesia Tbk. | C35: =Ringkasan!C34 -> 1575 | D35: =Ringkasan!D34 -> #N/A | E35: =Ringkasan!E34 -> IDXQ30 | F35: =Ringkasan!F34 -> 4 Agustus 2026 | G35: =Ringkasan!G34 -> 9 | H35: =Ringkasan!H34 -> 12.6 | ... AB35: =Ringkasan!AB34 -> Energy
A36: =Ringkasan!A35 -> ADMR | B36: =Ringkasan!B35 -> Alamtri Minerals Indonesia Tbk. | C36: =Ringkasan!C35 -> 1575 | D36: =Ringkasan!D35 -> #N/A | E36: =Ringkasan!E35 -> Kompas100 | F36: =Ringkasan!F35 -> 31 Juli 2026 | G36: =Ringkasan!G35 -> 9 | H36: =Ringkasan!H35 -> 12.6 | ... AB36: =Ringkasan!AB35 -> Energy
A37: =Ringkasan!A36 -> ADMR | B37: =Ringkasan!B36 -> Alamtri Minerals Indonesia Tbk. | C37: =Ringkasan!C36 -> 1575 | D37: =Ringkasan!D36 -> #N/A | E37: =Ringkasan!E36 -> LQ45 | F37: =Ringkasan!F36 -> 31 Juli 2026 | G37: =Ringkasan!G36 -> 9 | H37: =Ringkasan!H36 -> 12.6 | ... AB37: =Ringkasan!AB36 -> Energy
A38: =Ringkasan!A37 -> ADMR | B38: =Ringkasan!B37 -> Alamtri Minerals Indonesia Tbk. | C38: =Ringkasan!C37 -> 1575 | D38: =Ringkasan!D37 -> #N/A | E38: =Ringkasan!E37 -> IDX80 | F38: =Ringkasan!F37 -> 31 Juli 2026 | G38: =Ringkasan!G37 -> 9 | H38: =Ringkasan!H37 -> 12.6 | ... AB38: =Ringkasan!AB37 -> Energy
A39: =Ringkasan!A38 -> ADMR | B39: =Ringkasan!B38 -> Alamtri Minerals Indonesia Tbk. | C39: =Ringkasan!C38 -> 1575 | D39: =Ringkasan!D38 -> #N/A | E39: =Ringkasan!E38 -> IDX30 | F39: =Ringkasan!F38 -> 31 Juli 2026 | G39: =Ringkasan!G38 -> 9 | H39: =Ringkasan!H38 -> 12.6 | ... AB39: =Ringkasan!AB38 -> Energy
A40: =Ringkasan!A39 -> ADMR | B40: =Ringkasan!B39 -> Alamtri Minerals Indonesia Tbk. | C40: =Ringkasan!C39 -> 1575 | D40: =Ringkasan!D39 -> #N/A | E40: =Ringkasan!E39 -> IDXSHAGROW | F40: =Ringkasan!F39 -> 46356 | G40: =Ringkasan!G39 -> 9 | H40: =Ringkasan!H39 -> 12.6 | ... AB40: =Ringkasan!AB39 -> Energy
A41: =Ringkasan!A40 -> ADMR | B41: =Ringkasan!B40 -> Alamtri Minerals Indonesia Tbk. | C41: =Ringkasan!C40 -> 1575 | D41: =Ringkasan!D40 -> #N/A | E41: =Ringkasan!E40 -> Investor33 | F41: =Ringkasan!F40 -> 46356 | G41: =Ringkasan!G40 -> 9 | H41: =Ringkasan!H40 -> 12.6 | ... AB41: =Ringkasan!AB40 -> Energy
A42: =Ringkasan!A41 -> ADMR | B42: =Ringkasan!B41 -> Alamtri Minerals Indonesia Tbk. | C42: =Ringkasan!C41 -> 1575 | D42: =Ringkasan!D41 -> #N/A | E42: =Ringkasan!E41 -> JII30 | F42: =Ringkasan!F41 -> 46356 | G42: =Ringkasan!G41 -> 9 | H42: =Ringkasan!H41 -> 12.6 | ... AB42: =Ringkasan!AB41 -> Energy
A43: =Ringkasan!A42 -> ADMR | B43: =Ringkasan!B42 -> Alamtri Minerals Indonesia Tbk. | C43: =Ringkasan!C42 -> 1575 | D43: =Ringkasan!D42 -> #N/A | E43: =Ringkasan!E42 -> JII70 | F43: =Ringkasan!F42 -> 46356 | G43: =Ringkasan!G42 -> 9 | H43: =Ringkasan!H42 -> 12.6 | ... AB43: =Ringkasan!AB42 -> Energy
A44: =Ringkasan!A43 -> ADRO | B44: =Ringkasan!B43 -> Alamtri Resources Indonesia Tbk. | C44: =Ringkasan!C43 -> 2280 | D44: =Ringkasan!D43 -> #N/A | E44: =Ringkasan!E43 -> BISNIS-27 | F44: =Ringkasan!F43 -> 30 Oktober 2026 | G44: =Ringkasan!G43 -> 14 | H44: =Ringkasan!H43 -> 8 | ... AB44: =Ringkasan!AB43 -> Energy
... A47: =Ringkasan!A46 -> ADRO | B47: =Ringkasan!B46 -> Alamtri Resources Indonesia Tbk. | C47: =Ringkasan!C46 -> 2280 | D47: =Ringkasan!D46 -> #N/A | E47: =Ringkasan!E46 -> IDXG30 | F47: =Ringkasan!F46 -> 4 Agustus 2026 | G47: =Ringkasan!G46 -> 14 | H47: =Ringkasan!H46 -> 8 | ... AB47: =Ringkasan!AB46 -> Energy
A48: =Ringkasan!A31 -> ADHI | B48: =Ringkasan!B31 -> PT Adhi Karya (Persero) Tbk. | C48: =Ringkasan!C31 -> 158 | D48: =Ringkasan!D31 -> #N/A | E48: =Ringkasan!E31 -> IDXBUMN20 | F48: =Ringkasan!F31 -> 4 Agustus 2026 | G48: =Ringkasan!G31 -> 1 | H48: =Ringkasan!H31 -> -0.27 | ... AB48: =Ringkasan!AB31 -> Infrastructures
A49: =Ringkasan!A48 -> ADRO | B49: =Ringkasan!B48 -> Alamtri Resources Indonesia Tbk. | C49: =Ringkasan!C48 -> 2280 | D49: =Ringkasan!D48 -> #N/A | E49: =Ringkasan!E48 -> Kompas100 | F49: =Ringkasan!F48 -> 31 Juli 2026 | G49: =Ringkasan!G48 -> 14 | H49: =Ringkasan!H48 -> 8 | ... AB49: =Ringkasan!AB48 -> Energy
A50: =Ringkasan!A49 -> ADRO | B50: =Ringkasan!B49 -> Alamtri Resources Indonesia Tbk. | C50: =Ringkasan!C49 -> 2280 | D50: =Ringkasan!D49 -> #N/A | E50: =Ringkasan!E49 -> LQ45 | F50: =Ringkasan!F49 -> 31 Juli 2026 | G50: =Ringkasan!G49 -> 14 | H50: =Ringkasan!H49 -> 8 | ... AB50: =Ringkasan!AB49 -> Energy
A51: =Ringkasan!A50 -> ADRO | B51: =Ringkasan!B50 -> Alamtri Resources Indonesia Tbk. | C51: =Ringkasan!C50 -> 2280 | D51: =Ringkasan!D50 -> #N/A | E51: =Ringkasan!E50 -> IDXV30 | F51: =Ringkasan!F50 -> 4 Agustus 2026 | G51: =Ringkasan!G50 -> 14 | H51: =Ringkasan!H50 -> 8 | ... AB51: =Ringkasan!AB50 -> Energy
A52: =Ringkasan!A51 -> ADRO | B52: =Ringkasan!B51 -> Alamtri Resources Indonesia Tbk. | C52: =Ringkasan!C51 -> 2280 | D52: =Ringkasan!D51 -> #N/A | E52: =Ringkasan!E51 -> FTSE Large Cap | F52: =Ringkasan!F51 -> Juni 2026 | G52: =Ringkasan!G51 -> 14 | H52: =Ringkasan!H51 -> 8 | ... AB52: =Ringkasan!AB51 -> Energy
A53: =Ringkasan!A52 -> ADRO | B53: =Ringkasan!B52 -> Alamtri Resources Indonesia Tbk. | C53: =Ringkasan!C52 -> 2280 | D53: =Ringkasan!D52 -> #N/A | E53: =Ringkasan!E52 -> MSCI Small Cap | F53: =Ringkasan!F52 -> 12 Agustus 2026 | G53: =Ringkasan!G52 -> 14 | H53: =Ringkasan!H52 -> 8 | ... AB53: =Ringkasan!AB52 -> Energy
A54: =Ringkasan!A53 -> ADRO | B54: =Ringkasan!B53 -> Alamtri Resources Indonesia Tbk. | C54: =Ringkasan!C53 -> 2280 | D54: =Ringkasan!D53 -> #N/A | E54: =Ringkasan!E53 -> IDXSHAGROW | F54: =Ringkasan!F53 -> 46356 | G54: =Ringkasan!G53 -> 14 | H54: =Ringkasan!H53 -> 8 | ... AB54: =Ringkasan!AB53 -> Energy
A55: =Ringkasan!A54 -> ADRO | B55: =Ringkasan!B54 -> Alamtri Resources Indonesia Tbk. | C55: =Ringkasan!C54 -> 2280 | D55: =Ringkasan!D54 -> #N/A | E55: =Ringkasan!E54 -> Investor33 | F55: =Ringkasan!F54 -> 46356 | G55: =Ringkasan!G54 -> 14 | H55: =Ringkasan!H54 -> 8 | ... AB55: =Ringkasan!AB54 -> Energy
A56: =Ringkasan!A55 -> ADRO | B56: =Ringkasan!B55 -> Alamtri Resources Indonesia Tbk. | C56: =Ringkasan!C55 -> 2280 | D56: =Ringkasan!D55 -> #N/A | E56: =Ringkasan!E55 -> JII30 | F56: =Ringkasan!F55 -> 46356 | G56: =Ringkasan!G55 -> 14 | H56: =Ringkasan!H55 -> 8 | ... AB56: =Ringkasan!AB55 -> Energy
A57: =Ringkasan!A56 -> ADRO | B57: =Ringkasan!B56 -> Alamtri Resources Indonesia Tbk. | C57: =Ringkasan!C56 -> 2280 | D57: =Ringkasan!D56 -> #N/A | E57: =Ringkasan!E56 -> JII70 | F57: =Ringkasan!F56 -> 46356 | G57: =Ringkasan!G56 -> 14 | H57: =Ringkasan!H56 -> 8 | ... AB57: =Ringkasan!AB56 -> Energy
A58: =Ringkasan!A61 -> AGRO | B58: =Ringkasan!B61 -> PT Bank Rakyat Indonesia Agroniaga Tbk | C58: =Ringkasan!C61 -> 151 | D58: =Ringkasan!D61 -> #N/A | E58: =Ringkasan!E61 -> Infobank15 | F58: =Ringkasan!F61 -> 30 Juni 2026 | G58: =Ringkasan!G61 -> 2 | H58: =Ringkasan!H61 -> -8 | ... AB58: =Ringkasan!AB61 -> Financials
A59: =Ringkasan!A58 -> AGAR | B59: =Ringkasan!B58 -> Asia Sejahtera Mina Tbk. | C59: =Ringkasan!C58 -> 216 | D59: =Ringkasan!D58 -> #N/A | E59: =Ringkasan!E58 | F59: =Ringkasan!F58 | G59: =Ringkasan!G58 -> 0 | H59: =Ringkasan!H58 -> 48.2 | ... AB59: =Ringkasan!AB58 -> Consumer Non-Cyclicals
A60: =Ringkasan!A59 -> AGII | B60: =Ringkasan!B59 -> Samator Indo Gas Tbk. | C60: =Ringkasan!C59 -> 2680 | D60: =Ringkasan!D59 -> #N/A | E60: =Ringkasan!E59 | F60: =Ringkasan!F59 | G60: =Ringkasan!G59 -> 0 | H60: =Ringkasan!H59 -> 97.9 | ... AB60: =Ringkasan!AB59 -> Basic Materials
A61: =Ringkasan!A60 -> AGRO | B61: =Ringkasan!B60 -> PT Bank Rakyat Indonesia Agroniaga Tbk | C61: =Ringkasan!C60 -> 151 | D61: =Ringkasan!D60 -> #N/A | E61: =Ringkasan!E60 -> IDXBUMN20 | F61: =Ringkasan!F60 -> 4 Agustus 2026 | G61: =Ringkasan!G60 -> 2 | H61: =Ringkasan!H60 -> -8 | ... AB61: =Ringkasan!AB60 -> Financials
A62: =Ringkasan!A106 -> AMRT | B62: =Ringkasan!B106 -> Sumber Alfaria Trijaya Tbk. | C62: =Ringkasan!C106 -> 1375 | D62: =Ringkasan!D106 -> #N/A | E62: =Ringkasan!E106 -> IDX30 | F62: =Ringkasan!F106 -> 31 Juli 2026 | G62: =Ringkasan!G106 -> 10 | H62: =Ringkasan!H106 -> 13.6 | ... AB62: =Ringkasan!AB106 -> Consumer Non-Cyclicals
A63: =Ringkasan!A62 -> AGRS | B63: =Ringkasan!B62 -> PT Bank IBK Indonesia Tbk. | C63: =Ringkasan!C62 -> 62 | D63: =Ringkasan!D62 -> #N/A | E63: =Ringkasan!E62 | F63: =Ringkasan!F62 | G63: =Ringkasan!G62 -> 0 | H63: =Ringkasan!H62 -> 17.3 | ... AB63: =Ringkasan!AB62 -> Financials
A64: =Ringkasan!A63 -> AHAP | B64: =Ringkasan!B63 -> Asuransi Harta Aman Pratama Tbk. | C64: =Ringkasan!C63 -> 82 | D64: =Ringkasan!D63 -> #N/A | E64: =Ringkasan!E63 | F64: =Ringkasan!F63 | G64: =Ringkasan!G63 -> 0 | H64: =Ringkasan!H63 -> -18 | ... AB64: =Ringkasan!AB63 -> Financials
A65: =Ringkasan!A64 -> AIMS | B65: =Ringkasan!B64 -> Artha Mahiya Investama Tbk. | C65: =Ringkasan!C64 -> 390 | D65: =Ringkasan!D64 -> #N/A | E65: =Ringkasan!E64 | F65: =Ringkasan!F64 | G65: =Ringkasan!G64 -> 0 | H65: =Ringkasan!H64 -> -110 | ... AB65: =Ringkasan!AB64 -> Energy
A66: =Ringkasan!A101 -> AMOR | B66: =Ringkasan!B101 -> Ashmore Asset Management Indonesia Tbk. | C66: =Ringkasan!C101 -> 312 | D66: =Ringkasan!D101 -> #N/A | E66: =Ringkasan!E101 | F66: =Ringkasan!F101 | G66: =Ringkasan!G101 -> 0 | H66: =Ringkasan!H101 -> 11.1 | ... AB66: =Ringkasan!AB101 -> Financials
A67: =Ringkasan!A103 -> AMRT | B67: =Ringkasan!B103 -> Sumber Alfaria Trijaya Tbk. | C67: =Ringkasan!C103 -> 1375 | D67: =Ringkasan!D103 -> #N/A | E67: =Ringkasan!E103 -> IDX80 | F67: =Ringkasan!F103 -> 31 Juli 2026 | G67: =Ringkasan!G103 -> 10 | H67: =Ringkasan!H103 -> 13.6 | ... AB67: =Ringkasan!AB103 -> Consumer Non-Cyclicals
A68: =Ringkasan!A67 -> AKPI | B68: =Ringkasan!B67 -> Argha Karya Prima Industry Tbk. | C68: =Ringkasan!C67 -> #N/A | D68: =Ringkasan!D67 -> #N/A | E68: =Ringkasan!E67 | F68: =Ringkasan!F67 | G68: =Ringkasan!G67 -> 0 | H68: =Ringkasan!H67 -> 10.1 | ... AB68: =Ringkasan!AB67 -> Basic Materials
A69: =Ringkasan!A68 -> AKRA | B69: =Ringkasan!B68 -> AKR Corporindo Tbk. | C69: =Ringkasan!C68 -> 1250 | D69: =Ringkasan!D68 -> #N/A | E69: =Ringkasan!E68 -> ESGQKEHATI | F69: =Ringkasan!F68 -> 46356 | G69: =Ringkasan!G68 -> 16 | H69: =Ringkasan!H68 -> 9.7 | ... AB69: =Ringkasan!AB68 -> Energy
A70: =Ringkasan!A69 -> AKRA | B70: =Ringkasan!B69 -> AKR Corporindo Tbk. | C70: =Ringkasan!C69 -> 1250 | D70: =Ringkasan!D69 -> #N/A | E70: =Ringkasan!E69 -> IDXHIDIV20 | F70: =Ringkasan!F69 -> 2 Februari 2027 | G70: =Ringkasan!G69 -> 16 | H70: =Ringkasan!H69 -> 9.7 | ... AB70: =Ringkasan!AB69 -> Energy
A71: =Ringkasan!A70 -> AKRA | B71: =Ringkasan!B70 -> AKR Corporindo Tbk. | C71: =Ringkasan!C70 -> 1250 | D71: =Ringkasan!D70 -> #N/A | E71: =Ringkasan!E70 -> LQ45 | F71: =Ringkasan!F70 -> 31 Juli 2026 | G71: =Ringkasan!G70 -> 16 | H71: =Ringkasan!H70 -> 9.7 | ... AB71: =Ringkasan!AB70 -> Energy
A72: =Ringkasan!A71 -> AKRA | B72: =Ringkasan!B71 -> AKR Corporindo Tbk. | C72: =Ringkasan!C71 -> 1250 | D72: =Ringkasan!D71 -> #N/A | E72: =Ringkasan!E71 -> IDX80 | F72: =Ringkasan!F71 -> 31 Juli 2026 | G72: =Ringkasan!G71 -> 16 | H72: =Ringkasan!H71 -> 9.7 | ... AB72: =Ringkasan!AB71 -> Energy
A73: =Ringkasan!A72 -> AKRA | B73: =Ringkasan!B72 -> AKR Corporindo Tbk. | C73: =Ringkasan!C72 -> 1250 | D73: =Ringkasan!D72 -> #N/A | E73: =Ringkasan!E72 -> MNC36 | F73: =Ringkasan!F72 -> 30 Oktober 2026 | G73: =Ringkasan!G72 -> 16 | H73: =Ringkasan!H72 -> 9.7 | ... AB73: =Ringkasan!AB72 -> Energy
A74: =Ringkasan!A73 -> AKRA | B74: =Ringkasan!B73 -> AKR Corporindo Tbk. | C74: =Ringkasan!C73 -> 1250 | D74: =Ringkasan!D73 -> #N/A | E74: =Ringkasan!E73 -> SMINFRA18 | F74: =Ringkasan!F73 -> 30 Oktober 2026 | G74: =Ringkasan!G73 -> 16 | H74: =Ringkasan!H73 -> 9.7 | ... AB74: =Ringkasan!AB73 -> Energy
A75: =Ringkasan!A74 -> AKRA | B75: =Ringkasan!B74 -> AKR Corporindo Tbk. | C75: =Ringkasan!C74 -> 1250 | D75: =Ringkasan!D74 -> #N/A | E75: =Ringkasan!E74 -> Kompas100 | F75: =Ringkasan!F74 -> 31 Juli 2026 | G75: =Ringkasan!G74 -> 16 | H75: =Ringkasan!H74 -> 9.7 | ... AB75: =Ringkasan!AB74 -> Energy
A76: =Ringkasan!A75 -> AKRA | B76: =Ringkasan!B75 -> AKR Corporindo Tbk. | C76: =Ringkasan!C75 -> 1250 | D76: =Ringkasan!D75 -> #N/A | E76: =Ringkasan!E75 -> IDXSMC-LIQ | F76: =Ringkasan!F75 -> 4 Agustus 2026 | G76: =Ringkasan!G75 -> 16 | H76: =Ringkasan!H75 -> 9.7 | ... AB76: =Ringkasan!AB75 -> Energy
A77: =Ringkasan!A204 -> AWAN | B77: =Ringkasan!B204 -> PT Era Digital Media Tbk | C77: =Ringkasan!C204 -> #N/A | D77: =Ringkasan!D204 -> #N/A | E77: =Ringkasan!E204 | F77: =Ringkasan!F204 | G77: =Ringkasan!G204 -> 0 | H77: =Ringkasan!H204 -> -59.7 | ... AB77: =Ringkasan!AB204 -> Technology
A78: =Ringkasan!A77 -> AKRA | B78: =Ringkasan!B77 -> AKR Corporindo Tbk. | C78: =Ringkasan!C77 -> 1250 | D78: =Ringkasan!D77 -> #N/A | E78: =Ringkasan!E77 -> IDXG30 | F78: =Ringkasan!F77 -> 4 Agustus 2026 | G78: =Ringkasan!G77 -> 16 | H78: =Ringkasan!H77 -> 9.7 | ... AB78: =Ringkasan!AB77 -> Energy
A79: =Ringkasan!A237 -> BBCA | B79: =Ringkasan!B237 -> Bank Central Asia Tbk. | C79: =Ringkasan!C237 -> #N/A | D79: =Ringkasan!D237 -> #N/A | E79: =Ringkasan!E237 -> PRIMBANK-10 | F79: =Ringkasan!F237 -> 30 Juni 2026 | G79: =Ringkasan!G237 -> 21 | H79: =Ringkasan!H237 -> 12.1 | ... AB79: =Ringkasan!AB237 -> Financials
A80: =Ringkasan!A79 -> AKRA | B80: =Ringkasan!B79 -> AKR Corporindo Tbk. | C80: =Ringkasan!C79 -> 1250 | D80: =Ringkasan!D79 -> #N/A | E80: =Ringkasan!E79 -> MSCI Small Cap | F80: =Ringkasan!F79 -> 12 Agustus 2026 | G80: =Ringkasan!G79 -> 16 | H80: =Ringkasan!H79 -> 9.7 | ... AB80: =Ringkasan!AB79 -> Energy
A81: =Ringkasan!A80 -> AKRA | B81: =Ringkasan!B80 -> AKR Corporindo Tbk. | C81: =Ringkasan!C80 -> 1250 | D81: =Ringkasan!D80 -> #N/A | E81: =Ringkasan!E80 -> ESGSKEHATI | F81: =Ringkasan!F80 -> 46356 | G81: =Ringkasan!G80 -> 16 | H81: =Ringkasan!H80 -> 9.7 | ... AB81: =Ringkasan!AB80 -> Energy
A82: =Ringkasan!A81 -> AKRA | B82: =Ringkasan!B81 -> AKR Corporindo Tbk. | C82: =Ringkasan!C81 -> 1250 | D82: =Ringkasan!D81 -> #N/A | E82: =Ringkasan!E81 -> SRI-KEHATI | F82: =Ringkasan!F81 -> 46356 | G82: =Ringkasan!G81 -> 16 | H82: =Ringkasan!H81 -> 9.7 | ... AB82: =Ringkasan!AB81 -> Energy
A83: =Ringkasan!A82 -> AKRA | B83: =Ringkasan!B82 -> AKR Corporindo Tbk. | C83: =Ringkasan!C82 -> 1250 | D83: =Ringkasan!D82 -> #N/A | E83: =Ringkasan!E82 -> Investor33 | F83: =Ringkasan!F82 -> 46356 | G83: =Ringkasan!G82 -> 16 | H83: =Ringkasan!H82 -> 9.7 | ... AB83: =Ringkasan!AB82 -> Energy
A84: =Ringkasan!A83 -> AKRA | B84: =Ringkasan!B83 -> AKR Corporindo Tbk. | C84: =Ringkasan!C83 -> 1250 | D84: =Ringkasan!D83 -> #N/A | E84: =Ringkasan!E83 -> JII70 | F84: =Ringkasan!F83 -> 46356 | G84: =Ringkasan!G83 -> 16 | H84: =Ringkasan!H83 -> 9.7 | ... AB84: =Ringkasan!AB83 -> Energy
A85: =Ringkasan!A84 -> AKSI | B85: =Ringkasan!B84 -> PT Maming Enam Sembilan Mineral Tbk. | C85: =Ringkasan!C84 -> 183 | D85: =Ringkasan!D84 -> #N/A | E85: =Ringkasan!E84 | F85: =Ringkasan!F84 | G85: =Ringkasan!G84 -> 0 | H85: =Ringkasan!H84 -> -16.7 | ... AB85: =Ringkasan!AB84 -> Transportation & Logistic
A86: =Ringkasan!A312 -> BCIP | B86: =Ringkasan!B312 -> Bumi Citra Permai Tbk. | C86: =Ringkasan!C312 -> 61 | D86: =Ringkasan!D312 -> #N/A | E86: =Ringkasan!E312 | F86: =Ringkasan!F312 | G86: =Ringkasan!G312 -> 0 | H86: =Ringkasan!H312 -> 3.5 | ... AB86: =Ringkasan!AB312 -> Properties & Real Estate
A87: =Ringkasan!A86 -> ALII | B87: =Ringkasan!B86 -> Ancara Logistics Indonesia Tbk. | C87: =Ringkasan!C86 -> 835 | D87: =Ringkasan!D86 -> #N/A | E87: =Ringkasan!E86 | F87: =Ringkasan!F86 | G87: =Ringkasan!G86 -> 0 | H87: =Ringkasan!H86 -> 35.1 | ... AB87: =Ringkasan!AB86 -> Energy
A88: =Ringkasan!A87 -> ALKA | B88: =Ringkasan!B87 -> Alakasa Industrindo Tbk | C88: =Ringkasan!C87 -> 605 | D88: =Ringkasan!D87 -> #N/A | E88: =Ringkasan!E87 | F88: =Ringkasan!F87 | G88: =Ringkasan!G87 -> 0 | H88: =Ringkasan!H87 -> 16.7 | ... AB88: =Ringkasan!AB87 -> Basic Materials
A89: =Ringkasan!A393 -> BOBA | B89: =Ringkasan!B393 -> Formosa Ingredient Factory Tbk. | C89: =Ringkasan!C393 -> 336 | D89: =Ringkasan!D393 -> #N/A | E89: =Ringkasan!E393 | F89: =Ringkasan!F393 | G89: =Ringkasan!G393 -> 0 | H89: =Ringkasan!H393 -> 17.4 | ... AB89: =Ringkasan!AB393 -> Consumer Non-Cyclicals
A90: =Ringkasan!A89 -> ALTO | B90: =Ringkasan!B89 -> Tri Banyan Tirta Tbk. | C90: =Ringkasan!C89 -> 18 | D90: =Ringkasan!D89 -> #N/A | E90: =Ringkasan!E89 | F90: =Ringkasan!F89 | G90: =Ringkasan!G89 -> 0 | H90: =Ringkasan!H89 -> 0 | ... AB90: =Ringkasan!AB89 -> Consumer Non-Cyclicals
A91: =Ringkasan!A90 -> AMAG | B91: =Ringkasan!B90 -> Asuransi Multi Artha Guna Tbk. | C91: =Ringkasan!C90 -> 390 | D91: =Ringkasan!D90 -> #N/A | E91: =Ringkasan!E90 | F91: =Ringkasan!F90 | G91: =Ringkasan!G90 -> 0 | H91: =Ringkasan!H90 -> 9.6 | ... AB91: =Ringkasan!AB90 -> Financials
A92: =Ringkasan!A91 -> AMAN | B92: =Ringkasan!B91 -> Makmur Berkah Amanda Tbk. | C92: =Ringkasan!C91 -> 250 | D92: =Ringkasan!D91 -> #N/A | E92: =Ringkasan!E91 | F92: =Ringkasan!F91 | G92: =Ringkasan!G91 -> 0 | H92: =Ringkasan!H91 -> 22.2 | ... AB92: =Ringkasan!AB91 -> Properties & Real Estate
A93: =Ringkasan!A92 -> AMAR | B93: =Ringkasan!B92 -> Bank Amar Indonesia Tbk. | C93: =Ringkasan!C92 -> 198 | D93: =Ringkasan!D92 -> #N/A | E93: =Ringkasan!E92 | F93: =Ringkasan!F92 | G93: =Ringkasan!G92 -> 0 | H93: =Ringkasan!H92 -> 14.1 | ... AB93: =Ringkasan!AB92 -> Financials
A94: =Ringkasan!A93 -> AMFG | B94: =Ringkasan!B93 -> Asahimas Flat Glass Tbk. | C94: =Ringkasan!C93 -> 3190 | D94: =Ringkasan!D93 -> #N/A | E94: =Ringkasan!E93 | F94: =Ringkasan!F93 | G94: =Ringkasan!G93 -> 0 | H94: =Ringkasan!H93 -> 53.1 | ... AB94: =Ringkasan!AB93 -> Industrials
A95: =Ringkasan!A94 -> AMIN | B95: =Ringkasan!B94 -> PT Ateliers Mecaniques D Indonesie Tbk. | C95: =Ringkasan!C94 -> 260 | D95: =Ringkasan!D94 -> #N/A | E95: =Ringkasan!E94 | F95: =Ringkasan!F94 | G95: =Ringkasan!G94 -> 0 | H95: =Ringkasan!H94 -> 11.5 | ... AB95: =Ringkasan!AB94 -> Industrials
A96: =Ringkasan!A95 -> AMMN | B96: =Ringkasan!B95 -> PT Amman Mineral Internasional Tbk. | C96: =Ringkasan!C95 -> 3450 | D96: =Ringkasan!D95 -> #N/A | E96: =Ringkasan!E95 -> IDX80 | F96: =Ringkasan!F95 -> 31 Juli 2026 | G96: =Ringkasan!G95 -> 5 | H96: =Ringkasan!H95 -> 26 | ... AB96: =Ringkasan!AB95 -> Basic Materials
A97: =Ringkasan!A96 -> AMMN | B97: =Ringkasan!B96 -> PT Amman Mineral Internasional Tbk. | C97: =Ringkasan!C96 -> 3450 | D97: =Ringkasan!D96 -> #N/A | E97: =Ringkasan!E96 -> LQ45 | F97: =Ringkasan!F96 -> 31 Juli 2026 | G97: =Ringkasan!G96 -> 5 | H97: =Ringkasan!H96 -> 26 | ... AB97: =Ringkasan!AB96 -> Basic Materials
A98: =Ringkasan!A410 -> BRIS | B98: =Ringkasan!B410 -> Bank Syariah Indonesia (Persero) Tbk. | C98: =Ringkasan!C410 -> #N/A | D98: =Ringkasan!D410 -> #N/A | E98: =Ringkasan!E410 -> FTSE Large Cap | F98: =Ringkasan!F410 -> Juni 2026 | G98: =Ringkasan!G410 -> 13 | H98: =Ringkasan!H410 -> 11.6 | ... AB98: =Ringkasan!AB410 -> Financials
A99: =Ringkasan!A98 -> AMMN | B99: =Ringkasan!B98 -> PT Amman Mineral Internasional Tbk. | C99: =Ringkasan!C98 -> 3450 | D99: =Ringkasan!D98 -> #N/A | E99: =Ringkasan!E98 -> ECONOMIC30 | F99: =Ringkasan!F98 -> 31 Agustus 2026 | G99: =Ringkasan!G98 -> 5 | H99: =Ringkasan!H98 -> 26 | ... AB99: =Ringkasan!AB98 -> Basic Materials
A100: =Ringkasan!A99 -> AMMN | B100: =Ringkasan!B99 -> PT Amman Mineral Internasional Tbk. | C100: =Ringkasan!C99 -> 3450 | D100: =Ringkasan!D99 -> #N/A | E100: =Ringkasan!E99 -> FTSE Large Cap | F100: =Ringkasan!F99 -> Juni 2026 | G100: =Ringkasan!G99 -> 5 | H100: =Ringkasan!H99 -> 26 | ... AB100: =Ringkasan!AB99 -> Basic Materials
A101: =Ringkasan!A100 -> AMMS | B101: =Ringkasan!B100 -> Agung Menjangan Mas Tbk. | C101: =Ringkasan!C100 -> 328 | D101: =Ringkasan!D100 -> #N/A | E101: =Ringkasan!E100 | F101: =Ringkasan!F100 | G101: =Ringkasan!G100 -> 0 | H101: =Ringkasan!H100 -> -1020 | ... AB101: =Ringkasan!AB100 -> Consumer Non-Cyclicals
A102: =Ringkasan!A431 -> BRPT | B102: =Ringkasan!B431 -> Barito Pacific Tbk. | C102: =Ringkasan!C431 -> 1700 | D102: =Ringkasan!D431 -> #N/A | E102: =Ringkasan!E431 -> Pefindo - iGrade | F102: =Ringkasan!F431 -> 30 Juni 2026 | G102: =Ringkasan!G431 -> 10 | H102: =Ringkasan!H431 -> 19.2 | ... AB102: =Ringkasan!AB431 -> Basic Materials
...

Sheet Banking
A1: Kode | B1: Nama Perusahaan | C1: Penutupan | D1: =IFERROR(__xludf.DUMMYFUNCTION("""Last Update: "" & TEXT(NOW() - GOOGLEFINANCE(""IDX:BBCA"",""datadelay"")/1440, ""dddd, yyyymmdd HH:mm"")"),"Last Update: Minggu, 20260614 14:19") -> Last Update: Minggu, 20260614 14:19 | E1: Index | F1: Index Expired | G1: ∑i ≥ 7 | H1: PER ≤ 15 | I1: PBV ≤ 3 | J1: ROE ≥ 12% | K1: ROA ≥ 1% | L1: DER ≤ 1.5 | M1: NPM ≥ 7% | N1: NIM ≥ 3.5% | O1: CAR ≥ 15% | P1: LDR ≥ 75% | Q1: NPL ≤ 3.5% | R1: BOPO ≤ 80% | S1: CIR ≤ 65% | T1: LAR ≤ 11% | U1: Sebelumnya | V1: %Change | W1: Open | X1: High | Y1: Low | Z1: Volume | AA1: Industry | AB1: Sektor
A2: =Ringkasan!A2 -> AADI | B2: =Ringkasan!B2 -> Adaro Andalan Indonesia Tbk. | C2: =Ringkasan!C2 -> 8650 | D2: =Ringkasan!D2 -> #N/A | E2: =Ringkasan!E2 -> IDX80 | F2: =Ringkasan!F2 -> 31 Juli 2026 | G2: =Ringkasan!G2 -> 9 | H2: =Ringkasan!H2 -> 5.5 | ... AB2: =Ringkasan!AB2 -> Energy
A3: =Ringkasan!A3 -> AADI | B3: =Ringkasan!B3 -> Adaro Andalan Indonesia Tbk. | C3: =Ringkasan!C3 -> 8650 | D3: =Ringkasan!D3 -> #N/A | E3: =Ringkasan!E3 -> IDX30 | F3: =Ringkasan!F3 -> 31 Juli 2026 | G3: =Ringkasan!G3 -> 9 | H3: =Ringkasan!H3 -> 5.5 | ... AB3: =Ringkasan!AB3 -> Energy
A4: =Ringkasan!A4 -> AADI | B4: =Ringkasan!B4 -> Adaro Andalan Indonesia Tbk. | C4: =Ringkasan!C4 -> 8650 | D4: =Ringkasan!D4 -> #N/A | E4: =Ringkasan!E4 -> LQ45 | F4: =Ringkasan!F4 -> 31 Juli 2026 | G4: =Ringkasan!G4 -> 9 | H4: =Ringkasan!H4 -> 5.5 | ... AB4: =Ringkasan!AB4 -> Energy
A5: =Ringkasan!A5 -> AADI | B5: =Ringkasan!B5 -> Adaro Andalan Indonesia Tbk. | C5: =Ringkasan!C5 -> 8650 | D5: =Ringkasan!D5 -> #N/A | E5: =Ringkasan!E5 -> Kompas100 | F5: =Ringkasan!F5 -> 31 Juli 2026 | G5: =Ringkasan!G5 -> 9 | H5: =Ringkasan!H5 -> 5.5 | ... AB5: =Ringkasan!AB5 -> Energy
A6: =Ringkasan!A6 -> AADI | B6: =Ringkasan!B6 -> Adaro Andalan Indonesia Tbk. | C6: =Ringkasan!C6 -> 8650 | D6: =Ringkasan!D6 -> #N/A | E6: =Ringkasan!E6 -> IDXV30 | F6: =Ringkasan!F6 -> 4 Agustus 2026 | G6: =Ringkasan!G6 -> 9 | H6: =Ringkasan!H6 -> 5.5 | ... AB6: =Ringkasan!AB6 -> Energy
A7: =Ringkasan!A7 -> AADI | B7: =Ringkasan!B7 -> Adaro Andalan Indonesia Tbk. | C7: =Ringkasan!C7 -> 8650 | D7: =Ringkasan!D7 -> #N/A | E7: =Ringkasan!E7 -> MSCI Small Cap | F7: =Ringkasan!F7 -> 12 Agustus 2026 | G7: =Ringkasan!G7 -> 9 | H7: =Ringkasan!H7 -> 5.5 | ... AB7: =Ringkasan!AB7 -> Energy
A8: =Ringkasan!A8 -> AADI | B8: =Ringkasan!B8 -> Adaro Andalan Indonesia Tbk. | C8: =Ringkasan!C8 -> 8650 | D8: =Ringkasan!D8 -> #N/A | E8: =Ringkasan!E8 -> FTSE Small Cap | F8: =Ringkasan!F8 -> 12 Agustus 2026 | G8: =Ringkasan!G8 -> 9 | H8: =Ringkasan!H8 -> 5.5 | ... AB8: =Ringkasan!AB8 -> Energy
A9: =Ringkasan!A33 -> ADMG | B9: =Ringkasan!B33 -> Polychem Indonesia Tbk | C9: =Ringkasan!C33 -> 200 | D9: =Ringkasan!D33 -> #N/A | E9: =Ringkasan!E33 | F9: =Ringkasan!F33 | G9: =Ringkasan!G33 -> 0 | H9: =Ringkasan!H33 -> -250 | ... AB9: =Ringkasan!AB33 -> Basic Materials
A10: =Ringkasan!A67 -> AKPI | B10: =Ringkasan!B67 -> Argha Karya Prima Industry Tbk. | C10: =Ringkasan!C67 -> #N/A | D10: =Ringkasan!D67 -> #N/A | E10: =Ringkasan!E67 | F10: =Ringkasan!F67 | G10: =Ringkasan!G67 -> 0 | H10: =Ringkasan!H67 -> 10.1 | ... AB10: =Ringkasan!AB67 -> Basic Materials
A11: =#REF! -> #REF! | B11: =#REF! -> #REF! | C11: =#REF! -> #REF! | D11: =#REF! -> #REF! | E11: =#REF! -> #REF! | F11: =#REF! -> #REF! | G11: =#REF! -> #REF! | H11: =#REF! -> #REF! | ... AB11: =#REF! -> #REF!
A12: =Ringkasan!A11 -> AALI | B12: =Ringkasan!B11 -> Astra Agro Lestari Tbk | C12: =Ringkasan!C11 -> 6175 | D12: =Ringkasan!D11 -> #N/A | E12: =Ringkasan!E11 -> IDXSMC-LIQ | F12: =Ringkasan!F11 -> 4 Agustus 2026 | G12: =Ringkasan!G11 -> 2 | H12: =Ringkasan!H11 -> 8 | ... AB12: =Ringkasan!AB11 -> Consumer Non-Cyclicals
A13: =Ringkasan!A12 -> AALI | B13: =Ringkasan!B12 -> Astra Agro Lestari Tbk | C13: =Ringkasan!C12 -> 6175 | D13: =Ringkasan!D12 -> #N/A | E13: =Ringkasan!E12 -> Investor33 | F13: =Ringkasan!F12 -> 46356 | G13: =Ringkasan!G12 -> 2 | H13: =Ringkasan!H12 -> 8 | ... AB13: =Ringkasan!AB12 -> Consumer Non-Cyclicals
A14: =Ringkasan!A13 -> ABBA | B14: =Ringkasan!B13 -> Mahaka Media Tbk. | C14: =Ringkasan!C13 -> 35 | D14: =Ringkasan!D13 -> #N/A | E14: =Ringkasan!E13 | F14: =Ringkasan!F13 | G14: =Ringkasan!G13 -> 0 | H14: =Ringkasan!H13 -> -5.5 | ... AB14: =Ringkasan!AB13 -> Consumer Cyclicals
A15: =Ringkasan!A14 -> ABDA | B15: =Ringkasan!B14 -> Asuransi Bina Dana Arta Tbk. | C15: =Ringkasan!C14 -> 3390 | D15: =Ringkasan!D14 -> #N/A | E15: =Ringkasan!E14 | F15: =Ringkasan!F14 | G15: =Ringkasan!G14 -> 0 | H15: =Ringkasan!H14 -> 19.6 | ... AB15: =Ringkasan!AB14 -> Financials
A16: =Ringkasan!A15 -> ABMM | B16: =Ringkasan!B15 -> ABM Investama Tbk | C16: =Ringkasan!C15 -> 2420 | D16: =Ringkasan!D15 -> #N/A | E16: =Ringkasan!E15 | F16: =Ringkasan!F15 | G16: =Ringkasan!G15 -> 0 | H16: =Ringkasan!H15 -> 6.2 | ... AB16: =Ringkasan!AB15 -> Industrials
A17: =Ringkasan!A16 -> ACES | B17: =Ringkasan!B16 -> Aspirasi Hidup Indonesia Tbk. | C17: =Ringkasan!C16 -> 356 | D17: =Ringkasan!D16 -> #N/A | E17: =Ringkasan!E16 -> ESGQKEHATI | F17: =Ringkasan!F16 -> 46356 | G17: =Ringkasan!G16 -> 11 | H17: =Ringkasan!H16 -> 8.6 | ... AB17: =Ringkasan!AB16 -> Consumer Cyclicals
A18: =Ringkasan!A17 -> ACES | B18: =Ringkasan!B17 -> Aspirasi Hidup Indonesia Tbk. | C18: =Ringkasan!C17 -> 356 | D18: =Ringkasan!D17 -> #N/A | E18: =Ringkasan!E17 -> IDXHIDIV20 | F18: =Ringkasan!F17 -> 2 Februari 2027 | G18: =Ringkasan!G17 -> 11 | H18: =Ringkasan!H17 -> 8.6 | ... AB18: =Ringkasan!AB17 -> Consumer Cyclicals
A19: =Ringkasan!A18 -> ACES | B19: =Ringkasan!B18 -> Aspirasi Hidup Indonesia Tbk. | C19: =Ringkasan!C18 -> 356 | D19: =Ringkasan!D18 -> #N/A | E19: =Ringkasan!E18 -> IDX80 | F19: =Ringkasan!F18 -> 31 Juli 2026 | G19: =Ringkasan!G18 -> 11 | H19: =Ringkasan!H18 -> 8.6 | ... AB19: =Ringkasan!AB18 -> Consumer Cyclicals
A20: =Ringkasan!A19 -> ACES | B20: =Ringkasan!B19 -> Aspirasi Hidup Indonesia Tbk. | C20: =Ringkasan!C19 -> 356 | D20: =Ringkasan!D19 -> #N/A | E20: =Ringkasan!E19 -> IDXESGL | F20: =Ringkasan!F19 -> 30 Oktober 2026 | G20: =Ringkasan!G19 -> 11 | H20: =Ringkasan!H19 -> 8.6 | ... AB20: =Ringkasan!AB19 -> Consumer Cyclicals
A21: =Ringkasan!A20 -> ACES | B21: =Ringkasan!B20 -> Aspirasi Hidup Indonesia Tbk. | C21: =Ringkasan!C20 -> 356 | D21: =Ringkasan!D20 -> #N/A | E21: =Ringkasan!E20 -> ECONOMIC30 | F21: =Ringkasan!F20 -> 31 Agustus 2026 | G21: =Ringkasan!G20 -> 11 | H21: =Ringkasan!H20 -> 8.6 | ... AB21: =Ringkasan!AB20 -> Consumer Cyclicals
A22: =Ringkasan!A21 -> ACES | B22: =Ringkasan!B21 -> Aspirasi Hidup Indonesia Tbk. | C22: =Ringkasan!C21 -> 356 | D22: =Ringkasan!D21 -> #N/A | E22: =Ringkasan!E21 -> Kompas100 | F22: =Ringkasan!F21 -> 31 Juli 2026 | G22: =Ringkasan!G21 -> 11 | H22: =Ringkasan!H21 -> 8.6 | ... AB22: =Ringkasan!AB21 -> Consumer Cyclicals
A23: =Ringkasan!A22 -> ACES | B23: =Ringkasan!B22 -> Aspirasi Hidup Indonesia Tbk. | C23: =Ringkasan!C22 -> 356 | D23: =Ringkasan!D22 -> #N/A | E23: =Ringkasan!E22 -> IDXQ30 | F23: =Ringkasan!F22 -> 4 Agustus 2026 | G23: =Ringkasan!G22 -> 11 | H23: =Ringkasan!H22 -> 8.6 | ... AB23: =Ringkasan!AB22 -> Consumer Cyclicals
... A33: =Ringkasan!A32 -> ADMF | B33: =Ringkasan!B32 -> Adira Dinamika Multi Finance Tbk. | C33: =Ringkasan!C32 -> 8200 | D33: =Ringkasan!D32 -> #N/A | E33: =Ringkasan!E32 | F33: =Ringkasan!F32 | G33: =Ringkasan!G32 -> 0 | H33: =Ringkasan!H32 -> 5.9 | ... AB33: =Ringkasan!AB32 -> Financials
A34: =Ringkasan!A112 -> ANDI | B34: =Ringkasan!B112 -> Andira Agro Tbk. | C34: =Ringkasan!C112 -> 18 | D34: =Ringkasan!D112 -> #N/A | E34: =Ringkasan!E112 | F34: =Ringkasan!F112 | G34: =Ringkasan!G112 -> 0 | H34: =Ringkasan!H112 -> -3.7 | ... AB34: =Ringkasan!AB112 -> Consumer Non-Cyclicals
A35: =Ringkasan!A34 -> ADMR | B35: =Ringkasan!B34 -> Alamtri Minerals Indonesia Tbk. | C35: =Ringkasan!C34 -> 1575 | D35: =Ringkasan!D34 -> #N/A | E35: =Ringkasan!E34 -> IDXQ30 | F35: =Ringkasan!F34 -> 4 Agustus 2026 | G35: =Ringkasan!G34 -> 9 | H35: =Ringkasan!H34 -> 12.6 | ... AB35: =Ringkasan!AB34 -> Energy
A36: =Ringkasan!A206 -> AYAM | B36: =Ringkasan!B206 -> Janu Putra Sejahtera Tbk. | C36: =Ringkasan!C206 -> 332 | D36: =Ringkasan!D206 -> #N/A | E36: =Ringkasan!E206 | F36: =Ringkasan!F206 | G36: =Ringkasan!G206 -> 0 | H36: =Ringkasan!H206 -> 640 | ... AB36: =Ringkasan!AB206 -> Consumer Non-Cyclicals
A37: =Ringkasan!A36 -> ADMR | B37: =Ringkasan!B36 -> Alamtri Minerals Indonesia Tbk. | C37: =Ringkasan!C36 -> 1575 | D37: =Ringkasan!D36 -> #N/A | E37: =Ringkasan!E36 -> LQ45 | F37: =Ringkasan!F36 -> 31 Juli 2026 | G37: =Ringkasan!G36 -> 9 | H37: =Ringkasan!H36 -> 12.6 | ... AB37: =Ringkasan!AB36 -> Energy
A38: =Ringkasan!A240 -> BBCA | B38: =Ringkasan!B240 -> Bank Central Asia Tbk. | C38: =Ringkasan!C240 -> #N/A | D38: =Ringkasan!D240 -> #N/A | E38: =Ringkasan!E240 -> SRI-KEHATI | F38: =Ringkasan!F240 -> 46356 | G38: =Ringkasan!G240 -> 21 | H38: =Ringkasan!H240 -> 12.1 | ... AB38: =Ringkasan!AB240 -> Financials
A39: =Ringkasan!A331 -> BIKE | B39: =Ringkasan!B331 -> Sepeda Bersama Indonesia Tbk. | C39: =Ringkasan!C331 -> 510 | D39: =Ringkasan!D331 -> #N/A | E39: =Ringkasan!E331 | F39: =Ringkasan!F331 | G39: =Ringkasan!G331 -> 0 | H39: =Ringkasan!H331 -> -27 | ... AB39: =Ringkasan!AB331 -> Consumer Cyclicals
A40: =Ringkasan!A39 -> ADMR | B40: =Ringkasan!B39 -> Alamtri Minerals Indonesia Tbk. | C40: =Ringkasan!C39 -> 1575 | D40: =Ringkasan!D39 -> #N/A | E40: =Ringkasan!E39 -> IDXSHAGROW | F40: =Ringkasan!F39 -> 46356 | G40: =Ringkasan!G39 -> 9 | H40: =Ringkasan!H39 -> 12.6 | ... AB40: =Ringkasan!AB39 -> Energy
A41: =Ringkasan!A40 -> ADMR | B41: =Ringkasan!B40 -> Alamtri Minerals Indonesia Tbk. | C41: =Ringkasan!C40 -> 1575 | D41: =Ringkasan!D40 -> #N/A | E41: =Ringkasan!E40 -> Investor33 | F41: =Ringkasan!F40 -> 46356 | G41: =Ringkasan!G40 -> 9 | H41: =Ringkasan!H40 -> 12.6 | ... AB41: =Ringkasan!AB40 -> Energy
A42: =Ringkasan!A41 -> ADMR | B42: =Ringkasan!B41 -> Alamtri Minerals Indonesia Tbk. | C42: =Ringkasan!C41 -> 1575 | D42: =Ringkasan!D41 -> #N/A | E42: =Ringkasan!E41 -> JII30 | F42: =Ringkasan!F41 -> 46356 | G42: =Ringkasan!G41 -> 9 | H42: =Ringkasan!H41 -> 12.6 | ... AB42: =Ringkasan!AB41 -> Energy
A43: =Ringkasan!A42 -> ADMR | B43: =Ringkasan!B42 -> Alamtri Minerals Indonesia Tbk. | C43: =Ringkasan!C42 -> 1575 | D43: =Ringkasan!D42 -> #N/A | E43: =Ringkasan!E42 -> JII70 | F43: =Ringkasan!F42 -> 46356 | G43: =Ringkasan!G42 -> 9 | H43: =Ringkasan!H42 -> 12.6 | ... AB43: =Ringkasan!AB42 -> Energy
A44: =Ringkasan!A43 -> ADRO | B44: =Ringkasan!B43 -> Alamtri Resources Indonesia Tbk. | C44: =Ringkasan!C43 -> 2280 | D44: =Ringkasan!D43 -> #N/A | E44: =Ringkasan!E43 -> BISNIS-27 | F44: =Ringkasan!F43 -> 30 Oktober 2026 | G44: =Ringkasan!G43 -> 14 | H44: =Ringkasan!H43 -> 8 | ... AB44: =Ringkasan!AB43 -> Energy
A45: =Ringkasan!A44 -> ADRO | B45: =Ringkasan!B44 -> Alamtri Resources Indonesia Tbk. | C45: =Ringkasan!C44 -> 2280 | D45: =Ringkasan!D44 -> #N/A | E45: =Ringkasan!E44 -> IDX30 | F45: =Ringkasan!F44 -> 31 Juli 2026 | G45: =Ringkasan!G44 -> 14 | H45: =Ringkasan!H44 -> 8 | ... AB45: =Ringkasan!AB44 -> Energy
A46: =Ringkasan!A45 -> ADRO | B46: =Ringkasan!B45 -> Alamtri Resources Indonesia Tbk. | C46: =Ringkasan!C45 -> 2280 | D46: =Ringkasan!D45 -> #N/A | E46: =Ringkasan!E45 -> IDX80 | F46: =Ringkasan!F45 -> 31 Juli 2026 | G46: =Ringkasan!G45 -> 14 | H46: =Ringkasan!H45 -> 8 | ... AB46: =Ringkasan!AB45 -> Energy
A47: =Ringkasan!A46 -> ADRO | B47: =Ringkasan!B46 -> Alamtri Resources Indonesia Tbk. | C47: =Ringkasan!C46 -> 2280 | D47: =Ringkasan!D46 -> #N/A | E47: =Ringkasan!E46 -> IDXG30 | F47: =Ringkasan!F46 -> 4 Agustus 2026 | G47: =Ringkasan!G46 -> 14 | H47: =Ringkasan!H46 -> 8 | ... AB47: =Ringkasan!AB46 -> Energy
A48: =Ringkasan!A47 -> ADRO | B48: =Ringkasan!B47 -> Alamtri Resources Indonesia Tbk. | C48: =Ringkasan!C47 -> 2280 | D48: =Ringkasan!D47 -> #N/A | E48: =Ringkasan!E47 -> IDXHIDIV20 | F48: =Ringkasan!F47 -> 2 Februari 2027 | G48: =Ringkasan!G47 -> 14 | H48: =Ringkasan!H47 -> 8 | ... AB48: =Ringkasan!AB47 -> Energy
A49: =Ringkasan!A48 -> ADRO | B49: =Ringkasan!B48 -> Alamtri Resources Indonesia Tbk. | C49: =Ringkasan!C48 -> 2280 | D49: =Ringkasan!D48 -> #N/A | E49: =Ringkasan!E48 -> Kompas100 | F49: =Ringkasan!F48 -> 31 Juli 2026 | G49: =Ringkasan!G48 -> 14 | H49: =Ringkasan!H48 -> 8 | ... AB49: =Ringkasan!AB48 -> Energy
A50: =Ringkasan!A49 -> ADRO | B50: =Ringkasan!B49 -> Alamtri Resources Indonesia Tbk. | C50: =Ringkasan!C49 -> 2280 | D50: =Ringkasan!D49 -> #N/A | E50: =Ringkasan!E49 -> LQ45 | F50: =Ringkasan!F49 -> 31 Juli 2026 | G50: =Ringkasan!G49 -> 14 | H50: =Ringkasan!H49 -> 8 | ... AB50: =Ringkasan!AB49 -> Energy
A51: =Ringkasan!A50 -> ADRO | B51: =Ringkasan!B50 -> Alamtri Resources Indonesia Tbk. | C51: =Ringkasan!C50 -> 2280 | D51: =Ringkasan!D50 -> #N/A | E51: =Ringkasan!E50 -> IDXV30 | F51: =Ringkasan!F50 -> 4 Agustus 2026 | G51: =Ringkasan!G50 -> 14 | H51: =Ringkasan!H50 -> 8 | ... AB51: =Ringkasan!AB50 -> Energy
... A67: =Ringkasan!A66 -> AKKU | B67: =Ringkasan!B66 -> Anugerah Kagum Karya Utama Tbk. | C67: =Ringkasan!C66 -> 38 | D67: =Ringkasan!D66 -> #N/A | E67: =Ringkasan!E66 | F67: =Ringkasan!F66 | G67: =Ringkasan!G66 -> 0 | H67: =Ringkasan!H66 -> -9.4 | ... AB67: =Ringkasan!AB66 -> Consumer Cyclicals
A68: =Ringkasan!A221 -> BBCA | B68: =Ringkasan!B221 -> Bank Central Asia Tbk. | C68: =Ringkasan!C221 -> #N/A | D68: =Ringkasan!D221 -> #N/A | E68: =Ringkasan!E221 -> ESGQKEHATI | F68: =Ringkasan!F221 -> 46356 | G68: =Ringkasan!G221 -> 21 | H68: =Ringkasan!H221 -> 12.1 | ... AB68: =Ringkasan!AB221 -> Financials
A69: =Ringkasan!A68 -> AKRA | B69: =Ringkasan!B68 -> AKR Corporindo Tbk. | C69: =Ringkasan!C68 -> 1250 | D69: =Ringkasan!D68 -> #N/A | E69: =Ringkasan!E68 -> ESGQKEHATI | F69: =Ringkasan!F68 -> 46356 | G69: =Ringkasan!G68 -> 16 | H69: =Ringkasan!H68 -> 9.7 | ... AB69: =Ringkasan!AB68 -> Energy
A70: =Ringkasan!A395 -> BOLA | B70: =Ringkasan!B395 -> Bali Bintang Sejahtera Tbk. | C70: =Ringkasan!C395 -> 130 | D70: =Ringkasan!D395 -> #N/A | E70: =Ringkasan!E395 | F70: =Ringkasan!F395 | G70: =Ringkasan!G395 -> 0 | H70: =Ringkasan!H395 -> 21.8 | ... AB70: =Ringkasan!AB395 -> Consumer Cyclicals
A71: =Ringkasan!A70 -> AKRA | B71: =Ringkasan!B70 -> AKR Corporindo Tbk. | C71: =Ringkasan!C70 -> 1250 | D71: =Ringkasan!D70 -> #N/A | E71: =Ringkasan!E70 -> LQ45 | F71: =Ringkasan!F70 -> 31 Juli 2026 | G71: =Ringkasan!G70 -> 16 | H71: =Ringkasan!H70 -> 9.7 | ... AB71: =Ringkasan!AB70 -> Energy
A72: =Ringkasan!A71 -> AKRA | B72: =Ringkasan!B71 -> AKR Corporindo Tbk. | C72: =Ringkasan!C71 -> 1250 | D72: =Ringkasan!D71 -> #N/A | E72: =Ringkasan!E71 -> IDX80 | F72: =Ringkasan!F71 -> 31 Juli 2026 | G72: =Ringkasan!G71 -> 16 | H72: =Ringkasan!H71 -> 9.7 | ... AB72: =Ringkasan!AB71 -> Energy
A73: =Ringkasan!A433 -> BRPT | B73: =Ringkasan!B433 -> Barito Pacific Tbk. | C73: =Ringkasan!C433 -> 1700 | D73: =Ringkasan!D433 -> #N/A | E73: =Ringkasan!E433 -> FTSE Large Cap | F73: =Ringkasan!F433 -> Juni 2026 | G73: =Ringkasan!G433 -> 10 | H73: =Ringkasan!H433 -> 19.2 | ... AB73: =Ringkasan!AB433 -> Basic Materials
A74: =Ringkasan!A73 -> AKRA | B74: =Ringkasan!B73 -> AKR Corporindo Tbk. | C74: =Ringkasan!C73 -> 1250 | D74: =Ringkasan!D73 -> #N/A | E74: =Ringkasan!E73 -> SMINFRA18 | F74: =Ringkasan!F73 -> 30 Oktober 2026 | G74: =Ringkasan!G73 -> 16 | H74: =Ringkasan!H73 -> 9.7 | ... AB74: =Ringkasan!AB73 -> Energy
A75: =Ringkasan!A74 -> AKRA | B75: =Ringkasan!B74 -> AKR Corporindo Tbk. | C75: =Ringkasan!C74 -> 1250 | D75: =Ringkasan!D74 -> #N/A | E75: =Ringkasan!E74 -> Kompas100 | F75: =Ringkasan!F74 -> 31 Juli 2026 | G75: =Ringkasan!G74 -> 16 | H75: =Ringkasan!H74 -> 9.7 | ... AB75: =Ringkasan!AB74 -> Energy
A76: =Ringkasan!A75 -> AKRA | B76: =Ringkasan!B75 -> AKR Corporindo Tbk. | C76: =Ringkasan!C75 -> 1250 | D76: =Ringkasan!D75 -> #N/A | E76: =Ringkasan!E75 -> IDXSMC-LIQ | F76: =Ringkasan!F75 -> 4 Agustus 2026 | G76: =Ringkasan!G75 -> 16 | H76: =Ringkasan!H75 -> 9.7 | ... AB76: =Ringkasan!AB75 -> Energy
A77: =Ringkasan!A76 -> AKRA | B77: =Ringkasan!B76 -> AKR Corporindo Tbk. | C77: =Ringkasan!C76 -> 1250 | D77: =Ringkasan!D76 -> #N/A | E77: =Ringkasan!E76 -> IDXQ30 | F77: =Ringkasan!F76 -> 4 Agustus 2026 | G77: =Ringkasan!G76 -> 16 | H77: =Ringkasan!H76 -> 9.7 | ... AB77: =Ringkasan!AB76 -> Energy
A78: =Ringkasan!A77 -> AKRA | B78: =Ringkasan!B77 -> AKR Corporindo Tbk. | C78: =Ringkasan!C77 -> 1250 | D78: =Ringkasan!D77 -> #N/A | E78: =Ringkasan!E77 -> IDXG30 | F78: =Ringkasan!F77 -> 4 Agustus 2026 | G78: =Ringkasan!G77 -> 16 | H78: =Ringkasan!H77 -> 9.7 | ... AB78: =Ringkasan!AB77 -> Energy
A79: =Ringkasan!A78 -> AKRA | B79: =Ringkasan!B78 -> AKR Corporindo Tbk. | C79: =Ringkasan!C78 -> 1250 | D79: =Ringkasan!D78 -> #N/A | E79: =Ringkasan!E78 -> BISNIS-27 | F79: =Ringkasan!F78 -> 30 Oktober 2026 | G79: =Ringkasan!G78 -> 16 | H79: =Ringkasan!H78 -> 9.7 | ... AB79: =Ringkasan!AB78 -> Energy
A80: =Ringkasan!A79 -> AKRA | B80: =Ringkasan!B79 -> AKR Corporindo Tbk. | C80: =Ringkasan!C79 -> 1250 | D80: =Ringkasan!D79 -> #N/A | E80: =Ringkasan!E79 -> MSCI Small Cap | F80: =Ringkasan!F79 -> 12 Agustus 2026 | G80: =Ringkasan!G79 -> 16 | H80: =Ringkasan!H79 -> 9.7 | ... AB80: =Ringkasan!AB79 -> Energy
A81: =Ringkasan!A80 -> AKRA | B81: =Ringkasan!B80 -> AKR Corporindo Tbk. | C81: =Ringkasan!C80 -> 1250 | D81: =Ringkasan!D80 -> #N/A | E81: =Ringkasan!E80 -> ESGSKEHATI | F81: =Ringkasan!F80 -> 46356 | G81: =Ringkasan!G80 -> 16 | H81: =Ringkasan!H80 -> 9.7 | ... AB81: =Ringkasan!AB80 -> Energy
A82: =Ringkasan!A81 -> AKRA | B82: =Ringkasan!B81 -> AKR Corporindo Tbk. | C82: =Ringkasan!C81 -> 1250 | D82: =Ringkasan!D81 -> #N/A | E82: =Ringkasan!E81 -> SRI-KEHATI | F82: =Ringkasan!F81 -> 46356 | G82: =Ringkasan!G81 -> 16 | H82: =Ringkasan!H81 -> 9.7 | ... AB82: =Ringkasan!AB81 -> Energy
A83: =Ringkasan!A82 -> AKRA | B83: =Ringkasan!B82 -> AKR Corporindo Tbk. | C83: =Ringkasan!C82 -> 1250 | D83: =Ringkasan!D82 -> #N/A | E83: =Ringkasan!E82 -> Investor33 | F83: =Ringkasan!F82 -> 46356 | G83: =Ringkasan!G82 -> 16 | H83: =Ringkasan!H82 -> 9.7 | ... AB83: =Ringkasan!AB82 -> Energy
A84: =Ringkasan!A83 -> AKRA | B84: =Ringkasan!B83 -> AKR Corporindo Tbk. | C84: =Ringkasan!C83 -> 1250 | D84: =Ringkasan!D83 -> #N/A | E84: =Ringkasan!E83 -> JII70 | F84: =Ringkasan!F83 -> 46356 | G84: =Ringkasan!G83 -> 16 | H84: =Ringkasan!H83 -> 9.7 | ... AB84: =Ringkasan!AB83 -> Energy
A85: =Ringkasan!A84 -> AKSI | B85: =Ringkasan!B84 -> PT Maming Enam Sembilan Mineral Tbk. | C85: =Ringkasan!C84 -> 183 | D85: =Ringkasan!D84 -> #N/A | E85: =Ringkasan!E84 | F85: =Ringkasan!F84 | G85: =Ringkasan!G84 -> 0 | H85: =Ringkasan!H84 -> -16.7 | ... AB85: =Ringkasan!AB84 -> Transportation & Logistic
... A112: =Ringkasan!A111 -> AMRT | B112: =Ringkasan!B111 -> Sumber Alfaria Trijaya Tbk. | C112: =Ringkasan!C111 -> 1375 | D112: =Ringkasan!D111 -> #N/A | E112: =Ringkasan!E111 -> Investor33 | F112: =Ringkasan!F111 -> 46356 | G112: =Ringkasan!G111 -> 10 | H112: =Ringkasan!H111 -> 13.6 | ... AB112: =Ringkasan!AB111 -> Consumer Non-Cyclicals
A113: =Ringkasan!A580 -> DART | B113: =Ringkasan!B580 -> Duta Anggada Realty Tbk. | C113: =Ringkasan!C580 -> 119 | D113: =Ringkasan!D580 -> #N/A | E113: =Ringkasan!E580 | F113: =Ringkasan!F580 | G113: =Ringkasan!G580 -> 0 | H113: =Ringkasan!H580 -> -1.6 | ... AB113: =Ringkasan!AB580 -> Properties & Real Estate
